Workbook

Sheet 2.2.Brecha Efectiva x UdM
A1: Cuadro 2.2.1. Brecha Efectiva por UdM, 2024 - 2033, en millones de pesos, (sin ajustes)
A2: JURISDICCIÓN | B2: SECTOR | C2: Unidad de Medida (UdM) | D2: Brecha x UdM (millones $) META 2053 | E2: Plazo (Años) META 2053 | F2: Brecha x UdM (millones $) META 2033 | G2: (%) de la Brecha cubierto en 2033 | H2: 2024 | I2: 2025 | J2: 2026 | K2: 2027 | L2: 2028 | M2: 2029 | N2: 2030 | O2: 2031 | P2: 2032 | Q2: 2033 | R2: 2034 | S2: 2035 | T2: 2036 | U2: 2037 | V2: 2038 | W2: 2039 | X2: 2040 | Y2: 2041 | Z2: 2042 | AA2: 2043 | AB2: 2044 | AC2: 2045 | AD2: 2046 | AE2: 2047 | AF2: 2048 | AG2: 2049 | AH2: 2050 | AI2: 2051 | AJ2: 2052 | AK2: 2053
A3: Nombre Jurisdicción | B3: Nombre Sector | C3: Nombre UdM 1 | D3: =SUM(H3:AK3) -> 17996390400 | E3: =COUNTIF(H3:AK3,">0") -> 10 | F3: =SUM(H3:Q3) -> 17996390400 | G3: =IFERROR(F3/D3,0) -> 1 | H3: 3944448000 | I3: 3944448000 | J3: 2428928000 | K3: 1910886400 | L3: 1000000000 | M3: 1000000000 | N3: 1000000000 | O3: 922560000 | P3: 922560000 | Q3: 922560000
A4: Nombre Jurisdicción | B4: Nombre Sector | C4: Nombre UdM 2 | D4: =SUM(H4:AK4) -> 1.009931e+10 | E4: =COUNTIF(H4:AK4,">0") -> 3 | F4: =SUM(H4:Q4) -> 1.009931e+10 | G4: =IFERROR(F4/D4,0) -> 1 | H4: 2.7610423e+09 | I4: 2.9365119e+09 | J4: 4.4017558e+09
A5: Nombre Jurisdicción | B5: Nombre Sector | C5: Nombre UdM 3 | D5: =SUM(H5:AK5) -> 7.5090704e+09 | E5: =COUNTIF(H5:AK5,">0") -> 4 | F5: =SUM(H5:Q5) -> 7.5090704e+09 | G5: =IFERROR(F5/D5,0) -> 1 | H5: 9.0875594e+08 | I5: 6.1241118e+09 | J5: 3.0868853e+08 | K5: 1.6751418e+08
A6: Nombre Jurisdicción | B6: Nombre Sector | D6: =SUM(H6:AK6) -> 0 | E6: =COUNTIF(H6:AK6,">0") -> 0 | F6: =SUM(H6:Q6) -> 0 | G6: =IFERROR(F6/D6,0) -> 0
A7: Nombre Jurisdicción | B7: Nombre Sector | D7: =SUM(H7:AK7) -> 0 | E7: =COUNTIF(H7:AK7,">0") -> 0 | F7: =SUM(H7:Q7) -> 0 | G7: =IFERROR(F7/D7,0) -> 0
A8: Nombre Jurisdicción | B8: Nombre Sector | D8: =SUM(H8:AK8) -> 0 | E8: =COUNTIF(H8:AK8,">0") -> 0 | F8: =SUM(H8:Q8) -> 0 | G8: =IFERROR(F8/D8,0) -> 0
A9: TOTAL | D9: =SUM(D3:D8) -> 3.5604771e+10 | F9: =SUM(F3:F8) -> 3.5604771e+10 | G9: =IFERROR(F9/D9,0) -> 1 | H9: =SUM(H3:H8) -> 7.6142463e+09 | I9: =SUM(I3:I8) -> 1.3005072e+10 | J9: =SUM(J3:J8) -> 7.1393723e+09 | K9: =SUM(K3:K8) -> 2.0784006e+09 | L9: =SUM(L3:L8) -> 1000000000 | M9: =SUM(M3:M8) -> 1000000000 | N9: =SUM(N3:N8) -> 1000000000 | O9: =SUM(O3:O8) -> 922560000 | ... AK9: =SUM(AK3:AK8) -> 0
A11: INSTRUCTIVO
A13: Por favor, completar únicamente la columna C (UdM) y las columnas a partir de H (años de la curva de inversión) que correspondan según la estimación de la jurisdicción. (Ejemplo en Rojo)
A14: Los montos deben ser completados en pesos, ingresando la cifra completa (no en millones). El Excel mostrará, automáticamente, el monto en formato millones.
A15: Por favor, ordenar las UdM de manera que la de mayor monto total quede en primer lugar, y continuar de manera descendente.
A16: Aclaración: Columnas ocultas D y E hacen referencia a casos excepcionales en los que la curva de inversión se extienda más allá de 2033.
A18: AJUSTE DE LA BRECHA EFECTIVA EN FUNCIÓN DEL CRECIMIENTO ESTIMADO DE LA POBLACIÓN (La jurisdicción que lo considere conveniente puede sustituir esta variable de actualización por otra que le resulte más apropiada)
A19: Cuadro 2.2.2 Variable de Actualización e Índice de Actualización - Ejemplo Preestablecido: Evolución de la Población (Actualizar fila 21 cuando esté disponible la proyección poblacional según el censo 2022) | Y19: Estimado | Z19: =(((X21/H21)^(1/17))-1)*100 -> 0.67590777 | AA19: =(((Z21/H21)^(1/19))-1)*100 -> 0.67590777 | AK19: =(((AK21/H21)^(1/30))-1)*100 -> 0.67590777
A20: POBLACIÓN | H20: 2024 | I20: 2025 | J20: 2026 | K20: 2027 | L20: 2028 | M20: 2029 | N20: 2030 | O20: 2031 | P20: 2032 | Q20: 2033 | R20: 2034 | S20: 2035 | T20: 2036 | U20: 2037 | V20: 2038 | W20: 2039 | X20: 2040 | Y20: 2041 | Z20: 2041 | AA20: 2042 | AB20: 2043 | AC20: 2044 | AD20: 2045 | AE20: 2046 | AF20: 2047 | AG20: 2048 | AH20: 2049 | AI20: 2050 | AJ20: 2051 | AK20: 2052
A21: TOTAL (en millones) | H21: 47067641 | I21: 47473760 | J21: 47873268 | K21: 48266524 | L21: 48653385 | M21: 49033678 | N21: 49407265 | O21: 49774276 | P21: 50134861 | Q21: 50488930 | R21: 50836373 | S21: 51177087 | T21: 51511042 | U21: 51838245 | V21: 52158610 | W21: 52472054 | X21: 52778477 | Y21: =X21*(1+(($Z$19)/100)) -> 53135211 | Z21: =Y21*(1+(($Z$19)/100)) -> 53494356 | AA21: =Z21*(1+(($Z$19)/100)) -> 53855928 | AB21: =AA21*(1+(($Z$19)/100)) -> 54219945 | AC21: =AB21*(1+(($Z$19)/100)) -> 54586422 | AD21: =AC21*(1+(($Z$19)/100)) -> 54955375 | AE21: =AD21*(1+(($Z$19)/100)) -> 55326823 | AF21: =AE21*(1+(($Z$19)/100)) -> 55700781 | ... AK21: =AJ21*(1+(($Z$19)/100)) -> 57608830
A22: Indice de Actualización | H22: =(H21/$H$21)*100 -> 100 | I22: =(I21/$H$21)*100 -> 100.86284 | J22: =(J21/$H$21)*100 -> 101.71164 | K22: =(K21/$H$21)*100 -> 102.54715 | L22: =(L21/$H$21)*100 -> 103.36907 | M22: =(M21/$H$21)*100 -> 104.17705 | N22: =(N21/$H$21)*100 -> 104.97077 | O22: =(O21/$H$21)*100 -> 105.75052 | ... AK22: =(AK21/$H$21)*100 -> 122.39583
A24: Cuadro 2.2.3 Brecha Efectiva por UdM, 2024 - 2033, en millones de pesos, ajustada por el índice de actualización
A25: JURISDICCIÓN | B25: SECTOR | C25: Unidad de Medida (UdM) | D25: Brecha x UdM (millones $) META 2053 | E25: Plazo (Años) META 2053 | F25: Brecha x UdM (millones $) META 2033 | G25: (%) de la Brecha cubierto en 2033 | H25: 2024 | I25: 2025 | J25: 2026 | K25: 2027 | L25: 2028 | M25: 2029 | N25: 2030 | O25: 2031 | P25: 2032 | Q25: 2033 | R25: 2034 | S25: 2035 | T25: 2036 | U25: 2037 | V25: 2038 | W25: 2039 | X25: 2040 | Y25: 2041 | Z25: 2042 | AA25: 2043 | AB25: 2044 | AC25: 2045 | AD25: 2046 | AE25: 2047 | AF25: 2048 | AG25: 2049 | AH25: 2050 | AI25: 2051 | AJ25: 2052 | AK25: 2053
A26: =A3 -> Nombre Jurisdicción | B26: =B3 -> Nombre Sector | C26: =C3 -> Nombre UdM 1 | D26: =SUM(H26:AK26) -> 1.8426073e+10 | E26: =COUNTIF(H26:AK26,">0") -> 10 | F26: =SUM(H26:Q26) -> 1.8426073e+10 | G26: =IFERROR(F26/D26,0) -> 1 | H26: =(H3*H$22)/100 -> 3944448000 | I26: =(I3*I$22)/100 -> 3.9784823e+09 | J26: =(J3*J$22)/100 -> 2.4705024e+09 | K26: =(K3*K$22)/100 -> 1.9595595e+09 | L26: =(L3*L$22)/100 -> 1.0336907e+09 | M26: =(M3*M$22)/100 -> 1.0417705e+09 | N26: =(N3*N$22)/100 -> 1.0497077e+09 | O26: =(O3*O$22)/100 -> 9.7561201e+08 | ... AK26: =(AK3*AK$22)/100 -> 0
A27: =A4 -> Nombre Jurisdicción | B27: =B4 -> Nombre Sector | C27: =C4 -> Nombre UdM 2 | D27: =SUM(H27:AK27) -> 1.0199989e+10 | E27: =COUNTIF(H27:AK27,">0") -> 3 | F27: =SUM(H27:Q27) -> 1.0199989e+10 | G27: =IFERROR(F27/D27,0) -> 1 | H27: =(H4*H$22)/100 -> 2.7610423e+09 | I27: =(I4*I$22)/100 -> 2.9618493e+09 | J27: =(J4*J$22)/100 -> 4.4770978e+09 | K27: =(K4*K$22)/100 -> 0 | L27: =(L4*L$22)/100 -> 0 | M27: =(M4*M$22)/100 -> 0 | N27: =(N4*N$22)/100 -> 0 | O27: =(O4*O$22)/100 -> 0 | ... AK27: =(AK4*AK$22)/100 -> 0
A28: =A5 -> Nombre Jurisdicción | B28: =B5 -> Nombre Sector | C28: =C5 -> Nombre UdM 3 | D28: =SUM(H28:AK28) -> 7.5714622e+09 | E28: =COUNTIF(H28:AK28,">0") -> 4 | F28: =SUM(H28:Q28) -> 7.5714622e+09 | G28: =IFERROR(F28/D28,0) -> 1 | H28: =(H5*H$22)/100 -> 9.0875594e+08 | I28: =(I5*I$22)/100 -> 6.1769531e+09 | J28: =(J5*J$22)/100 -> 3.1397216e+08 | K28: =(K5*K$22)/100 -> 1.7178102e+08 | L28: =(L5*L$22)/100 -> 0 | M28: =(M5*M$22)/100 -> 0 | N28: =(N5*N$22)/100 -> 0 | O28: =(O5*O$22)/100 -> 0 | ... AK28: =(AK5*AK$22)/100 -> 0
A29: =A6 -> Nombre Jurisdicción | B29: =B6 -> Nombre Sector | C29: =C6 -> 0 | D29: =SUM(H29:AK29) -> 0 | E29: =COUNTIF(H29:AK29,">0") -> 0 | F29: =SUM(H29:Q29) -> 0 | G29: =IFERROR(F29/D29,0) -> 0 | H29: =(H6*H$22)/100 -> 0 | I29: =(I6*I$22)/100 -> 0 | J29: =(J6*J$22)/100 -> 0 | K29: =(K6*K$22)/100 -> 0 | L29: =(L6*L$22)/100 -> 0 | M29: =(M6*M$22)/100 -> 0 | N29: =(N6*N$22)/100 -> 0 | O29: =(O6*O$22)/100 -> 0 | ... AK29: =(AK6*AK$22)/100 -> 0
A30: =A7 -> Nombre Jurisdicción | B30: =B7 -> Nombre Sector | C30: =C7 -> 0 | D30: =SUM(H30:AK30) -> 0 | E30: =COUNTIF(H30:AK30,">0") -> 0 | F30: =SUM(H30:Q30) -> 0 | G30: =IFERROR(F30/D30,0) -> 0 | H30: =(H7*H$22)/100 -> 0 | I30: =(I7*I$22)/100 -> 0 | J30: =(J7*J$22)/100 -> 0 | K30: =(K7*K$22)/100 -> 0 | L30: =(L7*L$22)/100 -> 0 | M30: =(M7*M$22)/100 -> 0 | N30: =(N7*N$22)/100 -> 0 | O30: =(O7*O$22)/100 -> 0 | ... AK30: =(AK7*AK$22)/100 -> 0
A31: =A8 -> Nombre Jurisdicción | B31: =B8 -> Nombre Sector | C31: =C8 -> 0 | D31: =SUM(H31:AK31) -> 0 | E31: =COUNTIF(H31:AK31,">0") -> 0 | F31: =SUM(H31:Q31) -> 0 | G31: =IFERROR(F31/D31,0) -> 0 | H31: =(H8*H$22)/100 -> 0 | I31: =(I8*I$22)/100 -> 0 | J31: =(J8*J$22)/100 -> 0 | K31: =(K8*K$22)/100 -> 0 | L31: =(L8*L$22)/100 -> 0 | M31: =(M8*M$22)/100 -> 0 | N31: =(N8*N$22)/100 -> 0 | O31: =(O8*O$22)/100 -> 0 | ... AK31: =(AK8*AK$22)/100 -> 0
A32: TOTAL | D32: =SUM(D26:D28) -> 3.6197524e+10 | F32: =SUM(F26:F28) -> 3.6197524e+10 | G32: =IFERROR(F32/D32,0) -> 1 | H32: =SUM(H26:H28) -> 7.6142463e+09 | I32: =SUM(I26:I28) -> 1.3117285e+10 | J32: =SUM(J26:J28) -> 7.2615724e+09 | K32: =SUM(K26:K28) -> 2.1313405e+09 | L32: =SUM(L26:L28) -> 1.0336907e+09 | M32: =SUM(M26:M28) -> 1.0417705e+09 | N32: =SUM(N26:N28) -> 1.0497077e+09 | O32: =SUM(O26:O28) -> 9.7561201e+08 | ... AK32: =SUM(AK26:AK28) -> 0
A33: Nota: Debe tenerse en cuenta que, implícitamente, el ajuste de este valor en función del crecimiento de la población supone, como contracara, una variación en las metas físicas de igual proporción.
A35: COSTO DE REPOSICIÓN EN LAS UDM DURANTE EL AVANCE DE LA BRECHA EFECTIVA
A36: Cuadro 2.2.4. Inversiones de Reposición de las UdMs durante el Avance de la Brecha Efectiva por UdM, 2024 - 2033, en millones de pesos, (sin ajustes)
A37: JURISDICCIÓN | B37: SECTOR | C37: Unidad de Medida (UdM) | H37: 2024 | I37: 2025 | J37: 2026 | K37: 2027 | L37: 2028 | M37: 2029 | N37: 2030 | O37: 2031 | P37: 2032 | Q37: 2033 | R37: 2034 | S37: 2035 | T37: 2036 | U37: 2037 | V37: 2038 | W37: 2039 | X37: 2040 | Y37: 2041 | Z37: 2042 | AA37: 2043 | AB37: 2044 | AC37: 2045 | AD37: 2046 | AE37: 2047 | AF37: 2048 | AG37: 2049 | AH37: 2050 | AI37: 2051 | AJ37: 2052 | AK37: 2053
A38: =A3 -> Nombre Jurisdicción | B38: =B3 -> Nombre Sector | C38: =C3 -> Nombre UdM 1 | H38: 394444800 | I38: 394444800 | J38: 242892800 | K38: 191088640 | L38: 100000000 | M38: 100000000 | N38: 100000000 | O38: 92256000 | P38: 92256000 | Q38: 92256000 | R38: =R3*0.1 -> 0 | S38: =S3*0.1 -> 0 | T38: =T3*0.1 -> 0 | U38: =U3*0.1 -> 0 | V38: =V3*0.1 -> 0 | W38: =W3*0.1 -> 0 | X38: =X3*0.1 -> 0 | Y38: =Y3*0.1 -> 0 | ... AK38: =AK3*0.1 -> 0
A39: =A4 -> Nombre Jurisdicción | B39: =B4 -> Nombre Sector | C39: =C4 -> Nombre UdM 2 | H39: 2.7610423e+08 | I39: 2.9365119e+08 | J39: 4.4017558e+08 | K39: 0 | L39: 0 | M39: 0 | N39: 0 | O39: 0 | P39: 0 | Q39: 0 | R39: =R4*0.1 -> 0 | S39: =S4*0.1 -> 0 | T39: =T4*0.1 -> 0 | U39: =U4*0.1 -> 0 | V39: =V4*0.1 -> 0 | W39: =W4*0.1 -> 0 | X39: =X4*0.1 -> 0 | Y39: =Y4*0.1 -> 0 | ... AK39: =AK4*0.1 -> 0
A40: =A5 -> Nombre Jurisdicción | B40: =B5 -> Nombre Sector | C40: =C5 -> Nombre UdM 3 | H40: 90875594 | I40: 6.1241118e+08 | J40: 30868853 | K40: 16751418 | L40: 0 | M40: 0 | N40: 0 | O40: 0 | P40: 0 | Q40: 0 | R40: =R5*0.1 -> 0 | S40: =S5*0.1 -> 0 | T40: =T5*0.1 -> 0 | U40: =U5*0.1 -> 0 | V40: =V5*0.1 -> 0 | W40: =W5*0.1 -> 0 | X40: =X5*0.1 -> 0 | Y40: =Y5*0.1 -> 0 | ... AK40: =AK5*0.1 -> 0
A41: =A6 -> Nombre Jurisdicción | B41: =B6 -> Nombre Sector | C41: =C6 -> 0 | H41: =H6*0.1 -> 0 | I41: =I6*0.1 -> 0 | J41: =J6*0.1 -> 0 | K41: =K6*0.1 -> 0 | L41: =L6*0.1 -> 0 | M41: =M6*0.1 -> 0 | N41: =N6*0.1 -> 0 | O41: =O6*0.1 -> 0 | ... AK41: =AK6*0.1 -> 0
A42: =A7 -> Nombre Jurisdicción | B42: =B7 -> Nombre Sector | C42: =C7 -> 0 | H42: =H7*0.1 -> 0 | I42: =I7*0.1 -> 0 | J42: =J7*0.1 -> 0 | K42: =K7*0.1 -> 0 | L42: =L7*0.1 -> 0 | M42: =M7*0.1 -> 0 | N42: =N7*0.1 -> 0 | O42: =O7*0.1 -> 0 | ... AK42: =AK7*0.1 -> 0
A43: =A8 -> Nombre Jurisdicción | B43: =B8 -> Nombre Sector | C43: =C8 -> 0 | H43: =H8*0.1 -> 0 | I43: =I8*0.1 -> 0 | J43: =J8*0.1 -> 0 | K43: =K8*0.1 -> 0 | L43: =L8*0.1 -> 0 | M43: =M8*0.1 -> 0 | N43: =N8*0.1 -> 0 | O43: =O8*0.1 -> 0 | ... AK43: =AK8*0.1 -> 0
A44: TOTAL | H44: =SUM(H38:H40) -> 7.6142463e+08 | I44: =SUM(I38:I40) -> 1.3005072e+09 | J44: =SUM(J38:J40) -> 7.1393723e+08 | K44: =SUM(K38:K40) -> 2.0784006e+08 | L44: =SUM(L38:L40) -> 100000000 | M44: =SUM(M38:M40) -> 100000000 | N44: =SUM(N38:N40) -> 100000000 | O44: =SUM(O38:O40) -> 92256000 | ... AK44: =SUM(AK38:AK40) -> 0
A46: INSTRUCTIVO
A48: Por favor, completar únicamente las columnas a partir de H (años de la curva de inversión) que correspondan según la estimación de la jurisdicción. Completar ÚNICAMENTE los montos estimados por Reposiciones de bienes de capital que se planea que tengan lugar durante el lapso de tiempo comprendido entre los años estimados para cerrar la brecha de cada UdM. No deben incluirse otros gastos de mantenimiento de la jurisdicción (aquellos que no están relacionados con ampliación o reposición, y que no se vinculan con las actividades derivadas del cierre de la brecha). En el ejemplo en rojo, se realizó el supuesto de un costo de mantenimiento de 10% anual, a fines ilustrativos, pero las jurisdicciones deberían realizar una estimación más afinada.
A49: Los montos deben ser completados en pesos, ingresando la cifra completa (no en millones). El Excel mostrará, automáticamente, el monto en formato millones.
A51: AJUSTE DEL COSTO DE REPOSICIÓN EN LAS UDMs DURANTE EL AVANCE DE LA BRECHA EFECTIVA, EN FUNCIÓN DEL CRECIMIENTO ESTIMADO DE LA POBLACIÓN. (o índice de actualización alternativo)
A52: Cuadro 2.2.5. Inversiones de Reposición de las UdMs durante el Avance de la Brecha Efectiva por UdM, 2024 - 2033, en millones de pesos, ajustado por el Índice de Actualización (i.e. Poblacional)
A53: JURISDICCIÓN | B53: SECTOR | C53: Unidad de Medida (UdM) | H53: 2024 | I53: 2025 | J53: 2026 | K53: 2027 | L53: 2028 | M53: 2029 | N53: 2030 | O53: 2031 | P53: 2032 | Q53: 2033 | R53: 2034 | S53: 2035 | T53: 2036 | U53: 2037 | V53: 2038 | W53: 2039 | X53: 2040 | Y53: 2041 | Z53: 2042 | AA53: 2043 | AB53: 2044 | AC53: 2045 | AD53: 2046 | AE53: 2047 | AF53: 2048 | AG53: 2049 | AH53: 2050 | AI53: 2051 | AJ53: 2052 | AK53: 2053
A54: =A38 -> Nombre Jurisdicción | B54: =B38 -> Nombre Sector | C54: =C38 -> Nombre UdM 1 | H54: =(H38*(H$22/100)) -> 394444800 | I54: =(I38*(I$22/100)) -> 3.9784823e+08 | J54: =(J38*(J$22/100)) -> 2.4705024e+08 | K54: =(K38*(K$22/100)) -> 1.9595595e+08 | L54: =(L38*(L$22/100)) -> 1.0336907e+08 | M54: =(M38*(M$22/100)) -> 1.0417705e+08 | N54: =(N38*(N$22/100)) -> 1.0497077e+08 | O54: =(O38*(O$22/100)) -> 97561201 | ... AK54: =(AK38*(AK$22/100)) -> 0
A55: =A39 -> Nombre Jurisdicción | B55: =B39 -> Nombre Sector | C55: =C39 -> Nombre UdM 2 | H55: =(H39*(H$22/100)) -> 2.7610423e+08 | I55: =(I39*(I$22/100)) -> 2.9618493e+08 | J55: =(J39*(J$22/100)) -> 4.4770978e+08 | K55: =(K39*(K$22/100)) -> 0 | L55: =(L39*(L$22/100)) -> 0 | M55: =(M39*(M$22/100)) -> 0 | N55: =(N39*(N$22/100)) -> 0 | O55: =(O39*(O$22/100)) -> 0 | ... AK55: =(AK39*(AK$22/100)) -> 0
A56: =A40 -> Nombre Jurisdicción | B56: =B40 -> Nombre Sector | C56: =C40 -> Nombre UdM 3 | H56: =(H40*(H$22/100)) -> 90875594 | I56: =(I40*(I$22/100)) -> 6.1769531e+08 | J56: =(J40*(J$22/100)) -> 31397216 | K56: =(K40*(K$22/100)) -> 17178102 | L56: =(L40*(L$22/100)) -> 0 | M56: =(M40*(M$22/100)) -> 0 | N56: =(N40*(N$22/100)) -> 0 | O56: =(O40*(O$22/100)) -> 0 | ... AK56: =(AK40*(AK$22/100)) -> 0
A57: =A41 -> Nombre Jurisdicción | B57: =B41 -> Nombre Sector | C57: =C41 -> 0 | H57: =(H41*(H$22/100)) -> 0 | I57: =(I41*(I$22/100)) -> 0 | J57: =(J41*(J$22/100)) -> 0 | K57: =(K41*(K$22/100)) -> 0 | L57: =(L41*(L$22/100)) -> 0 | M57: =(M41*(M$22/100)) -> 0 | N57: =(N41*(N$22/100)) -> 0 | O57: =(O41*(O$22/100)) -> 0 | ... AK57: =(AK41*(AK$22/100)) -> 0
A58: =A42 -> Nombre Jurisdicción | B58: =B42 -> Nombre Sector | C58: =C42 -> 0 | H58: =(H42*(H$22/100)) -> 0 | I58: =(I42*(I$22/100)) -> 0 | J58: =(J42*(J$22/100)) -> 0 | K58: =(K42*(K$22/100)) -> 0 | L58: =(L42*(L$22/100)) -> 0 | M58: =(M42*(M$22/100)) -> 0 | N58: =(N42*(N$22/100)) -> 0 | O58: =(O42*(O$22/100)) -> 0 | ... AK58: =(AK42*(AK$22/100)) -> 0
A59: =A43 -> Nombre Jurisdicción | B59: =B43 -> Nombre Sector | C59: =C43 -> 0 | H59: =(H43*(H$22/100)) -> 0 | I59: =(I43*(I$22/100)) -> 0 | J59: =(J43*(J$22/100)) -> 0 | K59: =(K43*(K$22/100)) -> 0 | L59: =(L43*(L$22/100)) -> 0 | M59: =(M43*(M$22/100)) -> 0 | N59: =(N43*(N$22/100)) -> 0 | O59: =(O43*(O$22/100)) -> 0 | ... AK59: =(AK43*(AK$22/100)) -> 0
A60: TOTAL | H60: =SUM(H54:H56) -> 7.6142463e+08 | I60: =SUM(I54:I56) -> 1.3117285e+09 | J60: =SUM(J54:J56) -> 7.2615724e+08 | K60: =SUM(K54:K56) -> 2.1313405e+08 | L60: =SUM(L54:L56) -> 1.0336907e+08 | M60: =SUM(M54:M56) -> 1.0417705e+08 | N60: =SUM(N54:N56) -> 1.0497077e+08 | O60: =SUM(O54:O56) -> 97561201 | ... AK60: =SUM(AK54:AK56) -> 0
A62: UDMs AJUSTADAS POR EL CRECIMIENTO DE LA POBLACIÓN Y POR EL COSTO DE REPOSICIÓN DURANTE EL AVANCE DE LA BRECHA EFECTIVA (éste último también ajustada por el crecimiento de la población)
A63: Cuadro 2.2.6. Subtotal de la Brecha Efectiva por UdM, 2024 - 2033, en millones de pesos, ajustada por el Índice de Actualización (i.e. Poblacional) y por el costo de Reposición durante el Avance de la Brecha
A64: JURISDICCIÓN | B64: SECTOR | C64: Unidad de Medida (UdM) | D64: Brecha x UdM (millones $) META 2053 | E64: Plazo (Años) META 2053 | F64: Brecha x UdM (millones $) META 2033 | G64: (%) de la Brecha cubierto en 2033 | H64: 2024 | I64: 2025 | J64: 2026 | K64: 2027 | L64: 2028 | M64: 2029 | N64: 2030 | O64: 2031 | P64: 2032 | Q64: 2033 | R64: 2034 | S64: 2035 | T64: 2036 | U64: 2037 | V64: 2038 | W64: 2039 | X64: 2040 | Y64: 2041 | Z64: 2042 | AA64: 2043 | AB64: 2044 | AC64: 2045 | AD64: 2046 | AE64: 2047 | AF64: 2048 | AG64: 2049 | AH64: 2050 | AI64: 2051 | AJ64: 2052 | AK64: 2053
A65: =A3 -> Nombre Jurisdicción | B65: =B3 -> Nombre Sector | C65: =C3 -> Nombre UdM 1 | D65: =SUM(H65:AK65) -> 2.026868e+10 | E65: =COUNTIF(H65:AK65,">0") -> 10 | F65: =SUM(H65:Q65) -> 2.026868e+10 | G65: =IFERROR(F65/D65,0) -> 1 | H65: =SUM(H54,H26) -> 4338892800 | I65: =SUM(I54,I26) -> 4.3763306e+09 | J65: =SUM(J54,J26) -> 2.7175527e+09 | K65: =SUM(K54,K26) -> 2.1555155e+09 | L65: =SUM(L54,L26) -> 1.1370598e+09 | M65: =SUM(M54,M26) -> 1.1459475e+09 | N65: =SUM(N54,N26) -> 1.1546785e+09 | O65: =SUM(O54,O26) -> 1.0731732e+09 | ... AK65: =SUM(AK54,AK26) -> 0
A66: =A4 -> Nombre Jurisdicción | B66: =B4 -> Nombre Sector | C66: =C4 -> Nombre UdM 2 | D66: =SUM(H66:AK66) -> 1.1219988e+10 | E66: =COUNTIF(H66:AK66,">0") -> 3 | F66: =SUM(H66:Q66) -> 1.1219988e+10 | G66: =IFERROR(F66/D66,0) -> 1 | H66: =SUM(H55,H27) -> 3.0371465e+09 | I66: =SUM(I55,I27) -> 3.2580343e+09 | J66: =SUM(J55,J27) -> 4.9248076e+09 | K66: =SUM(K55,K27) -> 0 | L66: =SUM(L55,L27) -> 0 | M66: =SUM(M55,M27) -> 0 | N66: =SUM(N55,N27) -> 0 | O66: =SUM(O55,O27) -> 0 | ... AK66: =SUM(AK55,AK27) -> 0
A67: =A5 -> Nombre Jurisdicción | B67: =B5 -> Nombre Sector | C67: =C5 -> Nombre UdM 3 | D67: =SUM(H67:AK67) -> 8.3286085e+09 | E67: =COUNTIF(H67:AK67,">0") -> 4 | F67: =SUM(H67:Q67) -> 8.3286085e+09 | G67: =IFERROR(F67/D67,0) -> 1 | H67: =SUM(H56,H28) -> 9.9963154e+08 | I67: =SUM(I56,I28) -> 6.7946484e+09 | J67: =SUM(J56,J28) -> 3.4536937e+08 | K67: =SUM(K56,K28) -> 1.8895912e+08 | L67: =SUM(L56,L28) -> 0 | M67: =SUM(M56,M28) -> 0 | N67: =SUM(N56,N28) -> 0 | O67: =SUM(O56,O28) -> 0 | ... AK67: =SUM(AK56,AK28) -> 0
A68: =A6 -> Nombre Jurisdicción | B68: =B6 -> Nombre Sector | C68: =C6 -> 0 | D68: =SUM(H68:AK68) -> 0 | E68: =COUNTIF(H68:AK68,">0") -> 0 | F68: =SUM(H68:Q68) -> 0 | G68: =IFERROR(F68/D68,0) -> 0 | H68: =SUM(H57,H29) -> 0 | I68: =SUM(I57,I29) -> 0 | J68: =SUM(J57,J29) -> 0 | K68: =SUM(K57,K29) -> 0 | L68: =SUM(L57,L29) -> 0 | M68: =SUM(M57,M29) -> 0 | N68: =SUM(N57,N29) -> 0 | O68: =SUM(O57,O29) -> 0 | ... AK68: =SUM(AK57,AK29) -> 0
A69: =A7 -> Nombre Jurisdicción | B69: =B7 -> Nombre Sector | C69: =C7 -> 0 | D69: =SUM(H69:AK69) -> 0 | E69: =COUNTIF(H69:AK69,">0") -> 0 | F69: =SUM(H69:Q69) -> 0 | G69: =IFERROR(F69/D69,0) -> 0 | H69: =SUM(H58,H30) -> 0 | I69: =SUM(I58,I30) -> 0 | J69: =SUM(J58,J30) -> 0 | K69: =SUM(K58,K30) -> 0 | L69: =SUM(L58,L30) -> 0 | M69: =SUM(M58,M30) -> 0 | N69: =SUM(N58,N30) -> 0 | O69: =SUM(O58,O30) -> 0 | ... AK69: =SUM(AK58,AK30) -> 0
A70: =A8 -> Nombre Jurisdicción | B70: =B8 -> Nombre Sector | C70: =C8 -> 0 | D70: =SUM(H70:AK70) -> 0 | E70: =COUNTIF(H70:AK70,">0") -> 0 | F70: =SUM(H70:Q70) -> 0 | G70: =IFERROR(F70/D70,0) -> 0 | H70: =SUM(H59,H31) -> 0 | I70: =SUM(I59,I31) -> 0 | J70: =SUM(J59,J31) -> 0 | K70: =SUM(K59,K31) -> 0 | L70: =SUM(L59,L31) -> 0 | M70: =SUM(M59,M31) -> 0 | N70: =SUM(N59,N31) -> 0 | O70: =SUM(O59,O31) -> 0 | ... AK70: =SUM(AK59,AK31) -> 0
A71: TOTAL | D71: =SUM(D65:D67) -> 3.9817277e+10 | F71: =SUM(F65:F67) -> 3.9817277e+10 | G71: =IFERROR(F71/D71,0) -> 1 | H71: =SUM(H65:H67) -> 8.3756709e+09 | I71: =SUM(I65:I67) -> 1.4429013e+10 | J71: =SUM(J65:J67) -> 7.9877296e+09 | K71: =SUM(K65:K67) -> 2.3444746e+09 | L71: =SUM(L65:L67) -> 1.1370598e+09 | M71: =SUM(M65:M67) -> 1.1459475e+09 | N71: =SUM(N65:N67) -> 1.1546785e+09 | O71: =SUM(O65:O67) -> 1.0731732e+09 | ... AK71: =SUM(AK65:AK67) -> 0
A73: Variación % con respecto a la Brecha Efectiva original
A74: Cuadro 2.2.7. Variación porcentual de la Brecha Efectiva Ajustada por Índice de Actualización y por el costo de Reposición, con respecto a la Brecha Efectiva por UdM original, 2024 - 2033
A75: JURISDICCIÓN | B75: SECTOR | C75: Unidad de Medida (UdM) | D75: Brecha x UdM (millones $) META 2053 | E75: Plazo (Años) META 2053 | F75: Brecha x UdM (millones $) META 2033 | G75: (%) de la Brecha cubierto en 2033 | H75: 2024 | I75: 2025 | J75: 2026 | K75: 2027 | L75: 2028 | M75: 2029 | N75: 2030 | O75: 2031 | P75: 2032 | Q75: 2033 | R75: 2034 | S75: 2035 | T75: 2036 | U75: 2037 | V75: 2038 | W75: 2039 | X75: 2040 | Y75: 2041 | Z75: 2042 | AA75: 2043 | AB75: 2044 | AC75: 2045 | AD75: 2046 | AE75: 2047 | AF75: 2048 | AG75: 2049 | AH75: 2050 | AI75: 2051 | AJ75: 2052 | AK75: 2053
A76: =A3 -> Nombre Jurisdicción | B76: =B3 -> Nombre Sector | C76: =C3 -> Nombre UdM 1 | D76: =IFERROR(D65/D3-1,0) -> 0.12626363 | E76: =COUNTIF(H76:AK76,">0") -> 10 | F76: =IFERROR(F65/F3-1,0) -> 0.12626363 | H76: =IFERROR(H65/H3-1,0) -> 0.1 | I76: =IFERROR(I65/I3-1,0) -> 0.10949125 | J76: =IFERROR(J65/J3-1,0) -> 0.118828 | K76: =IFERROR(K65/K3-1,0) -> 0.12801864 | L76: =IFERROR(L65/L3-1,0) -> 0.13705982 | M76: =IFERROR(M65/M3-1,0) -> 0.14594751 | N76: =IFERROR(N65/N3-1,0) -> 0.15467847 | O76: =IFERROR(O65/O3-1,0) -> 0.16325574 | ... AK76: =IFERROR(AK65/AK3-1,0) -> 0
A77: =A4 -> Nombre Jurisdicción | B77: =B4 -> Nombre Sector | C77: =C4 -> Nombre UdM 2 | D77: =IFERROR(D66/D4-1,0) -> 0.11096584 | E77: =COUNTIF(H77:AK77,">0") -> 3 | F77: =IFERROR(F66/F4-1,0) -> 0.11096584 | H77: =IFERROR(H66/H4-1,0) -> 0.1 | I77: =IFERROR(I66/I4-1,0) -> 0.10949125 | J77: =IFERROR(J66/J4-1,0) -> 0.118828 | K77: =IFERROR(K66/K4-1,0) -> 0 | L77: =IFERROR(L66/L4-1,0) -> 0 | M77: =IFERROR(M66/M4-1,0) -> 0 | N77: =IFERROR(N66/N4-1,0) -> 0 | O77: =IFERROR(O66/O4-1,0) -> 0 | ... AK77: =IFERROR(AK66/AK4-1,0) -> 0
A78: =A5 -> Nombre Jurisdicción | B78: =B5 -> Nombre Sector | C78: =C5 -> Nombre UdM 3 | D78: =IFERROR(D67/D5-1,0) -> 0.10913975 | E78: =COUNTIF(H78:AK78,">0") -> 4 | F78: =IFERROR(F67/F5-1,0) -> 0.10913975 | H78: =IFERROR(H67/H5-1,0) -> 0.1 | I78: =IFERROR(I67/I5-1,0) -> 0.10949125 | J78: =IFERROR(J67/J5-1,0) -> 0.118828 | K78: =IFERROR(K67/K5-1,0) -> 0.12801864 | L78: =IFERROR(L67/L5-1,0) -> 0 | M78: =IFERROR(M67/M5-1,0) -> 0 | N78: =IFERROR(N67/N5-1,0) -> 0 | O78: =IFERROR(O67/O5-1,0) -> 0 | ... AK78: =IFERROR(AK67/AK5-1,0) -> 0
A79: =A6 -> Nombre Jurisdicción | B79: =B6 -> Nombre Sector | C79: =C6 -> 0 | D79: =IFERROR(D68/D6-1,0) -> 0 | E79: =COUNTIF(H79:AK79,">0") -> 0 | F79: =IFERROR(F68/F6-1,0) -> 0 | H79: =IFERROR(H68/H6-1,0) -> 0 | I79: =IFERROR(I68/I6-1,0) -> 0 | J79: =IFERROR(J68/J6-1,0) -> 0 | K79: =IFERROR(K68/K6-1,0) -> 0 | L79: =IFERROR(L68/L6-1,0) -> 0 | M79: =IFERROR(M68/M6-1,0) -> 0 | N79: =IFERROR(N68/N6-1,0) -> 0 | O79: =IFERROR(O68/O6-1,0) -> 0 | ... AK79: =IFERROR(AK68/AK6-1,0) -> 0
A80: =A7 -> Nombre Jurisdicción | B80: =B7 -> Nombre Sector | C80: =C7 -> 0 | D80: =IFERROR(D69/D7-1,0) -> 0 | E80: =COUNTIF(H80:AK80,">0") -> 0 | F80: =IFERROR(F69/F7-1,0) -> 0 | H80: =IFERROR(H69/H7-1,0) -> 0 | I80: =IFERROR(I69/I7-1,0) -> 0 | J80: =IFERROR(J69/J7-1,0) -> 0 | K80: =IFERROR(K69/K7-1,0) -> 0 | L80: =IFERROR(L69/L7-1,0) -> 0 | M80: =IFERROR(M69/M7-1,0) -> 0 | N80: =IFERROR(N69/N7-1,0) -> 0 | O80: =IFERROR(O69/O7-1,0) -> 0 | ... AK80: =IFERROR(AK69/AK7-1,0) -> 0
A81: =A8 -> Nombre Jurisdicción | B81: =B8 -> Nombre Sector | C81: =C8 -> 0 | D81: =IFERROR(D70/D8-1,0) -> 0 | E81: =COUNTIF(H81:AK81,">0") -> 0 | F81: =IFERROR(F70/F8-1,0) -> 0 | H81: =IFERROR(H70/H8-1,0) -> 0 | I81: =IFERROR(I70/I8-1,0) -> 0 | J81: =IFERROR(J70/J8-1,0) -> 0 | K81: =IFERROR(K70/K8-1,0) -> 0 | L81: =IFERROR(L70/L8-1,0) -> 0 | M81: =IFERROR(M70/M8-1,0) -> 0 | N81: =IFERROR(N70/N8-1,0) -> 0 | O81: =IFERROR(O70/O8-1,0) -> 0 | ... AK81: =IFERROR(AK70/AK8-1,0) -> 0
A82: TOTAL | D82: =IFERROR(D71/D9-1,0) -> 0.11831297 | F82: =IFERROR(F71/F9-1,0) -> 0.11831297 | H82: =IFERROR(H71/H9-1,0) -> 0.1 | I82: =IFERROR(I71/I9-1,0) -> 0.10949125 | J82: =IFERROR(J71/J9-1,0) -> 0.118828 | K82: =IFERROR(K71/K9-1,0) -> 0.12801864 | L82: =IFERROR(L71/L9-1,0) -> 0.13705982 | M82: =IFERROR(M71/M9-1,0) -> 0.14594751 | N82: =IFERROR(N71/N9-1,0) -> 0.15467847 | O82: =IFERROR(O71/O9-1,0) -> 0.16325574 | ... AK82: =IFERROR(AK71/AK9-1,0) -> 0
A84: REPOSICIÓN DEL STOCK DE CAPITAL EXISTENTE ACTUALMENTE, DURANTE EL AVANCE DE LA BRECHA EFECTIVA (AGRUPADO EN FUNCIÓN DE LAS UDM)
A85: Cuadro 2.2.8. Inversiones de Reposición del Stock de Capital Actualmente Existente, agrupadas según las UdMs, durante el Avance de la Brecha Efectiva por UdM, 2024 - 2033, en millones de pesos, (sin ajustes)
A86: JURISDICCIÓN | B86: SECTOR | C86: Unidad de Medida (UdM) | D86: Reposición de Stock de K Meta 2053 | F86: Reposición de Stock de K Meta 2033 | H86: 2024 | I86: 2025 | J86: 2026 | K86: 2027 | L86: 2028 | M86: 2029 | N86: 2030 | O86: 2031 | P86: 2032 | Q86: 2033 | R86: 2034 | S86: 2035 | T86: 2036 | U86: 2037 | V86: 2038 | W86: 2039 | X86: 2040 | Y86: 2041 | Z86: 2042 | AA86: 2043 | AB86: 2044 | AC86: 2045 | AD86: 2046 | AE86: 2047 | AF86: 2048 | AG86: 2049 | AH86: 2050 | AI86: 2051 | AJ86: 2052 | AK86: 2053
A87: =A3 -> Nombre Jurisdicción | B87: =B3 -> Nombre Sector | C87: =C3 -> Nombre UdM 1 | D87: =SUM(H87:AK87) -> 3599278080 | F87: =SUM(H87:Q87) -> 3599278080 | H87: 788889600 | I87: 788889600 | J87: 485785600 | K87: 382177280 | L87: 200000000 | M87: 200000000 | N87: 200000000 | O87: 184512000 | P87: 184512000 | Q87: 184512000
A88: =A4 -> Nombre Jurisdicción | B88: =B4 -> Nombre Sector | C88: =C4 -> Nombre UdM 2 | D88: =SUM(H88:AK88) -> 2.019862e+09 | F88: =SUM(H88:Q88) -> 2.019862e+09 | H88: 5.5220846e+08 | I88: 5.8730238e+08 | J88: 8.8035115e+08 | K88: 0 | L88: 0 | M88: 0 | N88: 0 | O88: 0 | P88: 0 | Q88: 0
A89: =A5 -> Nombre Jurisdicción | B89: =B5 -> Nombre Sector | C89: =C5 -> Nombre UdM 3 | D89: =SUM(H89:AK89) -> 1.5018141e+09 | F89: =SUM(H89:Q89) -> 1.5018141e+09 | H89: 1.8175119e+08 | I89: 1.2248224e+09 | J89: 61737706 | K89: 33502837 | L89: 0 | M89: 0 | N89: 0 | O89: 0 | P89: 0 | Q89: 0
A90: =A6 -> Nombre Jurisdicción | B90: =B6 -> Nombre Sector | C90: =C6 -> 0 | D90: =SUM(H90:AK90) -> 0 | F90: =SUM(H90:Q90) -> 0
A91: =A7 -> Nombre Jurisdicción | B91: =B7 -> Nombre Sector | C91: =C7 -> 0 | D91: =SUM(H91:AK91) -> 0 | F91: =SUM(H91:Q91) -> 0
A92: =A8 -> Nombre Jurisdicción | B92: =B8 -> Nombre Sector | C92: =C8 -> 0 | D92: =SUM(H92:AK92) -> 0 | F92: =SUM(H92:Q92) -> 0
A93: TOTAL | D93: =SUM(H93:AK93) -> 7.1209542e+09 | F93: =SUM(F87:F92) -> 7.1209542e+09 | H93: =SUM(H87:H89) -> 1.5228493e+09 | I93: =SUM(I87:I89) -> 2.6010143e+09 | J93: =SUM(J87:J89) -> 1.4278745e+09 | K93: =SUM(K87:K89) -> 4.1568012e+08 | L93: =SUM(L87:L89) -> 200000000 | M93: =SUM(M87:M89) -> 200000000 | N93: =SUM(N87:N89) -> 200000000 | O93: =SUM(O87:O89) -> 184512000 | ... AK93: =SUM(AK87:AK89) -> 0
A95: INSTRUCTIVO
A97: Por favor, completar únicamente las columnas a partir de H (años de la curva de inversión) que correspondan según la estimación de la jurisdicción. Completar ÚNICAMENTE los montos estimados por reposiciones de bienes de capital (DEL STOCK DE CAPITAL ACTUALMENTE EXISTENTE) que se planea que tengan lugar durante el lapso de tiempo comprendido entre los años estimados para cerrar la brecha de cada UdM. No deben incluirse otros gastos de mantenimiento de la jurisdicción (aquellos que no están relacionados con reposición, y que no se vinculan con las actividades derivadas del cierre de la brecha).
A98: Los montos deben ser completados en pesos, ingresando la cifra completa (no en millones). El Excel mostrará, automáticamente, el monto en formato millones.
A99: Aclaración: Los montos ingresados en este cuadro no requieren ajustes adicionales, dado que el ajuste por incremento de la demanda durante el plazo que demore cerrar la brecha, ya fue realizado a los montos del cuadro 2.2.4. Estos montos de inversiones apuntan a mantener el stock de capital que existe actualmente.
A101: Cuadro 2.2.9. Total del Monto de Inversión Necesaria para Cerrar la Brecha, teniendo en cuenta la Reposición del Stock de Capital Actualmente Existente, y las Inversiones Necesarias para Cerrar la Brecha ajustadas por el Plazo de la Brecha Efectiva, por UdM, 2024 - 2033, en millones de pesos
A102: JURISDICCIÓN | B102: SECTOR | C102: Unidad de Medida (UdM) | D102: Brecha x UdM (millones $) META 2053 | E102: Plazo (Años) META 2053 | F102: Brecha x UdM (millones $) META 2033 | G102: (%) de la Brecha cubierto en 2033 | H102: 2024 | I102: 2025 | J102: 2026 | K102: 2027 | L102: 2028 | M102: 2029 | N102: 2030 | O102: 2031 | P102: 2032 | Q102: 2033 | R102: 2034 | S102: 2035 | T102: 2036 | U102: 2037 | V102: 2038 | W102: 2039 | X102: 2040 | Y102: 2041 | Z102: 2042 | AA102: 2043 | AB102: 2044 | AC102: 2045 | AD102: 2046 | AE102: 2047 | AF102: 2048 | AG102: 2049 | AH102: 2050 | AI102: 2051 | AJ102: 2052 | AK102: 2053
A103: =A3 -> Nombre Jurisdicción | B103: =B3 -> Nombre Sector | C103: =C3 -> Nombre UdM 1 | D103: =SUM(H103:AK103) -> 2.3867958e+10 | E103: =COUNTIF(H103:AK103,">0") -> 10 | F103: =SUM(H103:Q103) -> 2.3867958e+10 | G103: =IFERROR(F103/D103,0) -> 1 | H103: =H65+H87 -> 5127782400 | I103: =I65+I87 -> 5.1652202e+09 | J103: =J65+J87 -> 3.2033383e+09 | K103: =K65+K87 -> 2.5376928e+09 | L103: =L65+L87 -> 1.3370598e+09 | M103: =M65+M87 -> 1.3459475e+09 | N103: =N65+N87 -> 1.3546785e+09 | O103: =O65+O87 -> 1.2576852e+09 | ... AK103: =AK65+AK87 -> 0
A104: =A4 -> Nombre Jurisdicción | B104: =B4 -> Nombre Sector | C104: =C4 -> Nombre UdM 2 | D104: =SUM(H104:AK104) -> 1.323985e+10 | E104: =COUNTIF(H104:AK104,">0") -> 3 | F104: =SUM(H104:Q104) -> 1.323985e+10 | G104: =IFERROR(F104/D104,0) -> 1 | H104: =H66+H88 -> 3.589355e+09 | I104: =I66+I88 -> 3.8453366e+09 | J104: =J66+J88 -> 5.8051587e+09 | K104: =K66+K88 -> 0 | L104: =L66+L88 -> 0 | M104: =M66+M88 -> 0 | N104: =N66+N88 -> 0 | O104: =O66+O88 -> 0 | ... AK104: =AK66+AK88 -> 0
A105: =A5 -> Nombre Jurisdicción | B105: =B5 -> Nombre Sector | C105: =C5 -> Nombre UdM 3 | D105: =SUM(H105:AK105) -> 9.8304225e+09 | E105: =COUNTIF(H105:AK105,">0") -> 4 | F105: =SUM(H105:Q105) -> 9.8304225e+09 | G105: =IFERROR(F105/D105,0) -> 1 | H105: =H67+H89 -> 1.1813827e+09 | I105: =I67+I89 -> 8.0194708e+09 | J105: =J67+J89 -> 4.0710708e+08 | K105: =K67+K89 -> 2.2246196e+08 | L105: =L67+L89 -> 0 | M105: =M67+M89 -> 0 | N105: =N67+N89 -> 0 | O105: =O67+O89 -> 0 | ... AK105: =AK67+AK89 -> 0
A106: =A6 -> Nombre Jurisdicción | B106: =B6 -> Nombre Sector | C106: =C6 -> 0 | D106: =SUM(H106:AK106) -> 0 | E106: =COUNTIF(H106:AK106,">0") -> 0 | F106: =SUM(H106:Q106) -> 0 | G106: =IFERROR(F106/D106,0) -> 0 | H106: =H68+H90 -> 0 | I106: =I68+I90 -> 0 | J106: =J68+J90 -> 0 | K106: =K68+K90 -> 0 | L106: =L68+L90 -> 0 | M106: =M68+M90 -> 0 | N106: =N68+N90 -> 0 | O106: =O68+O90 -> 0 | ... AK106: =AK68+AK90 -> 0
A107: =A7 -> Nombre Jurisdicción | B107: =B7 -> Nombre Sector | C107: =C7 -> 0 | D107: =SUM(H107:AK107) -> 0 | E107: =COUNTIF(H107:AK107,">0") -> 0 | F107: =SUM(H107:Q107) -> 0 | G107: =IFERROR(F107/D107,0) -> 0 | H107: =H69+H91 -> 0 | I107: =I69+I91 -> 0 | J107: =J69+J91 -> 0 | K107: =K69+K91 -> 0 | L107: =L69+L91 -> 0 | M107: =M69+M91 -> 0 | N107: =N69+N91 -> 0 | O107: =O69+O91 -> 0 | ... AK107: =AK69+AK91 -> 0
A108: =A8 -> Nombre Jurisdicción | B108: =B8 -> Nombre Sector | C108: =C8 -> 0 | D108: =SUM(H108:AK108) -> 0 | E108: =COUNTIF(H108:AK108,">0") -> 0 | F108: =SUM(H108:Q108) -> 0 | G108: =IFERROR(F108/D108,0) -> 0 | H108: =H70+H92 -> 0 | I108: =I70+I92 -> 0 | J108: =J70+J92 -> 0 | K108: =K70+K92 -> 0 | L108: =L70+L92 -> 0 | M108: =M70+M92 -> 0 | N108: =N70+N92 -> 0 | O108: =O70+O92 -> 0 | ... AK108: =AK70+AK92 -> 0
A109: TOTAL | D109: =SUM(H109:AK109) -> 4.6938231e+10 | F109: =SUM(F103:F105) -> 4.6938231e+10 | G109: =IFERROR(F109/D109,0) -> 1 | H109: =SUM(H103:H105) -> 9.8985201e+09 | I109: =SUM(I103:I105) -> 1.7030028e+10 | J109: =SUM(J103:J105) -> 9.4156041e+09 | K109: =SUM(K103:K105) -> 2.7601547e+09 | L109: =SUM(L103:L105) -> 1.3370598e+09 | M109: =SUM(M103:M105) -> 1.3459475e+09 | N109: =SUM(N103:N105) -> 1.3546785e+09 | O109: =SUM(O103:O105) -> 1.2576852e+09 | ... AK109: =SUM(AK103:AK105) -> 0
A112: Cuadro 2.2.10. Ponderación de las UdM para que, ante cambios en el escenario macroeconómico, ajusten según la variación de la inflación o la variación del tipo de cambio
A113: JURISDICCIÓN | B113: SECTOR | C113: Unidad de Medida (UdM) | F113: Ponderación ajuste por inflación | G113: Ponderación ajuste por TC
A114: =A3 -> Nombre Jurisdicción | B114: =B3 -> Nombre Sector | C114: =C3 -> Nombre UdM 1 | F114: 1 | G114: =1-F114 -> 0
A115: =A4 -> Nombre Jurisdicción | B115: =B4 -> Nombre Sector | C115: =C4 -> Nombre UdM 2 | F115: 1 | G115: =1-F115 -> 0
A116: =A5 -> Nombre Jurisdicción | B116: =B5 -> Nombre Sector | C116: =C5 -> Nombre UdM 3 | F116: 1 | G116: =1-F116 -> 0
...

Sheet 2.3.Brecha x Provincia
A1: Cuadro 2.3.1 Brecha por UdM, por Provincia, 2024 - 2033, en millones de pesos, (sin ajustes)
A2: Jurisdicción | B2: ='2.2.Brecha Efectiva x UdM'!A3 -> Nombre Jurisdicción
A3: Unidad de Medida | B3: % | C3: ='2.2.Brecha Efectiva x UdM'!C3 -> Nombre UdM 1 | D3: % | E3: ='2.2.Brecha Efectiva x UdM'!C4 -> Nombre UdM 2 | F3: % | G3: ='2.2.Brecha Efectiva x UdM'!C5 -> Nombre UdM 3 | H3: % | I3: ='2.2.Brecha Efectiva x UdM'!C6 -> 0 | J3: % | K3: ='2.2.Brecha Efectiva x UdM'!C7 -> 0 | L3: % | M3: ='2.2.Brecha Efectiva x UdM'!C8 -> 0 | N3: % | O3: TOTAL
A4: Buenos Aires | B4: =IFERROR(C4/C$28,0) -> 0.081790167 | C4: 1.4719278e+09 | D4: =IFERROR(E4/E$28,0) -> 0.034950626 | E4: 3.529772e+08 | F4: =IFERROR(G4/G$28,0) -> 0.79999608 | G4: 6.0072269e+09 | H4: =IFERROR(I4/I$28,0) -> 0 | I4: 0 | J4: =IFERROR(K4/K$28,0) -> 0 | K4: 0 | L4: =IFERROR(M4/M$28,0) -> 0 | M4: 0 | N4: =IFERROR(O4/O$28,0) -> 0.21997422 | O4: =SUM(C4,E4,G4,I4,K4,M4) -> 7.8321319e+09
A5: CABA | B5: =IFERROR(C5/C$28,0) -> 5.3184577e-05 | C5: 957130.4 | D5: =IFERROR(E5/E$28,0) -> 0.0032654904 | E5: 32979200 | F5: =IFERROR(G5/G$28,0) -> 0.02518396 | G5: 1.8910813e+08 | H5: =IFERROR(I5/I$28,0) -> 0 | I5: 0 | J5: =IFERROR(K5/K$28,0) -> 0 | K5: 0 | L5: =IFERROR(M5/M$28,0) -> 0 | M5: 0 | N5: =IFERROR(O5/O$28,0) -> 0.0062644542 | O5: =SUM(C5,E5,G5,I5,K5,M5) -> 2.2304446e+08
A6: Catamarca | B6: =IFERROR(C6/C$28,0) -> 0.020669489 | C6: 3.7197619e+08 | D6: =IFERROR(E6/E$28,0) -> 0.0055612125 | E6: 56164408 | F6: =IFERROR(G6/G$28,0) -> 0 | G6: 0 | H6: =IFERROR(I6/I$28,0) -> 0 | I6: 0 | J6: =IFERROR(K6/K$28,0) -> 0 | K6: 0 | L6: =IFERROR(M6/M$28,0) -> 0 | M6: 0 | N6: =IFERROR(O6/O$28,0) -> 0.01202481 | O6: =SUM(C6,E6,G6,I6,K6,M6) -> 4.281406e+08
A7: Chaco | B7: =IFERROR(C7/C$28,0) -> 0.011864623 | C7: 2.1352038e+08 | D7: =IFERROR(E7/E$28,0) -> 0.0081142405 | E7: 81948230 | F7: =IFERROR(G7/G$28,0) -> 0 | G7: 0 | H7: =IFERROR(I7/I$28,0) -> 0 | I7: 0 | J7: =IFERROR(K7/K$28,0) -> 0 | K7: 0 | L7: =IFERROR(M7/M$28,0) -> 0 | M7: 0 | N7: =IFERROR(O7/O$28,0) -> 0.0082985681 | O7: =SUM(C7,E7,G7,I7,K7,M7) -> 2.9546861e+08
A8: Chubut | B8: =IFERROR(C8/C$28,0) -> 0.16467584 | C8: 2963570688 | D8: =IFERROR(E8/E$28,0) -> 0.13641291 | E8: 1.3776762e+09 | F8: =IFERROR(G8/G$28,0) -> 0.019402268 | G8: 145693000 | H8: =IFERROR(I8/I$28,0) -> 0 | I8: 0 | J8: =IFERROR(K8/K$28,0) -> 0 | K8: 0 | L8: =IFERROR(M8/M$28,0) -> 0 | M8: 0 | N8: =IFERROR(O8/O$28,0) -> 0.12602075 | O8: =SUM(C8,E8,G8,I8,K8,M8) -> 4.4869399e+09
A9: Córdoba | B9: =IFERROR(C9/C$28,0) -> 0.035367531 | C9: 6.364879e+08 | D9: =IFERROR(E9/E$28,0) -> 0.0065309808 | E9: 65958399 | F9: =IFERROR(G9/G$28,0) -> 0.0093220593 | G9: 70000000 | H9: =IFERROR(I9/I$28,0) -> 0 | I9: 0 | J9: =IFERROR(K9/K$28,0) -> 0 | K9: 0 | L9: =IFERROR(M9/M$28,0) -> 0 | M9: 0 | N9: =IFERROR(O9/O$28,0) -> 0.021695022 | O9: =SUM(C9,E9,G9,I9,K9,M9) -> 7.724463e+08
A10: Corrientes | B10: =IFERROR(C10/C$28,0) -> 0.010593413 | C10: 190643200 | D10: =IFERROR(E10/E$28,0) -> 0.034777058 | E10: 3.5122429e+08 | F10: =IFERROR(G10/G$28,0) -> 0.0046136139 | G10: 34643952 | H10: =IFERROR(I10/I$28,0) -> 0 | I10: 0 | J10: =IFERROR(K10/K$28,0) -> 0 | K10: 0 | L10: =IFERROR(M10/M$28,0) -> 0 | M10: 0 | N10: =IFERROR(O10/O$28,0) -> 0.016191972 | O10: =SUM(C10,E10,G10,I10,K10,M10) -> 5.7651144e+08
A11: Entre Ríos | B11: =IFERROR(C11/C$28,0) -> 0.020949671 | C11: 3.7701845e+08 | D11: =IFERROR(E11/E$28,0) -> 0.054498795 | E11: 5.5040023e+08 | F11: =IFERROR(G11/G$28,0) -> 0.0032165815 | G11: 24153537 | H11: =IFERROR(I11/I$28,0) -> 0 | I11: 0 | J11: =IFERROR(K11/K$28,0) -> 0 | K11: 0 | L11: =IFERROR(M11/M$28,0) -> 0 | M11: 0 | N11: =IFERROR(O11/O$28,0) -> 0.026725975 | O11: =SUM(C11,E11,G11,I11,K11,M11) -> 9.5157222e+08
A12: Formosa | B12: =IFERROR(C12/C$28,0) -> 0.0084747306 | C12: 152514560 | D12: =IFERROR(E12/E$28,0) -> 0.033957377 | E12: 3.4294608e+08 | F12: =IFERROR(G12/G$28,0) -> 0 | G12: 0 | H12: =IFERROR(I12/I$28,0) -> 0 | I12: 0 | J12: =IFERROR(K12/K$28,0) -> 0 | K12: 0 | L12: =IFERROR(M12/M$28,0) -> 0 | M12: 0 | N12: =IFERROR(O12/O$28,0) -> 0.013915569 | O12: =SUM(C12,E12,G12,I12,K12,M12) -> 4.9546064e+08
A13: Jujuy | B13: =IFERROR(C13/C$28,0) -> 0.010334744 | C13: 1.859881e+08 | D13: =IFERROR(E13/E$28,0) -> 0.023903413 | E13: 2.4140798e+08 | F13: =IFERROR(G13/G$28,0) -> 0 | G13: 0 | H13: =IFERROR(I13/I$28,0) -> 0 | I13: 0 | J13: =IFERROR(K13/K$28,0) -> 0 | K13: 0 | L13: =IFERROR(M13/M$28,0) -> 0 | M13: 0 | N13: =IFERROR(O13/O$28,0) -> 0.012003899 | O13: =SUM(C13,E13,G13,I13,K13,M13) -> 4.2739608e+08
A14: La Pampa | B14: =IFERROR(C14/C$28,0) -> 0.051484378 | C14: 9.2653297e+08 | D14: =IFERROR(E14/E$28,0) -> 0.0032654904 | E14: 32979200 | F14: =IFERROR(G14/G$28,0) -> 0 | G14: 0 | H14: =IFERROR(I14/I$28,0) -> 0 | I14: 0 | J14: =IFERROR(K14/K$28,0) -> 0 | K14: 0 | L14: =IFERROR(M14/M$28,0) -> 0 | M14: 0 | N14: =IFERROR(O14/O$28,0) -> 0.026948978 | O14: =SUM(C14,E14,G14,I14,K14,M14) -> 9.5951217e+08
A15: La Rioja | B15: =IFERROR(C15/C$28,0) -> 0.017716705 | C15: 318836736 | D15: =IFERROR(E15/E$28,0) -> 0.0060460966 | E15: 61061404 | F15: =IFERROR(G15/G$28,0) -> 0 | G15: 0 | H15: =IFERROR(I15/I$28,0) -> 0 | I15: 0 | J15: =IFERROR(K15/K$28,0) -> 0 | K15: 0 | L15: =IFERROR(M15/M$28,0) -> 0 | M15: 0 | N15: =IFERROR(O15/O$28,0) -> 0.010669866 | O15: =SUM(C15,E15,G15,I15,K15,M15) -> 3.7989814e+08
... A27: Tucumán | B27: =IFERROR(C27/C$28,0) -> 0.0059055683 | C27: 106278912 | D27: =IFERROR(E27/E$28,0) -> 0.0032654904 | E27: 32979200 | F27: =IFERROR(G27/G$28,0) -> 0 | G27: 0 | H27: =IFERROR(I27/I$28,0) -> 0 | I27: 0 | J27: =IFERROR(K27/K$28,0) -> 0 | K27: 0 | L27: =IFERROR(M27/M$28,0) -> 0 | M27: 0 | N27: =IFERROR(O27/O$28,0) -> 0.0039112206 | O27: =SUM(C27,E27,G27,I27,K27,M27) -> 1.3925811e+08
A28: Total general | B28: =IFERROR(C28/C$28,0) -> 1 | C28: =SUM(C4:C27) -> 17996390400 | D28: =IFERROR(E28/E$28,0) -> 1 | E28: =SUM(E4:E27) -> 1.009931e+10 | F28: =IFERROR(G28/G$28,0) -> 1 | G28: =SUM(G4:G27) -> 7.5090704e+09 | H28: =IFERROR(I28/I$28,0) -> 0 | I28: =SUM(I4:I27) -> 0 | J28: =IFERROR(K28/K$28,0) -> 0 | K28: =SUM(K4:K27) -> 0 | L28: =IFERROR(M28/M$28,0) -> 0 | M28: =SUM(M4:M27) -> 0 | N28: =IFERROR(O28/O$28,0) -> 1 | O28: =SUM(C28,E28,G28,I28,K28,M28) -> 3.5604771e+10
A30: Chequeo | C30: =C28='2.2.Brecha Efectiva x UdM'!F3 -> TRUE | E30: =E28='2.2.Brecha Efectiva x UdM'!F4 -> TRUE | G30: =G28='2.2.Brecha Efectiva x UdM'!F5 -> TRUE | I30: =I28='2.2.Brecha Efectiva x UdM'!F6 -> TRUE | K30: =K28='2.2.Brecha Efectiva x UdM'!F7 -> TRUE | M30: =M28='2.2.Brecha Efectiva x UdM'!F8 -> TRUE | O30: =O28='2.2.Brecha Efectiva x UdM'!F9 -> TRUE
A32: INSTRUCTIVO
A34: Por favor, completar únicamente las columnas correspondiente a la distribución territorial del monto de la brecha en cada una de las UdMs calculadas por la Jurisdicción. Tener en cuenta que se trata de la distribución de la brecha total de cada una en las UdMs (sumatoria de las brechas efectivas) previamente a la realización de cualquier ajuste (Ejemplo en Rojo)
A35: Los montos deben ser completados en pesos, ingresando la cifra completa (no en millones). El Excel mostrará, automáticamente, el monto en formato millones.
A36: Por favor, mantener las provincias ordenadas alfabéticamente.
A38: DSITRIBUCIÓN PROVINCIAL DE LA BRECHA EFECTIVA DE CADA UDM, AJUSTADA POR EL ÍNDICE DE ACTUALIZACIÓN (EJEMPLO PREDETERMINADO: CRECIMIENTO DE LA POBLACIÓN) (un cuadro para cada UdM)
A39: Supuestos:
A40: Supone ponderaciones constantes, a lo largo de los años, de la distribución entre provincias de montos de la UDM.
A41: También supone la utilización de un único índice de actualización (en el ejemplo predeterminado: la tasa de crecimiento de la población nacional) para realizar el ajuste en cada provincia.
A42: Aclaración:
A43: Si la Jurisdicción decidiera estimar un índice de actualización diferente para cada provincia, podrá reemplazar ("pisar") el cálculo predeterminado de los cuadros de resultado con su propia estimación. Luego deberá explicar los índices de actualización utilizados para permitir que los resultados puedan ser interpretados adecuadamente.
A45: Cuadro 2.3.3.1. Distribución provincial de la UdM 1, por brecha efectiva, en millones de pesos, ajustada en función de la tasa de crecimiento de la Poblacional Nacional.
A47: Provincia | B47: UDM | C47: UDM Provincial | D47: 2024 | E47: 2025 | F47: 2026 | G47: 2027 | H47: 2028 | I47: 2029 | J47: 2030 | K47: 2031 | L47: 2032 | M47: 2033 | N47: 2034 | O47: 2035 | P47: 2036 | Q47: 2037 | R47: 2038 | S47: 2039 | T47: 2040 | U47: 2041 | V47: 2042 | W47: 2043 | X47: 2044 | Y47: 2045 | Z47: 2046 | AA47: 2047 | AB47: 2048 | AC47: 2049 | AD47: 2050 | AE47: 2051 | AF47: 2052 | AG47: 2053 | AH47: TOTAL
A48: =A4 -> Buenos Aires | B48: =$C$3 -> Nombre UdM 1 | C48: =CONCATENATE(A48," ",B48) -> Buenos Aires Nombre UdM 1 | D48: =VLOOKUP($A48,$A$4:$O$28,2,0)*(HLOOKUP(D$47,'2.2.Brecha Efectiva x UdM'!$H$25:$AK$32,2,0)) -> 3.2261706e+08 | E48: =VLOOKUP($A48,$A$4:$O$28,2,0)*(HLOOKUP(E$47,'2.2.Brecha Efectiva x UdM'!$H$25:$AK$32,2,0)) -> 3.2540073e+08 | F48: =VLOOKUP($A48,$A$4:$O$28,2,0)*(HLOOKUP(F$47,'2.2.Brecha Efectiva x UdM'!$H$25:$AK$32,2,0)) -> 2.0206281e+08 | G48: =VLOOKUP($A48,$A$4:$O$28,2,0)*(HLOOKUP(G$47,'2.2.Brecha Efectiva x UdM'!$H$25:$AK$32,2,0)) -> 1.602727e+08 | H48: =VLOOKUP($A48,$A$4:$O$28,2,0)*(HLOOKUP(H$47,'2.2.Brecha Efectiva x UdM'!$H$25:$AK$32,2,0)) -> 84545739 | I48: =VLOOKUP($A48,$A$4:$O$28,2,0)*(HLOOKUP(I$47,'2.2.Brecha Efectiva x UdM'!$H$25:$AK$32,2,0)) -> 85206580 | J48: =VLOOKUP($A48,$A$4:$O$28,2,0)*(HLOOKUP(J$47,'2.2.Brecha Efectiva x UdM'!$H$25:$AK$32,2,0)) -> 85855768 | K48: =VLOOKUP($A48,$A$4:$O$28,2,0)*(HLOOKUP(K$47,'2.2.Brecha Efectiva x UdM'!$H$25:$AK$32,2,0)) -> 79795470 | ... AG48: =VLOOKUP($A48,$A$4:$O$28,2,0)*(HLOOKUP(AG$47,'2.2.Brecha Efectiva x UdM'!$H$25:$AK$32,2,0)) -> 0 | AH48: =SUM(D48:AG48) -> 1.5070716e+09
A49: =A5 -> CABA | B49: =$C$3 -> Nombre UdM 1 | C49: =CONCATENATE(A49," ",B49) -> CABA Nombre UdM 1 | D49: =VLOOKUP($A49,$A$4:$O$28,2,0)*(HLOOKUP(D$47,'2.2.Brecha Efectiva x UdM'!$H$25:$AK$32,2,0)) -> 209783.8 | E49: =VLOOKUP($A49,$A$4:$O$28,2,0)*(HLOOKUP(E$47,'2.2.Brecha Efectiva x UdM'!$H$25:$AK$32,2,0)) -> 211593.9 | F49: =VLOOKUP($A49,$A$4:$O$28,2,0)*(HLOOKUP(F$47,'2.2.Brecha Efectiva x UdM'!$H$25:$AK$32,2,0)) -> 131392.63 | G49: =VLOOKUP($A49,$A$4:$O$28,2,0)*(HLOOKUP(G$47,'2.2.Brecha Efectiva x UdM'!$H$25:$AK$32,2,0)) -> 104218.34 | H49: =VLOOKUP($A49,$A$4:$O$28,2,0)*(HLOOKUP(H$47,'2.2.Brecha Efectiva x UdM'!$H$25:$AK$32,2,0)) -> 54976.405 | I49: =VLOOKUP($A49,$A$4:$O$28,2,0)*(HLOOKUP(I$47,'2.2.Brecha Efectiva x UdM'!$H$25:$AK$32,2,0)) -> 55406.121 | J49: =VLOOKUP($A49,$A$4:$O$28,2,0)*(HLOOKUP(J$47,'2.2.Brecha Efectiva x UdM'!$H$25:$AK$32,2,0)) -> 55828.259 | K49: =VLOOKUP($A49,$A$4:$O$28,2,0)*(HLOOKUP(K$47,'2.2.Brecha Efectiva x UdM'!$H$25:$AK$32,2,0)) -> 51887.512 | ... AG49: =VLOOKUP($A49,$A$4:$O$28,2,0)*(HLOOKUP(AG$47,'2.2.Brecha Efectiva x UdM'!$H$25:$AK$32,2,0)) -> 0 | AH49: =SUM(D49:AG49) -> 979982.87
A50: =A6 -> Catamarca | B50: =$C$3 -> Nombre UdM 1 | C50: =CONCATENATE(A50," ",B50) -> Catamarca Nombre UdM 1 | D50: =VLOOKUP($A50,$A$4:$O$28,2,0)*(HLOOKUP(D$47,'2.2.Brecha Efectiva x UdM'!$H$25:$AK$32,2,0)) -> 81529724 | E50: =VLOOKUP($A50,$A$4:$O$28,2,0)*(HLOOKUP(E$47,'2.2.Brecha Efectiva x UdM'!$H$25:$AK$32,2,0)) -> 82233196 | F50: =VLOOKUP($A50,$A$4:$O$28,2,0)*(HLOOKUP(F$47,'2.2.Brecha Efectiva x UdM'!$H$25:$AK$32,2,0)) -> 51064022 | G50: =VLOOKUP($A50,$A$4:$O$28,2,0)*(HLOOKUP(G$47,'2.2.Brecha Efectiva x UdM'!$H$25:$AK$32,2,0)) -> 40503094 | H50: =VLOOKUP($A50,$A$4:$O$28,2,0)*(HLOOKUP(H$47,'2.2.Brecha Efectiva x UdM'!$H$25:$AK$32,2,0)) -> 21365859 | I50: =VLOOKUP($A50,$A$4:$O$28,2,0)*(HLOOKUP(I$47,'2.2.Brecha Efectiva x UdM'!$H$25:$AK$32,2,0)) -> 21532863 | J50: =VLOOKUP($A50,$A$4:$O$28,2,0)*(HLOOKUP(J$47,'2.2.Brecha Efectiva x UdM'!$H$25:$AK$32,2,0)) -> 21696922 | K50: =VLOOKUP($A50,$A$4:$O$28,2,0)*(HLOOKUP(K$47,'2.2.Brecha Efectiva x UdM'!$H$25:$AK$32,2,0)) -> 20165402 | ... AG50: =VLOOKUP($A50,$A$4:$O$28,2,0)*(HLOOKUP(AG$47,'2.2.Brecha Efectiva x UdM'!$H$25:$AK$32,2,0)) -> 0 | AH50: =SUM(D50:AG50) -> 3.8085751e+08
A51: =A7 -> Chaco | B51: =$C$3 -> Nombre UdM 1 | C51: =CONCATENATE(A51," ",B51) -> Chaco Nombre UdM 1 | D51: =VLOOKUP($A51,$A$4:$O$28,2,0)*(HLOOKUP(D$47,'2.2.Brecha Efectiva x UdM'!$H$25:$AK$32,2,0)) -> 46799388 | E51: =VLOOKUP($A51,$A$4:$O$28,2,0)*(HLOOKUP(E$47,'2.2.Brecha Efectiva x UdM'!$H$25:$AK$32,2,0)) -> 47203192 | F51: =VLOOKUP($A51,$A$4:$O$28,2,0)*(HLOOKUP(F$47,'2.2.Brecha Efectiva x UdM'!$H$25:$AK$32,2,0)) -> 29311579 | G51: =VLOOKUP($A51,$A$4:$O$28,2,0)*(HLOOKUP(G$47,'2.2.Brecha Efectiva x UdM'!$H$25:$AK$32,2,0)) -> 23249435 | H51: =VLOOKUP($A51,$A$4:$O$28,2,0)*(HLOOKUP(H$47,'2.2.Brecha Efectiva x UdM'!$H$25:$AK$32,2,0)) -> 12264351 | I51: =VLOOKUP($A51,$A$4:$O$28,2,0)*(HLOOKUP(I$47,'2.2.Brecha Efectiva x UdM'!$H$25:$AK$32,2,0)) -> 12360214 | J51: =VLOOKUP($A51,$A$4:$O$28,2,0)*(HLOOKUP(J$47,'2.2.Brecha Efectiva x UdM'!$H$25:$AK$32,2,0)) -> 12454386 | K51: =VLOOKUP($A51,$A$4:$O$28,2,0)*(HLOOKUP(K$47,'2.2.Brecha Efectiva x UdM'!$H$25:$AK$32,2,0)) -> 11575269 | ... AG51: =VLOOKUP($A51,$A$4:$O$28,2,0)*(HLOOKUP(AG$47,'2.2.Brecha Efectiva x UdM'!$H$25:$AK$32,2,0)) -> 0 | AH51: =SUM(D51:AG51) -> 2.186184e+08
A52: =A8 -> Chubut | B52: =$C$3 -> Nombre UdM 1 | C52: =CONCATENATE(A52," ",B52) -> Chubut Nombre UdM 1 | D52: =VLOOKUP($A52,$A$4:$O$28,2,0)*(HLOOKUP(D$47,'2.2.Brecha Efectiva x UdM'!$H$25:$AK$32,2,0)) -> 6.4955528e+08 | E52: =VLOOKUP($A52,$A$4:$O$28,2,0)*(HLOOKUP(E$47,'2.2.Brecha Efectiva x UdM'!$H$25:$AK$32,2,0)) -> 6.5515991e+08 | F52: =VLOOKUP($A52,$A$4:$O$28,2,0)*(HLOOKUP(F$47,'2.2.Brecha Efectiva x UdM'!$H$25:$AK$32,2,0)) -> 4.0683206e+08 | G52: =VLOOKUP($A52,$A$4:$O$28,2,0)*(HLOOKUP(G$47,'2.2.Brecha Efectiva x UdM'!$H$25:$AK$32,2,0)) -> 3.2269211e+08 | H52: =VLOOKUP($A52,$A$4:$O$28,2,0)*(HLOOKUP(H$47,'2.2.Brecha Efectiva x UdM'!$H$25:$AK$32,2,0)) -> 1.7022389e+08 | I52: =VLOOKUP($A52,$A$4:$O$28,2,0)*(HLOOKUP(I$47,'2.2.Brecha Efectiva x UdM'!$H$25:$AK$32,2,0)) -> 1.7155442e+08 | J52: =VLOOKUP($A52,$A$4:$O$28,2,0)*(HLOOKUP(J$47,'2.2.Brecha Efectiva x UdM'!$H$25:$AK$32,2,0)) -> 1.728615e+08 | K52: =VLOOKUP($A52,$A$4:$O$28,2,0)*(HLOOKUP(K$47,'2.2.Brecha Efectiva x UdM'!$H$25:$AK$32,2,0)) -> 1.6065973e+08 | ... AG52: =VLOOKUP($A52,$A$4:$O$28,2,0)*(HLOOKUP(AG$47,'2.2.Brecha Efectiva x UdM'!$H$25:$AK$32,2,0)) -> 0 | AH52: =SUM(D52:AG52) -> 3.034329e+09
A53: =A9 -> Córdoba | B53: =$C$3 -> Nombre UdM 1 | C53: =CONCATENATE(A53," ",B53) -> Córdoba Nombre UdM 1 | D53: =VLOOKUP($A53,$A$4:$O$28,2,0)*(HLOOKUP(D$47,'2.2.Brecha Efectiva x UdM'!$H$25:$AK$32,2,0)) -> 1.3950539e+08 | E53: =VLOOKUP($A53,$A$4:$O$28,2,0)*(HLOOKUP(E$47,'2.2.Brecha Efectiva x UdM'!$H$25:$AK$32,2,0)) -> 1.407091e+08 | F53: =VLOOKUP($A53,$A$4:$O$28,2,0)*(HLOOKUP(F$47,'2.2.Brecha Efectiva x UdM'!$H$25:$AK$32,2,0)) -> 87375572 | G53: =VLOOKUP($A53,$A$4:$O$28,2,0)*(HLOOKUP(G$47,'2.2.Brecha Efectiva x UdM'!$H$25:$AK$32,2,0)) -> 69304783 | H53: =VLOOKUP($A53,$A$4:$O$28,2,0)*(HLOOKUP(H$47,'2.2.Brecha Efectiva x UdM'!$H$25:$AK$32,2,0)) -> 36559090 | I53: =VLOOKUP($A53,$A$4:$O$28,2,0)*(HLOOKUP(I$47,'2.2.Brecha Efectiva x UdM'!$H$25:$AK$32,2,0)) -> 36844849 | J53: =VLOOKUP($A53,$A$4:$O$28,2,0)*(HLOOKUP(J$47,'2.2.Brecha Efectiva x UdM'!$H$25:$AK$32,2,0)) -> 37125570 | K53: =VLOOKUP($A53,$A$4:$O$28,2,0)*(HLOOKUP(K$47,'2.2.Brecha Efectiva x UdM'!$H$25:$AK$32,2,0)) -> 34504989 | ... AG53: =VLOOKUP($A53,$A$4:$O$28,2,0)*(HLOOKUP(AG$47,'2.2.Brecha Efectiva x UdM'!$H$25:$AK$32,2,0)) -> 0 | AH53: =SUM(D53:AG53) -> 6.516847e+08
A54: =A10 -> Corrientes | B54: =$C$3 -> Nombre UdM 1 | C54: =CONCATENATE(A54," ",B54) -> Corrientes Nombre UdM 1 | D54: =VLOOKUP($A54,$A$4:$O$28,2,0)*(HLOOKUP(D$47,'2.2.Brecha Efectiva x UdM'!$H$25:$AK$32,2,0)) -> 41785168 | E54: =VLOOKUP($A54,$A$4:$O$28,2,0)*(HLOOKUP(E$47,'2.2.Brecha Efectiva x UdM'!$H$25:$AK$32,2,0)) -> 42145707 | F54: =VLOOKUP($A54,$A$4:$O$28,2,0)*(HLOOKUP(F$47,'2.2.Brecha Efectiva x UdM'!$H$25:$AK$32,2,0)) -> 26171053 | G54: =VLOOKUP($A54,$A$4:$O$28,2,0)*(HLOOKUP(G$47,'2.2.Brecha Efectiva x UdM'!$H$25:$AK$32,2,0)) -> 20758424 | H54: =VLOOKUP($A54,$A$4:$O$28,2,0)*(HLOOKUP(H$47,'2.2.Brecha Efectiva x UdM'!$H$25:$AK$32,2,0)) -> 10950313 | I54: =VLOOKUP($A54,$A$4:$O$28,2,0)*(HLOOKUP(I$47,'2.2.Brecha Efectiva x UdM'!$H$25:$AK$32,2,0)) -> 11035905 | J54: =VLOOKUP($A54,$A$4:$O$28,2,0)*(HLOOKUP(J$47,'2.2.Brecha Efectiva x UdM'!$H$25:$AK$32,2,0)) -> 11119987 | K54: =VLOOKUP($A54,$A$4:$O$28,2,0)*(HLOOKUP(K$47,'2.2.Brecha Efectiva x UdM'!$H$25:$AK$32,2,0)) -> 10335061 | ... AG54: =VLOOKUP($A54,$A$4:$O$28,2,0)*(HLOOKUP(AG$47,'2.2.Brecha Efectiva x UdM'!$H$25:$AK$32,2,0)) -> 0 | AH54: =SUM(D54:AG54) -> 1.95195e+08
A55: =A11 -> Entre Ríos | B55: =$C$3 -> Nombre UdM 1 | C55: =CONCATENATE(A55," ",B55) -> Entre Ríos Nombre UdM 1 | D55: =VLOOKUP($A55,$A$4:$O$28,2,0)*(HLOOKUP(D$47,'2.2.Brecha Efectiva x UdM'!$H$25:$AK$32,2,0)) -> 82634886 | E55: =VLOOKUP($A55,$A$4:$O$28,2,0)*(HLOOKUP(E$47,'2.2.Brecha Efectiva x UdM'!$H$25:$AK$32,2,0)) -> 83347894 | F55: =VLOOKUP($A55,$A$4:$O$28,2,0)*(HLOOKUP(F$47,'2.2.Brecha Efectiva x UdM'!$H$25:$AK$32,2,0)) -> 51756212 | G55: =VLOOKUP($A55,$A$4:$O$28,2,0)*(HLOOKUP(G$47,'2.2.Brecha Efectiva x UdM'!$H$25:$AK$32,2,0)) -> 41052127 | H55: =VLOOKUP($A55,$A$4:$O$28,2,0)*(HLOOKUP(H$47,'2.2.Brecha Efectiva x UdM'!$H$25:$AK$32,2,0)) -> 21655481 | I55: =VLOOKUP($A55,$A$4:$O$28,2,0)*(HLOOKUP(I$47,'2.2.Brecha Efectiva x UdM'!$H$25:$AK$32,2,0)) -> 21824748 | J55: =VLOOKUP($A55,$A$4:$O$28,2,0)*(HLOOKUP(J$47,'2.2.Brecha Efectiva x UdM'!$H$25:$AK$32,2,0)) -> 21991030 | K55: =VLOOKUP($A55,$A$4:$O$28,2,0)*(HLOOKUP(K$47,'2.2.Brecha Efectiva x UdM'!$H$25:$AK$32,2,0)) -> 20438750 | ... AG55: =VLOOKUP($A55,$A$4:$O$28,2,0)*(HLOOKUP(AG$47,'2.2.Brecha Efectiva x UdM'!$H$25:$AK$32,2,0)) -> 0 | AH55: =SUM(D55:AG55) -> 3.8602015e+08
A56: =A12 -> Formosa | B56: =$C$3 -> Nombre UdM 1 | C56: =CONCATENATE(A56," ",B56) -> Formosa Nombre UdM 1 | D56: =VLOOKUP($A56,$A$4:$O$28,2,0)*(HLOOKUP(D$47,'2.2.Brecha Efectiva x UdM'!$H$25:$AK$32,2,0)) -> 33428134 | E56: =VLOOKUP($A56,$A$4:$O$28,2,0)*(HLOOKUP(E$47,'2.2.Brecha Efectiva x UdM'!$H$25:$AK$32,2,0)) -> 33716566 | F56: =VLOOKUP($A56,$A$4:$O$28,2,0)*(HLOOKUP(F$47,'2.2.Brecha Efectiva x UdM'!$H$25:$AK$32,2,0)) -> 20936842 | G56: =VLOOKUP($A56,$A$4:$O$28,2,0)*(HLOOKUP(G$47,'2.2.Brecha Efectiva x UdM'!$H$25:$AK$32,2,0)) -> 16606739 | H56: =VLOOKUP($A56,$A$4:$O$28,2,0)*(HLOOKUP(H$47,'2.2.Brecha Efectiva x UdM'!$H$25:$AK$32,2,0)) -> 8760250.6 | I56: =VLOOKUP($A56,$A$4:$O$28,2,0)*(HLOOKUP(I$47,'2.2.Brecha Efectiva x UdM'!$H$25:$AK$32,2,0)) -> 8828724 | J56: =VLOOKUP($A56,$A$4:$O$28,2,0)*(HLOOKUP(J$47,'2.2.Brecha Efectiva x UdM'!$H$25:$AK$32,2,0)) -> 8895989.9 | K56: =VLOOKUP($A56,$A$4:$O$28,2,0)*(HLOOKUP(K$47,'2.2.Brecha Efectiva x UdM'!$H$25:$AK$32,2,0)) -> 8268049 | ... AG56: =VLOOKUP($A56,$A$4:$O$28,2,0)*(HLOOKUP(AG$47,'2.2.Brecha Efectiva x UdM'!$H$25:$AK$32,2,0)) -> 0 | AH56: =SUM(D56:AG56) -> 1.56156e+08
A57: =A13 -> Jujuy | B57: =$C$3 -> Nombre UdM 1 | C57: =CONCATENATE(A57," ",B57) -> Jujuy Nombre UdM 1 | D57: =VLOOKUP($A57,$A$4:$O$28,2,0)*(HLOOKUP(D$47,'2.2.Brecha Efectiva x UdM'!$H$25:$AK$32,2,0)) -> 40764862 | E57: =VLOOKUP($A57,$A$4:$O$28,2,0)*(HLOOKUP(E$47,'2.2.Brecha Efectiva x UdM'!$H$25:$AK$32,2,0)) -> 41116598 | F57: =VLOOKUP($A57,$A$4:$O$28,2,0)*(HLOOKUP(F$47,'2.2.Brecha Efectiva x UdM'!$H$25:$AK$32,2,0)) -> 25532011 | G57: =VLOOKUP($A57,$A$4:$O$28,2,0)*(HLOOKUP(G$47,'2.2.Brecha Efectiva x UdM'!$H$25:$AK$32,2,0)) -> 20251547 | H57: =VLOOKUP($A57,$A$4:$O$28,2,0)*(HLOOKUP(H$47,'2.2.Brecha Efectiva x UdM'!$H$25:$AK$32,2,0)) -> 10682930 | I57: =VLOOKUP($A57,$A$4:$O$28,2,0)*(HLOOKUP(I$47,'2.2.Brecha Efectiva x UdM'!$H$25:$AK$32,2,0)) -> 10766431 | J57: =VLOOKUP($A57,$A$4:$O$28,2,0)*(HLOOKUP(J$47,'2.2.Brecha Efectiva x UdM'!$H$25:$AK$32,2,0)) -> 10848461 | K57: =VLOOKUP($A57,$A$4:$O$28,2,0)*(HLOOKUP(K$47,'2.2.Brecha Efectiva x UdM'!$H$25:$AK$32,2,0)) -> 10082701 | ... AG57: =VLOOKUP($A57,$A$4:$O$28,2,0)*(HLOOKUP(AG$47,'2.2.Brecha Efectiva x UdM'!$H$25:$AK$32,2,0)) -> 0 | AH57: =SUM(D57:AG57) -> 1.9042875e+08
A58: =A14 -> La Pampa | B58: =$C$3 -> Nombre UdM 1 | C58: =CONCATENATE(A58," ",B58) -> La Pampa Nombre UdM 1 | D58: =VLOOKUP($A58,$A$4:$O$28,2,0)*(HLOOKUP(D$47,'2.2.Brecha Efectiva x UdM'!$H$25:$AK$32,2,0)) -> 2.0307745e+08 | E58: =VLOOKUP($A58,$A$4:$O$28,2,0)*(HLOOKUP(E$47,'2.2.Brecha Efectiva x UdM'!$H$25:$AK$32,2,0)) -> 2.0482969e+08 | F58: =VLOOKUP($A58,$A$4:$O$28,2,0)*(HLOOKUP(F$47,'2.2.Brecha Efectiva x UdM'!$H$25:$AK$32,2,0)) -> 1.2719228e+08 | G58: =VLOOKUP($A58,$A$4:$O$28,2,0)*(HLOOKUP(G$47,'2.2.Brecha Efectiva x UdM'!$H$25:$AK$32,2,0)) -> 1.008867e+08 | H58: =VLOOKUP($A58,$A$4:$O$28,2,0)*(HLOOKUP(H$47,'2.2.Brecha Efectiva x UdM'!$H$25:$AK$32,2,0)) -> 53218925 | I58: =VLOOKUP($A58,$A$4:$O$28,2,0)*(HLOOKUP(I$47,'2.2.Brecha Efectiva x UdM'!$H$25:$AK$32,2,0)) -> 53634904 | J58: =VLOOKUP($A58,$A$4:$O$28,2,0)*(HLOOKUP(J$47,'2.2.Brecha Efectiva x UdM'!$H$25:$AK$32,2,0)) -> 54043548 | K58: =VLOOKUP($A58,$A$4:$O$28,2,0)*(HLOOKUP(K$47,'2.2.Brecha Efectiva x UdM'!$H$25:$AK$32,2,0)) -> 50228778 | ... AG58: =VLOOKUP($A58,$A$4:$O$28,2,0)*(HLOOKUP(AG$47,'2.2.Brecha Efectiva x UdM'!$H$25:$AK$32,2,0)) -> 0 | AH58: =SUM(D58:AG58) -> 9.486549e+08
A59: =A15 -> La Rioja | B59: =$C$3 -> Nombre UdM 1 | C59: =CONCATENATE(A59," ",B59) -> La Rioja Nombre UdM 1 | D59: =VLOOKUP($A59,$A$4:$O$28,2,0)*(HLOOKUP(D$47,'2.2.Brecha Efectiva x UdM'!$H$25:$AK$32,2,0)) -> 69882621 | E59: =VLOOKUP($A59,$A$4:$O$28,2,0)*(HLOOKUP(E$47,'2.2.Brecha Efectiva x UdM'!$H$25:$AK$32,2,0)) -> 70485597 | F59: =VLOOKUP($A59,$A$4:$O$28,2,0)*(HLOOKUP(F$47,'2.2.Brecha Efectiva x UdM'!$H$25:$AK$32,2,0)) -> 43769162 | G59: =VLOOKUP($A59,$A$4:$O$28,2,0)*(HLOOKUP(G$47,'2.2.Brecha Efectiva x UdM'!$H$25:$AK$32,2,0)) -> 34716938 | H59: =VLOOKUP($A59,$A$4:$O$28,2,0)*(HLOOKUP(H$47,'2.2.Brecha Efectiva x UdM'!$H$25:$AK$32,2,0)) -> 18313594 | I59: =VLOOKUP($A59,$A$4:$O$28,2,0)*(HLOOKUP(I$47,'2.2.Brecha Efectiva x UdM'!$H$25:$AK$32,2,0)) -> 18456740 | J59: =VLOOKUP($A59,$A$4:$O$28,2,0)*(HLOOKUP(J$47,'2.2.Brecha Efectiva x UdM'!$H$25:$AK$32,2,0)) -> 18597361 | K59: =VLOOKUP($A59,$A$4:$O$28,2,0)*(HLOOKUP(K$47,'2.2.Brecha Efectiva x UdM'!$H$25:$AK$32,2,0)) -> 17284630 | ... AG59: =VLOOKUP($A59,$A$4:$O$28,2,0)*(HLOOKUP(AG$47,'2.2.Brecha Efectiva x UdM'!$H$25:$AK$32,2,0)) -> 0 | AH59: =SUM(D59:AG59) -> 3.2644929e+08
... A71: =A27 -> Tucumán | B71: =$C$3 -> Nombre UdM 1 | C71: =CONCATENATE(A71," ",B71) -> Tucumán Nombre UdM 1 | D71: =VLOOKUP($A71,$A$4:$O$28,2,0)*(HLOOKUP(D$47,'2.2.Brecha Efectiva x UdM'!$H$25:$AK$32,2,0)) -> 23294207 | E71: =VLOOKUP($A71,$A$4:$O$28,2,0)*(HLOOKUP(E$47,'2.2.Brecha Efectiva x UdM'!$H$25:$AK$32,2,0)) -> 23495199 | F71: =VLOOKUP($A71,$A$4:$O$28,2,0)*(HLOOKUP(F$47,'2.2.Brecha Efectiva x UdM'!$H$25:$AK$32,2,0)) -> 14589721 | G71: =VLOOKUP($A71,$A$4:$O$28,2,0)*(HLOOKUP(G$47,'2.2.Brecha Efectiva x UdM'!$H$25:$AK$32,2,0)) -> 11572313 | H71: =VLOOKUP($A71,$A$4:$O$28,2,0)*(HLOOKUP(H$47,'2.2.Brecha Efectiva x UdM'!$H$25:$AK$32,2,0)) -> 6104531.3 | I71: =VLOOKUP($A71,$A$4:$O$28,2,0)*(HLOOKUP(I$47,'2.2.Brecha Efectiva x UdM'!$H$25:$AK$32,2,0)) -> 6152246.6 | J71: =VLOOKUP($A71,$A$4:$O$28,2,0)*(HLOOKUP(J$47,'2.2.Brecha Efectiva x UdM'!$H$25:$AK$32,2,0)) -> 6199120.5 | K71: =VLOOKUP($A71,$A$4:$O$28,2,0)*(HLOOKUP(K$47,'2.2.Brecha Efectiva x UdM'!$H$25:$AK$32,2,0)) -> 5761543.4 | ... AG71: =VLOOKUP($A71,$A$4:$O$28,2,0)*(HLOOKUP(AG$47,'2.2.Brecha Efectiva x UdM'!$H$25:$AK$32,2,0)) -> 0 | AH71: =SUM(D71:AG71) -> 1.0881643e+08
A72: =CONCATENATE("Total"," ",B48) -> Total Nombre UdM 1 | D72: =SUM(D48:D71) -> 3.944448e+09 | E72: =SUM(E48:E71) -> 3.9784823e+09 | F72: =SUM(F48:F71) -> 2.4705024e+09 | G72: =SUM(G48:G71) -> 1.9595595e+09 | H72: =SUM(H48:H71) -> 1.0336907e+09 | I72: =SUM(I48:I71) -> 1.0417705e+09 | J72: =SUM(J48:J71) -> 1.0497077e+09 | K72: =SUM(K48:K71) -> 9.7561201e+08 | ... AG72: =SUM(AG48:AG71) -> 0 | AH72: =SUM(D72:AG72) -> 1.8426073e+10
A73: =CONCATENATE("Total Acumulado"," ",B48) -> Total Acumulado Nombre UdM 1 | D73: =D72 -> 3.944448e+09 | E73: =E72+D73 -> 7.9229303e+09 | F73: =F72+E73 -> 1.0393433e+10 | G73: =G72+F73 -> 1.2352992e+10 | H73: =H72+G73 -> 1.3386683e+10 | I73: =I72+H73 -> 1.4428453e+10 | J73: =J72+I73 -> 1.5478161e+10 | K73: =K72+J73 -> 1.6453773e+10 | L73: =L72+K73 -> 1.7436453e+10 | ... AG73: =AG72+AF73 -> 1.8426073e+10
A75: Chequeo | D75: =D72='2.2.Brecha Efectiva x UdM'!H26 -> TRUE | E75: =E72='2.2.Brecha Efectiva x UdM'!I26 -> TRUE | F75: =F72='2.2.Brecha Efectiva x UdM'!J26 -> TRUE | G75: =G72='2.2.Brecha Efectiva x UdM'!K26 -> TRUE | H75: =H72='2.2.Brecha Efectiva x UdM'!L26 -> TRUE | I75: =I72='2.2.Brecha Efectiva x UdM'!M26 -> TRUE | J75: =J72='2.2.Brecha Efectiva x UdM'!N26 -> TRUE | K75: =K72='2.2.Brecha Efectiva x UdM'!O26 -> TRUE | L75: =L72='2.2.Brecha Efectiva x UdM'!P26 -> TRUE | M75: =ROUND(M72,0)=ROUND('2.2.Brecha Efectiva x UdM'!Q26,0) -> TRUE
J76: =AG73=SUM('2.2.Brecha Efectiva x UdM'!H26:AK26) -> TRUE
A78: Cuadro 2.3.3.2. Distribución provincial de la UdM 2, por brecha efectiva, en millones de pesos, ajustada en función de la tasa de crecimiento de la Poblacional Nacional.
A80: Provincia | B80: UDM | C80: UDM Provincial | D80: 2024 | E80: 2025 | F80: 2026 | G80: 2027 | H80: 2028 | I80: 2029 | J80: 2030 | K80: 2031 | L80: 2032 | M80: 2033 | N80: 2034 | O80: 2035 | P80: 2036 | Q80: 2037 | R80: 2038 | S80: 2039 | T80: 2040 | U80: 2041 | V80: 2042 | W80: 2043 | X80: 2044 | Y80: 2045 | Z80: 2046 | AA80: 2047 | AB80: 2048 | AC80: 2049 | AD80: 2050 | AE80: 2051 | AF80: 2052 | AG80: 2053 | AH80: TOTAL
A81: =A4 -> Buenos Aires | B81: =$E$3 -> Nombre UdM 2 | C81: =CONCATENATE(A81," ",B81) -> Buenos Aires Nombre UdM 2 | D81: =VLOOKUP($A81,$A$4:$O$28,4,0)*(HLOOKUP(D$80,'2.2.Brecha Efectiva x UdM'!$H$25:$AK$32,3,0)) -> 96500157 | E81: =VLOOKUP($A81,$A$4:$O$28,4,0)*(HLOOKUP(E$80,'2.2.Brecha Efectiva x UdM'!$H$25:$AK$32,3,0)) -> 1.0351849e+08 | F81: =VLOOKUP($A81,$A$4:$O$28,4,0)*(HLOOKUP(F$80,'2.2.Brecha Efectiva x UdM'!$H$25:$AK$32,3,0)) -> 1.5647737e+08 | G81: =VLOOKUP($A81,$A$4:$O$28,4,0)*(HLOOKUP(G$80,'2.2.Brecha Efectiva x UdM'!$H$25:$AK$32,3,0)) -> 0 | H81: =VLOOKUP($A81,$A$4:$O$28,4,0)*(HLOOKUP(H$80,'2.2.Brecha Efectiva x UdM'!$H$25:$AK$32,3,0)) -> 0 | I81: =VLOOKUP($A81,$A$4:$O$28,4,0)*(HLOOKUP(I$80,'2.2.Brecha Efectiva x UdM'!$H$25:$AK$32,3,0)) -> 0 | J81: =VLOOKUP($A81,$A$4:$O$28,4,0)*(HLOOKUP(J$80,'2.2.Brecha Efectiva x UdM'!$H$25:$AK$32,3,0)) -> 0 | K81: =VLOOKUP($A81,$A$4:$O$28,4,0)*(HLOOKUP(K$80,'2.2.Brecha Efectiva x UdM'!$H$25:$AK$32,3,0)) -> 0 | ... AG81: =VLOOKUP($A81,$A$4:$O$28,4,0)*(HLOOKUP(AG$80,'2.2.Brecha Efectiva x UdM'!$H$25:$AK$32,3,0)) -> 0 | AH81: =SUM(D81:AG81) -> 3.5649602e+08
A82: =A5 -> CABA | B82: =$E$3 -> Nombre UdM 2 | C82: =CONCATENATE(A82," ",B82) -> CABA Nombre UdM 2 | D82: =VLOOKUP($A82,$A$4:$O$28,4,0)*(HLOOKUP(D$80,'2.2.Brecha Efectiva x UdM'!$H$25:$AK$32,3,0)) -> 9016157.1 | E82: =VLOOKUP($A82,$A$4:$O$28,4,0)*(HLOOKUP(E$80,'2.2.Brecha Efectiva x UdM'!$H$25:$AK$32,3,0)) -> 9671890.5 | F82: =VLOOKUP($A82,$A$4:$O$28,4,0)*(HLOOKUP(F$80,'2.2.Brecha Efectiva x UdM'!$H$25:$AK$32,3,0)) -> 14619920 | G82: =VLOOKUP($A82,$A$4:$O$28,4,0)*(HLOOKUP(G$80,'2.2.Brecha Efectiva x UdM'!$H$25:$AK$32,3,0)) -> 0 | H82: =VLOOKUP($A82,$A$4:$O$28,4,0)*(HLOOKUP(H$80,'2.2.Brecha Efectiva x UdM'!$H$25:$AK$32,3,0)) -> 0 | I82: =VLOOKUP($A82,$A$4:$O$28,4,0)*(HLOOKUP(I$80,'2.2.Brecha Efectiva x UdM'!$H$25:$AK$32,3,0)) -> 0 | J82: =VLOOKUP($A82,$A$4:$O$28,4,0)*(HLOOKUP(J$80,'2.2.Brecha Efectiva x UdM'!$H$25:$AK$32,3,0)) -> 0 | K82: =VLOOKUP($A82,$A$4:$O$28,4,0)*(HLOOKUP(K$80,'2.2.Brecha Efectiva x UdM'!$H$25:$AK$32,3,0)) -> 0 | ... AG82: =VLOOKUP($A82,$A$4:$O$28,4,0)*(HLOOKUP(AG$80,'2.2.Brecha Efectiva x UdM'!$H$25:$AK$32,3,0)) -> 0 | AH82: =SUM(D82:AG82) -> 33307968
A83: =A6 -> Catamarca | B83: =$E$3 -> Nombre UdM 2 | C83: =CONCATENATE(A83," ",B83) -> Catamarca Nombre UdM 2 | D83: =VLOOKUP($A83,$A$4:$O$28,4,0)*(HLOOKUP(D$80,'2.2.Brecha Efectiva x UdM'!$H$25:$AK$32,3,0)) -> 15354743 | E83: =VLOOKUP($A83,$A$4:$O$28,4,0)*(HLOOKUP(E$80,'2.2.Brecha Efectiva x UdM'!$H$25:$AK$32,3,0)) -> 16471473 | F83: =VLOOKUP($A83,$A$4:$O$28,4,0)*(HLOOKUP(F$80,'2.2.Brecha Efectiva x UdM'!$H$25:$AK$32,3,0)) -> 24898092 | G83: =VLOOKUP($A83,$A$4:$O$28,4,0)*(HLOOKUP(G$80,'2.2.Brecha Efectiva x UdM'!$H$25:$AK$32,3,0)) -> 0 | H83: =VLOOKUP($A83,$A$4:$O$28,4,0)*(HLOOKUP(H$80,'2.2.Brecha Efectiva x UdM'!$H$25:$AK$32,3,0)) -> 0 | I83: =VLOOKUP($A83,$A$4:$O$28,4,0)*(HLOOKUP(I$80,'2.2.Brecha Efectiva x UdM'!$H$25:$AK$32,3,0)) -> 0 | J83: =VLOOKUP($A83,$A$4:$O$28,4,0)*(HLOOKUP(J$80,'2.2.Brecha Efectiva x UdM'!$H$25:$AK$32,3,0)) -> 0 | K83: =VLOOKUP($A83,$A$4:$O$28,4,0)*(HLOOKUP(K$80,'2.2.Brecha Efectiva x UdM'!$H$25:$AK$32,3,0)) -> 0 | ... AG83: =VLOOKUP($A83,$A$4:$O$28,4,0)*(HLOOKUP(AG$80,'2.2.Brecha Efectiva x UdM'!$H$25:$AK$32,3,0)) -> 0 | AH83: =SUM(D83:AG83) -> 56724308
A84: =A7 -> Chaco | B84: =$E$3 -> Nombre UdM 2 | C84: =CONCATENATE(A84," ",B84) -> Chaco Nombre UdM 2 | D84: =VLOOKUP($A84,$A$4:$O$28,4,0)*(HLOOKUP(D$80,'2.2.Brecha Efectiva x UdM'!$H$25:$AK$32,3,0)) -> 22403761 | E84: =VLOOKUP($A84,$A$4:$O$28,4,0)*(HLOOKUP(E$80,'2.2.Brecha Efectiva x UdM'!$H$25:$AK$32,3,0)) -> 24033158 | F84: =VLOOKUP($A84,$A$4:$O$28,4,0)*(HLOOKUP(F$80,'2.2.Brecha Efectiva x UdM'!$H$25:$AK$32,3,0)) -> 36328249 | G84: =VLOOKUP($A84,$A$4:$O$28,4,0)*(HLOOKUP(G$80,'2.2.Brecha Efectiva x UdM'!$H$25:$AK$32,3,0)) -> 0 | H84: =VLOOKUP($A84,$A$4:$O$28,4,0)*(HLOOKUP(H$80,'2.2.Brecha Efectiva x UdM'!$H$25:$AK$32,3,0)) -> 0 | I84: =VLOOKUP($A84,$A$4:$O$28,4,0)*(HLOOKUP(I$80,'2.2.Brecha Efectiva x UdM'!$H$25:$AK$32,3,0)) -> 0 | J84: =VLOOKUP($A84,$A$4:$O$28,4,0)*(HLOOKUP(J$80,'2.2.Brecha Efectiva x UdM'!$H$25:$AK$32,3,0)) -> 0 | K84: =VLOOKUP($A84,$A$4:$O$28,4,0)*(HLOOKUP(K$80,'2.2.Brecha Efectiva x UdM'!$H$25:$AK$32,3,0)) -> 0 | ... AG84: =VLOOKUP($A84,$A$4:$O$28,4,0)*(HLOOKUP(AG$80,'2.2.Brecha Efectiva x UdM'!$H$25:$AK$32,3,0)) -> 0 | AH84: =SUM(D84:AG84) -> 82765168
A85: =A8 -> Chubut | B85: =$E$3 -> Nombre UdM 2 | C85: =CONCATENATE(A85," ",B85) -> Chubut Nombre UdM 2 | D85: =VLOOKUP($A85,$A$4:$O$28,4,0)*(HLOOKUP(D$80,'2.2.Brecha Efectiva x UdM'!$H$25:$AK$32,3,0)) -> 3.7664181e+08 | E85: =VLOOKUP($A85,$A$4:$O$28,4,0)*(HLOOKUP(E$80,'2.2.Brecha Efectiva x UdM'!$H$25:$AK$32,3,0)) -> 4.0403448e+08 | F85: =VLOOKUP($A85,$A$4:$O$28,4,0)*(HLOOKUP(F$80,'2.2.Brecha Efectiva x UdM'!$H$25:$AK$32,3,0)) -> 6.1073393e+08 | G85: =VLOOKUP($A85,$A$4:$O$28,4,0)*(HLOOKUP(G$80,'2.2.Brecha Efectiva x UdM'!$H$25:$AK$32,3,0)) -> 0 | H85: =VLOOKUP($A85,$A$4:$O$28,4,0)*(HLOOKUP(H$80,'2.2.Brecha Efectiva x UdM'!$H$25:$AK$32,3,0)) -> 0 | I85: =VLOOKUP($A85,$A$4:$O$28,4,0)*(HLOOKUP(I$80,'2.2.Brecha Efectiva x UdM'!$H$25:$AK$32,3,0)) -> 0 | J85: =VLOOKUP($A85,$A$4:$O$28,4,0)*(HLOOKUP(J$80,'2.2.Brecha Efectiva x UdM'!$H$25:$AK$32,3,0)) -> 0 | K85: =VLOOKUP($A85,$A$4:$O$28,4,0)*(HLOOKUP(K$80,'2.2.Brecha Efectiva x UdM'!$H$25:$AK$32,3,0)) -> 0 | ... AG85: =VLOOKUP($A85,$A$4:$O$28,4,0)*(HLOOKUP(AG$80,'2.2.Brecha Efectiva x UdM'!$H$25:$AK$32,3,0)) -> 0 | AH85: =SUM(D85:AG85) -> 1.3914102e+09
A86: =A9 -> Córdoba | B86: =$E$3 -> Nombre UdM 2 | C86: =CONCATENATE(A86," ",B86) -> Córdoba Nombre UdM 2 | D86: =VLOOKUP($A86,$A$4:$O$28,4,0)*(HLOOKUP(D$80,'2.2.Brecha Efectiva x UdM'!$H$25:$AK$32,3,0)) -> 18032314 | E86: =VLOOKUP($A86,$A$4:$O$28,4,0)*(HLOOKUP(E$80,'2.2.Brecha Efectiva x UdM'!$H$25:$AK$32,3,0)) -> 19343781 | F86: =VLOOKUP($A86,$A$4:$O$28,4,0)*(HLOOKUP(F$80,'2.2.Brecha Efectiva x UdM'!$H$25:$AK$32,3,0)) -> 29239840 | G86: =VLOOKUP($A86,$A$4:$O$28,4,0)*(HLOOKUP(G$80,'2.2.Brecha Efectiva x UdM'!$H$25:$AK$32,3,0)) -> 0 | H86: =VLOOKUP($A86,$A$4:$O$28,4,0)*(HLOOKUP(H$80,'2.2.Brecha Efectiva x UdM'!$H$25:$AK$32,3,0)) -> 0 | I86: =VLOOKUP($A86,$A$4:$O$28,4,0)*(HLOOKUP(I$80,'2.2.Brecha Efectiva x UdM'!$H$25:$AK$32,3,0)) -> 0 | J86: =VLOOKUP($A86,$A$4:$O$28,4,0)*(HLOOKUP(J$80,'2.2.Brecha Efectiva x UdM'!$H$25:$AK$32,3,0)) -> 0 | K86: =VLOOKUP($A86,$A$4:$O$28,4,0)*(HLOOKUP(K$80,'2.2.Brecha Efectiva x UdM'!$H$25:$AK$32,3,0)) -> 0 | ... AG86: =VLOOKUP($A86,$A$4:$O$28,4,0)*(HLOOKUP(AG$80,'2.2.Brecha Efectiva x UdM'!$H$25:$AK$32,3,0)) -> 0 | AH86: =SUM(D86:AG86) -> 66615935
A87: =A10 -> Corrientes | B87: =$E$3 -> Nombre UdM 2 | C87: =CONCATENATE(A87," ",B87) -> Corrientes Nombre UdM 2 | D87: =VLOOKUP($A87,$A$4:$O$28,4,0)*(HLOOKUP(D$80,'2.2.Brecha Efectiva x UdM'!$H$25:$AK$32,3,0)) -> 96020929 | E87: =VLOOKUP($A87,$A$4:$O$28,4,0)*(HLOOKUP(E$80,'2.2.Brecha Efectiva x UdM'!$H$25:$AK$32,3,0)) -> 1.0300441e+08 | F87: =VLOOKUP($A87,$A$4:$O$28,4,0)*(HLOOKUP(F$80,'2.2.Brecha Efectiva x UdM'!$H$25:$AK$32,3,0)) -> 1.5570029e+08 | G87: =VLOOKUP($A87,$A$4:$O$28,4,0)*(HLOOKUP(G$80,'2.2.Brecha Efectiva x UdM'!$H$25:$AK$32,3,0)) -> 0 | H87: =VLOOKUP($A87,$A$4:$O$28,4,0)*(HLOOKUP(H$80,'2.2.Brecha Efectiva x UdM'!$H$25:$AK$32,3,0)) -> 0 | I87: =VLOOKUP($A87,$A$4:$O$28,4,0)*(HLOOKUP(I$80,'2.2.Brecha Efectiva x UdM'!$H$25:$AK$32,3,0)) -> 0 | J87: =VLOOKUP($A87,$A$4:$O$28,4,0)*(HLOOKUP(J$80,'2.2.Brecha Efectiva x UdM'!$H$25:$AK$32,3,0)) -> 0 | K87: =VLOOKUP($A87,$A$4:$O$28,4,0)*(HLOOKUP(K$80,'2.2.Brecha Efectiva x UdM'!$H$25:$AK$32,3,0)) -> 0 | ... AG87: =VLOOKUP($A87,$A$4:$O$28,4,0)*(HLOOKUP(AG$80,'2.2.Brecha Efectiva x UdM'!$H$25:$AK$32,3,0)) -> 0 | AH87: =SUM(D87:AG87) -> 3.5472563e+08
A88: =A11 -> Entre Ríos | B88: =$E$3 -> Nombre UdM 2 | C88: =CONCATENATE(A88," ",B88) -> Entre Ríos Nombre UdM 2 | D88: =VLOOKUP($A88,$A$4:$O$28,4,0)*(HLOOKUP(D$80,'2.2.Brecha Efectiva x UdM'!$H$25:$AK$32,3,0)) -> 1.5047348e+08 | E88: =VLOOKUP($A88,$A$4:$O$28,4,0)*(HLOOKUP(E$80,'2.2.Brecha Efectiva x UdM'!$H$25:$AK$32,3,0)) -> 1.6141722e+08 | F88: =VLOOKUP($A88,$A$4:$O$28,4,0)*(HLOOKUP(F$80,'2.2.Brecha Efectiva x UdM'!$H$25:$AK$32,3,0)) -> 2.4399644e+08 | G88: =VLOOKUP($A88,$A$4:$O$28,4,0)*(HLOOKUP(G$80,'2.2.Brecha Efectiva x UdM'!$H$25:$AK$32,3,0)) -> 0 | H88: =VLOOKUP($A88,$A$4:$O$28,4,0)*(HLOOKUP(H$80,'2.2.Brecha Efectiva x UdM'!$H$25:$AK$32,3,0)) -> 0 | I88: =VLOOKUP($A88,$A$4:$O$28,4,0)*(HLOOKUP(I$80,'2.2.Brecha Efectiva x UdM'!$H$25:$AK$32,3,0)) -> 0 | J88: =VLOOKUP($A88,$A$4:$O$28,4,0)*(HLOOKUP(J$80,'2.2.Brecha Efectiva x UdM'!$H$25:$AK$32,3,0)) -> 0 | K88: =VLOOKUP($A88,$A$4:$O$28,4,0)*(HLOOKUP(K$80,'2.2.Brecha Efectiva x UdM'!$H$25:$AK$32,3,0)) -> 0 | ... AG88: =VLOOKUP($A88,$A$4:$O$28,4,0)*(HLOOKUP(AG$80,'2.2.Brecha Efectiva x UdM'!$H$25:$AK$32,3,0)) -> 0 | AH88: =SUM(D88:AG88) -> 5.5588714e+08
A89: =A12 -> Formosa | B89: =$E$3 -> Nombre UdM 2 | C89: =CONCATENATE(A89," ",B89) -> Formosa Nombre UdM 2 | D89: =VLOOKUP($A89,$A$4:$O$28,4,0)*(HLOOKUP(D$80,'2.2.Brecha Efectiva x UdM'!$H$25:$AK$32,3,0)) -> 93757755 | E89: =VLOOKUP($A89,$A$4:$O$28,4,0)*(HLOOKUP(E$80,'2.2.Brecha Efectiva x UdM'!$H$25:$AK$32,3,0)) -> 1.0057663e+08 | F89: =VLOOKUP($A89,$A$4:$O$28,4,0)*(HLOOKUP(F$80,'2.2.Brecha Efectiva x UdM'!$H$25:$AK$32,3,0)) -> 1.520305e+08 | G89: =VLOOKUP($A89,$A$4:$O$28,4,0)*(HLOOKUP(G$80,'2.2.Brecha Efectiva x UdM'!$H$25:$AK$32,3,0)) -> 0 | H89: =VLOOKUP($A89,$A$4:$O$28,4,0)*(HLOOKUP(H$80,'2.2.Brecha Efectiva x UdM'!$H$25:$AK$32,3,0)) -> 0 | I89: =VLOOKUP($A89,$A$4:$O$28,4,0)*(HLOOKUP(I$80,'2.2.Brecha Efectiva x UdM'!$H$25:$AK$32,3,0)) -> 0 | J89: =VLOOKUP($A89,$A$4:$O$28,4,0)*(HLOOKUP(J$80,'2.2.Brecha Efectiva x UdM'!$H$25:$AK$32,3,0)) -> 0 | K89: =VLOOKUP($A89,$A$4:$O$28,4,0)*(HLOOKUP(K$80,'2.2.Brecha Efectiva x UdM'!$H$25:$AK$32,3,0)) -> 0 | ... AG89: =VLOOKUP($A89,$A$4:$O$28,4,0)*(HLOOKUP(AG$80,'2.2.Brecha Efectiva x UdM'!$H$25:$AK$32,3,0)) -> 0 | AH89: =SUM(D89:AG89) -> 3.4636489e+08
A90: =A13 -> Jujuy | B90: =$E$3 -> Nombre UdM 2 | C90: =CONCATENATE(A90," ",B90) -> Jujuy Nombre UdM 2 | D90: =VLOOKUP($A90,$A$4:$O$28,4,0)*(HLOOKUP(D$80,'2.2.Brecha Efectiva x UdM'!$H$25:$AK$32,3,0)) -> 65998336 | E90: =VLOOKUP($A90,$A$4:$O$28,4,0)*(HLOOKUP(E$80,'2.2.Brecha Efectiva x UdM'!$H$25:$AK$32,3,0)) -> 70798309 | F90: =VLOOKUP($A90,$A$4:$O$28,4,0)*(HLOOKUP(F$80,'2.2.Brecha Efectiva x UdM'!$H$25:$AK$32,3,0)) -> 1.0701792e+08 | G90: =VLOOKUP($A90,$A$4:$O$28,4,0)*(HLOOKUP(G$80,'2.2.Brecha Efectiva x UdM'!$H$25:$AK$32,3,0)) -> 0 | H90: =VLOOKUP($A90,$A$4:$O$28,4,0)*(HLOOKUP(H$80,'2.2.Brecha Efectiva x UdM'!$H$25:$AK$32,3,0)) -> 0 | I90: =VLOOKUP($A90,$A$4:$O$28,4,0)*(HLOOKUP(I$80,'2.2.Brecha Efectiva x UdM'!$H$25:$AK$32,3,0)) -> 0 | J90: =VLOOKUP($A90,$A$4:$O$28,4,0)*(HLOOKUP(J$80,'2.2.Brecha Efectiva x UdM'!$H$25:$AK$32,3,0)) -> 0 | K90: =VLOOKUP($A90,$A$4:$O$28,4,0)*(HLOOKUP(K$80,'2.2.Brecha Efectiva x UdM'!$H$25:$AK$32,3,0)) -> 0 | ... AG90: =VLOOKUP($A90,$A$4:$O$28,4,0)*(HLOOKUP(AG$80,'2.2.Brecha Efectiva x UdM'!$H$25:$AK$32,3,0)) -> 0 | AH90: =SUM(D90:AG90) -> 2.4381456e+08
A91: =A14 -> La Pampa | B91: =$E$3 -> Nombre UdM 2 | C91: =CONCATENATE(A91," ",B91) -> La Pampa Nombre UdM 2 | D91: =VLOOKUP($A91,$A$4:$O$28,4,0)*(HLOOKUP(D$80,'2.2.Brecha Efectiva x UdM'!$H$25:$AK$32,3,0)) -> 9016157.1 | E91: =VLOOKUP($A91,$A$4:$O$28,4,0)*(HLOOKUP(E$80,'2.2.Brecha Efectiva x UdM'!$H$25:$AK$32,3,0)) -> 9671890.5 | F91: =VLOOKUP($A91,$A$4:$O$28,4,0)*(HLOOKUP(F$80,'2.2.Brecha Efectiva x UdM'!$H$25:$AK$32,3,0)) -> 14619920 | G91: =VLOOKUP($A91,$A$4:$O$28,4,0)*(HLOOKUP(G$80,'2.2.Brecha Efectiva x UdM'!$H$25:$AK$32,3,0)) -> 0 | H91: =VLOOKUP($A91,$A$4:$O$28,4,0)*(HLOOKUP(H$80,'2.2.Brecha Efectiva x UdM'!$H$25:$AK$32,3,0)) -> 0 | I91: =VLOOKUP($A91,$A$4:$O$28,4,0)*(HLOOKUP(I$80,'2.2.Brecha Efectiva x UdM'!$H$25:$AK$32,3,0)) -> 0 | J91: =VLOOKUP($A91,$A$4:$O$28,4,0)*(HLOOKUP(J$80,'2.2.Brecha Efectiva x UdM'!$H$25:$AK$32,3,0)) -> 0 | K91: =VLOOKUP($A91,$A$4:$O$28,4,0)*(HLOOKUP(K$80,'2.2.Brecha Efectiva x UdM'!$H$25:$AK$32,3,0)) -> 0 | ... AG91: =VLOOKUP($A91,$A$4:$O$28,4,0)*(HLOOKUP(AG$80,'2.2.Brecha Efectiva x UdM'!$H$25:$AK$32,3,0)) -> 0 | AH91: =SUM(D91:AG91) -> 33307968
A92: =A15 -> La Rioja | B92: =$E$3 -> Nombre UdM 2 | C92: =CONCATENATE(A92," ",B92) -> La Rioja Nombre UdM 2 | D92: =VLOOKUP($A92,$A$4:$O$28,4,0)*(HLOOKUP(D$80,'2.2.Brecha Efectiva x UdM'!$H$25:$AK$32,3,0)) -> 16693529 | E92: =VLOOKUP($A92,$A$4:$O$28,4,0)*(HLOOKUP(E$80,'2.2.Brecha Efectiva x UdM'!$H$25:$AK$32,3,0)) -> 17907627 | F92: =VLOOKUP($A92,$A$4:$O$28,4,0)*(HLOOKUP(F$80,'2.2.Brecha Efectiva x UdM'!$H$25:$AK$32,3,0)) -> 27068966 | G92: =VLOOKUP($A92,$A$4:$O$28,4,0)*(HLOOKUP(G$80,'2.2.Brecha Efectiva x UdM'!$H$25:$AK$32,3,0)) -> 0 | H92: =VLOOKUP($A92,$A$4:$O$28,4,0)*(HLOOKUP(H$80,'2.2.Brecha Efectiva x UdM'!$H$25:$AK$32,3,0)) -> 0 | I92: =VLOOKUP($A92,$A$4:$O$28,4,0)*(HLOOKUP(I$80,'2.2.Brecha Efectiva x UdM'!$H$25:$AK$32,3,0)) -> 0 | J92: =VLOOKUP($A92,$A$4:$O$28,4,0)*(HLOOKUP(J$80,'2.2.Brecha Efectiva x UdM'!$H$25:$AK$32,3,0)) -> 0 | K92: =VLOOKUP($A92,$A$4:$O$28,4,0)*(HLOOKUP(K$80,'2.2.Brecha Efectiva x UdM'!$H$25:$AK$32,3,0)) -> 0 | ... AG92: =VLOOKUP($A92,$A$4:$O$28,4,0)*(HLOOKUP(AG$80,'2.2.Brecha Efectiva x UdM'!$H$25:$AK$32,3,0)) -> 0 | AH92: =SUM(D92:AG92) -> 61670122
... A104: =A27 -> Tucumán | B104: =$E$3 -> Nombre UdM 2 | C104: =CONCATENATE(A104," ",B104) -> Tucumán Nombre UdM 2 | D104: =VLOOKUP($A104,$A$4:$O$28,4,0)*(HLOOKUP(D$80,'2.2.Brecha Efectiva x UdM'!$H$25:$AK$32,3,0)) -> 9016157.1 | E104: =VLOOKUP($A104,$A$4:$O$28,4,0)*(HLOOKUP(E$80,'2.2.Brecha Efectiva x UdM'!$H$25:$AK$32,3,0)) -> 9671890.5 | F104: =VLOOKUP($A104,$A$4:$O$28,4,0)*(HLOOKUP(F$80,'2.2.Brecha Efectiva x UdM'!$H$25:$AK$32,3,0)) -> 14619920 | G104: =VLOOKUP($A104,$A$4:$O$28,4,0)*(HLOOKUP(G$80,'2.2.Brecha Efectiva x UdM'!$H$25:$AK$32,3,0)) -> 0 | H104: =VLOOKUP($A104,$A$4:$O$28,4,0)*(HLOOKUP(H$80,'2.2.Brecha Efectiva x UdM'!$H$25:$AK$32,3,0)) -> 0 | I104: =VLOOKUP($A104,$A$4:$O$28,4,0)*(HLOOKUP(I$80,'2.2.Brecha Efectiva x UdM'!$H$25:$AK$32,3,0)) -> 0 | J104: =VLOOKUP($A104,$A$4:$O$28,4,0)*(HLOOKUP(J$80,'2.2.Brecha Efectiva x UdM'!$H$25:$AK$32,3,0)) -> 0 | K104: =VLOOKUP($A104,$A$4:$O$28,4,0)*(HLOOKUP(K$80,'2.2.Brecha Efectiva x UdM'!$H$25:$AK$32,3,0)) -> 0 | ... AG104: =VLOOKUP($A104,$A$4:$O$28,4,0)*(HLOOKUP(AG$80,'2.2.Brecha Efectiva x UdM'!$H$25:$AK$32,3,0)) -> 0 | AH104: =SUM(D104:AG104) -> 33307968
A105: =CONCATENATE("Total"," ",B81) -> Total Nombre UdM 2 | D105: =SUM(D81:D104) -> 2.7610423e+09 | E105: =SUM(E81:E104) -> 2.9618493e+09 | F105: =SUM(F81:F104) -> 4.4770978e+09 | G105: =SUM(G81:G104) -> 0 | H105: =SUM(H81:H104) -> 0 | I105: =SUM(I81:I104) -> 0 | J105: =SUM(J81:J104) -> 0 | K105: =SUM(K81:K104) -> 0 | ... AG105: =SUM(AG81:AG104) -> 0 | AH105: =SUM(D105:AG105) -> 1.0199989e+10
A106: =CONCATENATE("Total Acumulado"," ",B81) -> Total Acumulado Nombre UdM 2 | D106: =D105 -> 2.7610423e+09 | E106: =E105+D106 -> 5.7228917e+09 | F106: =F105+E106 -> 1.0199989e+10 | G106: =G105+F106 -> 1.0199989e+10 | H106: =H105+G106 -> 1.0199989e+10 | I106: =I105+H106 -> 1.0199989e+10 | J106: =J105+I106 -> 1.0199989e+10 | K106: =K105+J106 -> 1.0199989e+10 | L106: =L105+K106 -> 1.0199989e+10 | ... AG106: =AG105+AF106 -> 1.0199989e+10
A108: Chequeo | D108: =D105='2.2.Brecha Efectiva x UdM'!H27 -> TRUE | E108: =E105='2.2.Brecha Efectiva x UdM'!I27 -> TRUE | F108: =F105='2.2.Brecha Efectiva x UdM'!J27 -> FALSE | G108: =G105='2.2.Brecha Efectiva x UdM'!K27 -> TRUE
G109: =AG106=SUM('2.2.Brecha Efectiva x UdM'!H27:AK27) -> TRUE
A111: Cuadro 2.3.3.3. Distribución provincial de la UdM 3, por brecha efectiva, en millones de pesos, ajustada en función de la tasa de crecimiento de la Poblacional Nacional.
A113: Provincia | B113: UDM | C113: UDM Provincial | D113: 2024 | E113: 2025 | F113: 2026 | G113: 2027 | H113: 2028 | I113: 2029 | J113: 2030 | K113: 2031 | L113: 2032 | M113: 2033 | N113: 2034 | O113: 2035 | P113: 2036 | Q113: 2037 | R113: 2038 | S113: 2039 | T113: 2040 | U113: 2041 | V113: 2042 | W113: 2043 | X113: 2044 | Y113: 2045 | Z113: 2046 | AA113: 2047 | AB113: 2048 | AC113: 2049 | AD113: 2050 | AE113: 2051 | AF113: 2052 | AG113: 2053 | AH113: TOTAL
A114: =A4 -> Buenos Aires | B114: =$G$3 -> Nombre UdM 3 | C114: =CONCATENATE(A114," ",B114) -> Buenos Aires Nombre UdM 3 | D114: =VLOOKUP($A114,$A$4:$O$28,6,0)*(HLOOKUP(D$113,'2.2.Brecha Efectiva x UdM'!$H$25:$AK$32,4,0)) -> 7.2700119e+08 | E114: =VLOOKUP($A114,$A$4:$O$28,6,0)*(HLOOKUP(E$113,'2.2.Brecha Efectiva x UdM'!$H$25:$AK$32,4,0)) -> 4.9415383e+09 | F114: =VLOOKUP($A114,$A$4:$O$28,6,0)*(HLOOKUP(F$113,'2.2.Brecha Efectiva x UdM'!$H$25:$AK$32,4,0)) -> 2.5117649e+08 | G114: =VLOOKUP($A114,$A$4:$O$28,6,0)*(HLOOKUP(G$113,'2.2.Brecha Efectiva x UdM'!$H$25:$AK$32,4,0)) -> 1.3742414e+08 | H114: =VLOOKUP($A114,$A$4:$O$28,6,0)*(HLOOKUP(H$113,'2.2.Brecha Efectiva x UdM'!$H$25:$AK$32,4,0)) -> 0 | I114: =VLOOKUP($A114,$A$4:$O$28,6,0)*(HLOOKUP(I$113,'2.2.Brecha Efectiva x UdM'!$H$25:$AK$32,4,0)) -> 0 | J114: =VLOOKUP($A114,$A$4:$O$28,6,0)*(HLOOKUP(J$113,'2.2.Brecha Efectiva x UdM'!$H$25:$AK$32,4,0)) -> 0 | K114: =VLOOKUP($A114,$A$4:$O$28,6,0)*(HLOOKUP(K$113,'2.2.Brecha Efectiva x UdM'!$H$25:$AK$32,4,0)) -> 0 | ... AG114: =VLOOKUP($A114,$A$4:$O$28,6,0)*(HLOOKUP(AG$113,'2.2.Brecha Efectiva x UdM'!$H$25:$AK$32,4,0)) -> 0 | AH114: =SUM(D114:AG114) -> 6.0571401e+09
A115: =A5 -> CABA | B115: =$G$3 -> Nombre UdM 3 | C115: =CONCATENATE(A115," ",B115) -> CABA Nombre UdM 3 | D115: =VLOOKUP($A115,$A$4:$O$28,6,0)*(HLOOKUP(D$113,'2.2.Brecha Efectiva x UdM'!$H$25:$AK$32,4,0)) -> 22886073 | E115: =VLOOKUP($A115,$A$4:$O$28,6,0)*(HLOOKUP(E$113,'2.2.Brecha Efectiva x UdM'!$H$25:$AK$32,4,0)) -> 1.5556014e+08 | F115: =VLOOKUP($A115,$A$4:$O$28,6,0)*(HLOOKUP(F$113,'2.2.Brecha Efectiva x UdM'!$H$25:$AK$32,4,0)) -> 7907062.1 | G115: =VLOOKUP($A115,$A$4:$O$28,6,0)*(HLOOKUP(G$113,'2.2.Brecha Efectiva x UdM'!$H$25:$AK$32,4,0)) -> 4326126.2 | H115: =VLOOKUP($A115,$A$4:$O$28,6,0)*(HLOOKUP(H$113,'2.2.Brecha Efectiva x UdM'!$H$25:$AK$32,4,0)) -> 0 | I115: =VLOOKUP($A115,$A$4:$O$28,6,0)*(HLOOKUP(I$113,'2.2.Brecha Efectiva x UdM'!$H$25:$AK$32,4,0)) -> 0 | J115: =VLOOKUP($A115,$A$4:$O$28,6,0)*(HLOOKUP(J$113,'2.2.Brecha Efectiva x UdM'!$H$25:$AK$32,4,0)) -> 0 | K115: =VLOOKUP($A115,$A$4:$O$28,6,0)*(HLOOKUP(K$113,'2.2.Brecha Efectiva x UdM'!$H$25:$AK$32,4,0)) -> 0 | ... AG115: =VLOOKUP($A115,$A$4:$O$28,6,0)*(HLOOKUP(AG$113,'2.2.Brecha Efectiva x UdM'!$H$25:$AK$32,4,0)) -> 0 | AH115: =SUM(D115:AG115) -> 1.906794e+08
A116: =A6 -> Catamarca | B116: =$G$3 -> Nombre UdM 3 | C116: =CONCATENATE(A116," ",B116) -> Catamarca Nombre UdM 3 | D116: =VLOOKUP($A116,$A$4:$O$28,6,0)*(HLOOKUP(D$113,'2.2.Brecha Efectiva x UdM'!$H$25:$AK$32,4,0)) -> 0 | E116: =VLOOKUP($A116,$A$4:$O$28,6,0)*(HLOOKUP(E$113,'2.2.Brecha Efectiva x UdM'!$H$25:$AK$32,4,0)) -> 0 | F116: =VLOOKUP($A116,$A$4:$O$28,6,0)*(HLOOKUP(F$113,'2.2.Brecha Efectiva x UdM'!$H$25:$AK$32,4,0)) -> 0 | G116: =VLOOKUP($A116,$A$4:$O$28,6,0)*(HLOOKUP(G$113,'2.2.Brecha Efectiva x UdM'!$H$25:$AK$32,4,0)) -> 0 | H116: =VLOOKUP($A116,$A$4:$O$28,6,0)*(HLOOKUP(H$113,'2.2.Brecha Efectiva x UdM'!$H$25:$AK$32,4,0)) -> 0 | I116: =VLOOKUP($A116,$A$4:$O$28,6,0)*(HLOOKUP(I$113,'2.2.Brecha Efectiva x UdM'!$H$25:$AK$32,4,0)) -> 0 | J116: =VLOOKUP($A116,$A$4:$O$28,6,0)*(HLOOKUP(J$113,'2.2.Brecha Efectiva x UdM'!$H$25:$AK$32,4,0)) -> 0 | K116: =VLOOKUP($A116,$A$4:$O$28,6,0)*(HLOOKUP(K$113,'2.2.Brecha Efectiva x UdM'!$H$25:$AK$32,4,0)) -> 0 | ... AG116: =VLOOKUP($A116,$A$4:$O$28,6,0)*(HLOOKUP(AG$113,'2.2.Brecha Efectiva x UdM'!$H$25:$AK$32,4,0)) -> 0 | AH116: =SUM(D116:AG116) -> 0
A117: =A7 -> Chaco | B117: =$G$3 -> Nombre UdM 3 | C117: =CONCATENATE(A117," ",B117) -> Chaco Nombre UdM 3 | D117: =VLOOKUP($A117,$A$4:$O$28,6,0)*(HLOOKUP(D$113,'2.2.Brecha Efectiva x UdM'!$H$25:$AK$32,4,0)) -> 0 | E117: =VLOOKUP($A117,$A$4:$O$28,6,0)*(HLOOKUP(E$113,'2.2.Brecha Efectiva x UdM'!$H$25:$AK$32,4,0)) -> 0 | F117: =VLOOKUP($A117,$A$4:$O$28,6,0)*(HLOOKUP(F$113,'2.2.Brecha Efectiva x UdM'!$H$25:$AK$32,4,0)) -> 0 | G117: =VLOOKUP($A117,$A$4:$O$28,6,0)*(HLOOKUP(G$113,'2.2.Brecha Efectiva x UdM'!$H$25:$AK$32,4,0)) -> 0 | H117: =VLOOKUP($A117,$A$4:$O$28,6,0)*(HLOOKUP(H$113,'2.2.Brecha Efectiva x UdM'!$H$25:$AK$32,4,0)) -> 0 | I117: =VLOOKUP($A117,$A$4:$O$28,6,0)*(HLOOKUP(I$113,'2.2.Brecha Efectiva x UdM'!$H$25:$AK$32,4,0)) -> 0 | J117: =VLOOKUP($A117,$A$4:$O$28,6,0)*(HLOOKUP(J$113,'2.2.Brecha Efectiva x UdM'!$H$25:$AK$32,4,0)) -> 0 | K117: =VLOOKUP($A117,$A$4:$O$28,6,0)*(HLOOKUP(K$113,'2.2.Brecha Efectiva x UdM'!$H$25:$AK$32,4,0)) -> 0 | ... AG117: =VLOOKUP($A117,$A$4:$O$28,6,0)*(HLOOKUP(AG$113,'2.2.Brecha Efectiva x UdM'!$H$25:$AK$32,4,0)) -> 0 | AH117: =SUM(D117:AG117) -> 0
A118: =A8 -> Chubut | B118: =$G$3 -> Nombre UdM 3 | C118: =CONCATENATE(A118," ",B118) -> Chubut Nombre UdM 3 | D118: =VLOOKUP($A118,$A$4:$O$28,6,0)*(HLOOKUP(D$113,'2.2.Brecha Efectiva x UdM'!$H$25:$AK$32,4,0)) -> 17631927 | E118: =VLOOKUP($A118,$A$4:$O$28,6,0)*(HLOOKUP(E$113,'2.2.Brecha Efectiva x UdM'!$H$25:$AK$32,4,0)) -> 1.198469e+08 | F118: =VLOOKUP($A118,$A$4:$O$28,6,0)*(HLOOKUP(F$113,'2.2.Brecha Efectiva x UdM'!$H$25:$AK$32,4,0)) -> 6091772 | G118: =VLOOKUP($A118,$A$4:$O$28,6,0)*(HLOOKUP(G$113,'2.2.Brecha Efectiva x UdM'!$H$25:$AK$32,4,0)) -> 3332941.4 | H118: =VLOOKUP($A118,$A$4:$O$28,6,0)*(HLOOKUP(H$113,'2.2.Brecha Efectiva x UdM'!$H$25:$AK$32,4,0)) -> 0 | I118: =VLOOKUP($A118,$A$4:$O$28,6,0)*(HLOOKUP(I$113,'2.2.Brecha Efectiva x UdM'!$H$25:$AK$32,4,0)) -> 0 | J118: =VLOOKUP($A118,$A$4:$O$28,6,0)*(HLOOKUP(J$113,'2.2.Brecha Efectiva x UdM'!$H$25:$AK$32,4,0)) -> 0 | K118: =VLOOKUP($A118,$A$4:$O$28,6,0)*(HLOOKUP(K$113,'2.2.Brecha Efectiva x UdM'!$H$25:$AK$32,4,0)) -> 0 | ... AG118: =VLOOKUP($A118,$A$4:$O$28,6,0)*(HLOOKUP(AG$113,'2.2.Brecha Efectiva x UdM'!$H$25:$AK$32,4,0)) -> 0 | AH118: =SUM(D118:AG118) -> 1.4690354e+08
A119: =A9 -> Córdoba | B119: =$G$3 -> Nombre UdM 3 | C119: =CONCATENATE(A119," ",B119) -> Córdoba Nombre UdM 3 | D119: =VLOOKUP($A119,$A$4:$O$28,6,0)*(HLOOKUP(D$113,'2.2.Brecha Efectiva x UdM'!$H$25:$AK$32,4,0)) -> 8471476.8 | E119: =VLOOKUP($A119,$A$4:$O$28,6,0)*(HLOOKUP(E$113,'2.2.Brecha Efectiva x UdM'!$H$25:$AK$32,4,0)) -> 57581924 | F119: =VLOOKUP($A119,$A$4:$O$28,6,0)*(HLOOKUP(F$113,'2.2.Brecha Efectiva x UdM'!$H$25:$AK$32,4,0)) -> 2926867.1 | G119: =VLOOKUP($A119,$A$4:$O$28,6,0)*(HLOOKUP(G$113,'2.2.Brecha Efectiva x UdM'!$H$25:$AK$32,4,0)) -> 1601352.8 | H119: =VLOOKUP($A119,$A$4:$O$28,6,0)*(HLOOKUP(H$113,'2.2.Brecha Efectiva x UdM'!$H$25:$AK$32,4,0)) -> 0 | I119: =VLOOKUP($A119,$A$4:$O$28,6,0)*(HLOOKUP(I$113,'2.2.Brecha Efectiva x UdM'!$H$25:$AK$32,4,0)) -> 0 | J119: =VLOOKUP($A119,$A$4:$O$28,6,0)*(HLOOKUP(J$113,'2.2.Brecha Efectiva x UdM'!$H$25:$AK$32,4,0)) -> 0 | K119: =VLOOKUP($A119,$A$4:$O$28,6,0)*(HLOOKUP(K$113,'2.2.Brecha Efectiva x UdM'!$H$25:$AK$32,4,0)) -> 0 | ... AG119: =VLOOKUP($A119,$A$4:$O$28,6,0)*(HLOOKUP(AG$113,'2.2.Brecha Efectiva x UdM'!$H$25:$AK$32,4,0)) -> 0 | AH119: =SUM(D119:AG119) -> 70581620
A120: =A10 -> Corrientes | B120: =$G$3 -> Nombre UdM 3 | C120: =CONCATENATE(A120," ",B120) -> Corrientes Nombre UdM 3 | D120: =VLOOKUP($A120,$A$4:$O$28,6,0)*(HLOOKUP(D$113,'2.2.Brecha Efectiva x UdM'!$H$25:$AK$32,4,0)) -> 4192649.1 | E120: =VLOOKUP($A120,$A$4:$O$28,6,0)*(HLOOKUP(E$113,'2.2.Brecha Efectiva x UdM'!$H$25:$AK$32,4,0)) -> 28498077 | F120: =VLOOKUP($A120,$A$4:$O$28,6,0)*(HLOOKUP(F$113,'2.2.Brecha Efectiva x UdM'!$H$25:$AK$32,4,0)) -> 1448546.3 | G120: =VLOOKUP($A120,$A$4:$O$28,6,0)*(HLOOKUP(G$113,'2.2.Brecha Efectiva x UdM'!$H$25:$AK$32,4,0)) -> 792531.3 | H120: =VLOOKUP($A120,$A$4:$O$28,6,0)*(HLOOKUP(H$113,'2.2.Brecha Efectiva x UdM'!$H$25:$AK$32,4,0)) -> 0 | I120: =VLOOKUP($A120,$A$4:$O$28,6,0)*(HLOOKUP(I$113,'2.2.Brecha Efectiva x UdM'!$H$25:$AK$32,4,0)) -> 0 | J120: =VLOOKUP($A120,$A$4:$O$28,6,0)*(HLOOKUP(J$113,'2.2.Brecha Efectiva x UdM'!$H$25:$AK$32,4,0)) -> 0 | K120: =VLOOKUP($A120,$A$4:$O$28,6,0)*(HLOOKUP(K$113,'2.2.Brecha Efectiva x UdM'!$H$25:$AK$32,4,0)) -> 0 | ... AG120: =VLOOKUP($A120,$A$4:$O$28,6,0)*(HLOOKUP(AG$113,'2.2.Brecha Efectiva x UdM'!$H$25:$AK$32,4,0)) -> 0 | AH120: =SUM(D120:AG120) -> 34931804
A121: =A11 -> Entre Ríos | B121: =$G$3 -> Nombre UdM 3 | C121: =CONCATENATE(A121," ",B121) -> Entre Ríos Nombre UdM 3 | D121: =VLOOKUP($A121,$A$4:$O$28,6,0)*(HLOOKUP(D$113,'2.2.Brecha Efectiva x UdM'!$H$25:$AK$32,4,0)) -> 2923087.6 | E121: =VLOOKUP($A121,$A$4:$O$28,6,0)*(HLOOKUP(E$113,'2.2.Brecha Efectiva x UdM'!$H$25:$AK$32,4,0)) -> 19868673 | F121: =VLOOKUP($A121,$A$4:$O$28,6,0)*(HLOOKUP(F$113,'2.2.Brecha Efectiva x UdM'!$H$25:$AK$32,4,0)) -> 1009917 | G121: =VLOOKUP($A121,$A$4:$O$28,6,0)*(HLOOKUP(G$113,'2.2.Brecha Efectiva x UdM'!$H$25:$AK$32,4,0)) -> 552547.65 | H121: =VLOOKUP($A121,$A$4:$O$28,6,0)*(HLOOKUP(H$113,'2.2.Brecha Efectiva x UdM'!$H$25:$AK$32,4,0)) -> 0 | I121: =VLOOKUP($A121,$A$4:$O$28,6,0)*(HLOOKUP(I$113,'2.2.Brecha Efectiva x UdM'!$H$25:$AK$32,4,0)) -> 0 | J121: =VLOOKUP($A121,$A$4:$O$28,6,0)*(HLOOKUP(J$113,'2.2.Brecha Efectiva x UdM'!$H$25:$AK$32,4,0)) -> 0 | K121: =VLOOKUP($A121,$A$4:$O$28,6,0)*(HLOOKUP(K$113,'2.2.Brecha Efectiva x UdM'!$H$25:$AK$32,4,0)) -> 0 | ... AG121: =VLOOKUP($A121,$A$4:$O$28,6,0)*(HLOOKUP(AG$113,'2.2.Brecha Efectiva x UdM'!$H$25:$AK$32,4,0)) -> 0 | AH121: =SUM(D121:AG121) -> 24354225
A122: =A12 -> Formosa | B122: =$G$3 -> Nombre UdM 3 | C122: =CONCATENATE(A122," ",B122) -> Formosa Nombre UdM 3 | D122: =VLOOKUP($A122,$A$4:$O$28,6,0)*(HLOOKUP(D$113,'2.2.Brecha Efectiva x UdM'!$H$25:$AK$32,4,0)) -> 0 | E122: =VLOOKUP($A122,$A$4:$O$28,6,0)*(HLOOKUP(E$113,'2.2.Brecha Efectiva x UdM'!$H$25:$AK$32,4,0)) -> 0 | F122: =VLOOKUP($A122,$A$4:$O$28,6,0)*(HLOOKUP(F$113,'2.2.Brecha Efectiva x UdM'!$H$25:$AK$32,4,0)) -> 0 | G122: =VLOOKUP($A122,$A$4:$O$28,6,0)*(HLOOKUP(G$113,'2.2.Brecha Efectiva x UdM'!$H$25:$AK$32,4,0)) -> 0 | H122: =VLOOKUP($A122,$A$4:$O$28,6,0)*(HLOOKUP(H$113,'2.2.Brecha Efectiva x UdM'!$H$25:$AK$32,4,0)) -> 0 | I122: =VLOOKUP($A122,$A$4:$O$28,6,0)*(HLOOKUP(I$113,'2.2.Brecha Efectiva x UdM'!$H$25:$AK$32,4,0)) -> 0 | J122: =VLOOKUP($A122,$A$4:$O$28,6,0)*(HLOOKUP(J$113,'2.2.Brecha Efectiva x UdM'!$H$25:$AK$32,4,0)) -> 0 | K122: =VLOOKUP($A122,$A$4:$O$28,6,0)*(HLOOKUP(K$113,'2.2.Brecha Efectiva x UdM'!$H$25:$AK$32,4,0)) -> 0 | ... AG122: =VLOOKUP($A122,$A$4:$O$28,6,0)*(HLOOKUP(AG$113,'2.2.Brecha Efectiva x UdM'!$H$25:$AK$32,4,0)) -> 0 | AH122: =SUM(D122:AG122) -> 0
A123: =A13 -> Jujuy | B123: =$G$3 -> Nombre UdM 3 | C123: =CONCATENATE(A123," ",B123) -> Jujuy Nombre UdM 3 | D123: =VLOOKUP($A123,$A$4:$O$28,6,0)*(HLOOKUP(D$113,'2.2.Brecha Efectiva x UdM'!$H$25:$AK$32,4,0)) -> 0 | E123: =VLOOKUP($A123,$A$4:$O$28,6,0)*(HLOOKUP(E$113,'2.2.Brecha Efectiva x UdM'!$H$25:$AK$32,4,0)) -> 0 | F123: =VLOOKUP($A123,$A$4:$O$28,6,0)*(HLOOKUP(F$113,'2.2.Brecha Efectiva x UdM'!$H$25:$AK$32,4,0)) -> 0 | G123: =VLOOKUP($A123,$A$4:$O$28,6,0)*(HLOOKUP(G$113,'2.2.Brecha Efectiva x UdM'!$H$25:$AK$32,4,0)) -> 0 | H123: =VLOOKUP($A123,$A$4:$O$28,6,0)*(HLOOKUP(H$113,'2.2.Brecha Efectiva x UdM'!$H$25:$AK$32,4,0)) -> 0 | I123: =VLOOKUP($A123,$A$4:$O$28,6,0)*(HLOOKUP(I$113,'2.2.Brecha Efectiva x UdM'!$H$25:$AK$32,4,0)) -> 0 | J123: =VLOOKUP($A123,$A$4:$O$28,6,0)*(HLOOKUP(J$113,'2.2.Brecha Efectiva x UdM'!$H$25:$AK$32,4,0)) -> 0 | K123: =VLOOKUP($A123,$A$4:$O$28,6,0)*(HLOOKUP(K$113,'2.2.Brecha Efectiva x UdM'!$H$25:$AK$32,4,0)) -> 0 | ... AG123: =VLOOKUP($A123,$A$4:$O$28,6,0)*(HLOOKUP(AG$113,'2.2.Brecha Efectiva x UdM'!$H$25:$AK$32,4,0)) -> 0 | AH123: =SUM(D123:AG123) -> 0
A124: =A14 -> La Pampa | B124: =$G$3 -> Nombre UdM 3 | C124: =CONCATENATE(A124," ",B124) -> La Pampa Nombre UdM 3 | D124: =VLOOKUP($A124,$A$4:$O$28,6,0)*(HLOOKUP(D$113,'2.2.Brecha Efectiva x UdM'!$H$25:$AK$32,4,0)) -> 0 | E124: =VLOOKUP($A124,$A$4:$O$28,6,0)*(HLOOKUP(E$113,'2.2.Brecha Efectiva x UdM'!$H$25:$AK$32,4,0)) -> 0 | F124: =VLOOKUP($A124,$A$4:$O$28,6,0)*(HLOOKUP(F$113,'2.2.Brecha Efectiva x UdM'!$H$25:$AK$32,4,0)) -> 0 | G124: =VLOOKUP($A124,$A$4:$O$28,6,0)*(HLOOKUP(G$113,'2.2.Brecha Efectiva x UdM'!$H$25:$AK$32,4,0)) -> 0 | H124: =VLOOKUP($A124,$A$4:$O$28,6,0)*(HLOOKUP(H$113,'2.2.Brecha Efectiva x UdM'!$H$25:$AK$32,4,0)) -> 0 | I124: =VLOOKUP($A124,$A$4:$O$28,6,0)*(HLOOKUP(I$113,'2.2.Brecha Efectiva x UdM'!$H$25:$AK$32,4,0)) -> 0 | J124: =VLOOKUP($A124,$A$4:$O$28,6,0)*(HLOOKUP(J$113,'2.2.Brecha Efectiva x UdM'!$H$25:$AK$32,4,0)) -> 0 | K124: =VLOOKUP($A124,$A$4:$O$28,6,0)*(HLOOKUP(K$113,'2.2.Brecha Efectiva x UdM'!$H$25:$AK$32,4,0)) -> 0 | ... AG124: =VLOOKUP($A124,$A$4:$O$28,6,0)*(HLOOKUP(AG$113,'2.2.Brecha Efectiva x UdM'!$H$25:$AK$32,4,0)) -> 0 | AH124: =SUM(D124:AG124) -> 0
A125: =A15 -> La Rioja | B125: =$G$3 -> Nombre UdM 3 | C125: =CONCATENATE(A125," ",B125) -> La Rioja Nombre UdM 3 | D125: =VLOOKUP($A125,$A$4:$O$28,6,0)*(HLOOKUP(D$113,'2.2.Brecha Efectiva x UdM'!$H$25:$AK$32,4,0)) -> 0 | E125: =VLOOKUP($A125,$A$4:$O$28,6,0)*(HLOOKUP(E$113,'2.2.Brecha Efectiva x UdM'!$H$25:$AK$32,4,0)) -> 0 | F125: =VLOOKUP($A125,$A$4:$O$28,6,0)*(HLOOKUP(F$113,'2.2.Brecha Efectiva x UdM'!$H$25:$AK$32,4,0)) -> 0 | G125: =VLOOKUP($A125,$A$4:$O$28,6,0)*(HLOOKUP(G$113,'2.2.Brecha Efectiva x UdM'!$H$25:$AK$32,4,0)) -> 0 | H125: =VLOOKUP($A125,$A$4:$O$28,6,0)*(HLOOKUP(H$113,'2.2.Brecha Efectiva x UdM'!$H$25:$AK$32,4,0)) -> 0 | I125: =VLOOKUP($A125,$A$4:$O$28,6,0)*(HLOOKUP(I$113,'2.2.Brecha Efectiva x UdM'!$H$25:$AK$32,4,0)) -> 0 | J125: =VLOOKUP($A125,$A$4:$O$28,6,0)*(HLOOKUP(J$113,'2.2.Brecha Efectiva x UdM'!$H$25:$AK$32,4,0)) -> 0 | K125: =VLOOKUP($A125,$A$4:$O$28,6,0)*(HLOOKUP(K$113,'2.2.Brecha Efectiva x UdM'!$H$25:$AK$32,4,0)) -> 0 | ... AG125: =VLOOKUP($A125,$A$4:$O$28,6,0)*(HLOOKUP(AG$113,'2.2.Brecha Efectiva x UdM'!$H$25:$AK$32,4,0)) -> 0 | AH125: =SUM(D125:AG125) -> 0
... A137: =A27 -> Tucumán | B137: =$G$3 -> Nombre UdM 3 | C137: =CONCATENATE(A137," ",B137) -> Tucumán Nombre UdM 3 | D137: =VLOOKUP($A137,$A$4:$O$28,6,0)*(HLOOKUP(D$113,'2.2.Brecha Efectiva x UdM'!$H$25:$AK$32,4,0)) -> 0 | E137: =VLOOKUP($A137,$A$4:$O$28,6,0)*(HLOOKUP(E$113,'2.2.Brecha Efectiva x UdM'!$H$25:$AK$32,4,0)) -> 0 | F137: =VLOOKUP($A137,$A$4:$O$28,6,0)*(HLOOKUP(F$113,'2.2.Brecha Efectiva x UdM'!$H$25:$AK$32,4,0)) -> 0 | G137: =VLOOKUP($A137,$A$4:$O$28,6,0)*(HLOOKUP(G$113,'2.2.Brecha Efectiva x UdM'!$H$25:$AK$32,4,0)) -> 0 | H137: =VLOOKUP($A137,$A$4:$O$28,6,0)*(HLOOKUP(H$113,'2.2.Brecha Efectiva x UdM'!$H$25:$AK$32,4,0)) -> 0 | I137: =VLOOKUP($A137,$A$4:$O$28,6,0)*(HLOOKUP(I$113,'2.2.Brecha Efectiva x UdM'!$H$25:$AK$32,4,0)) -> 0 | J137: =VLOOKUP($A137,$A$4:$O$28,6,0)*(HLOOKUP(J$113,'2.2.Brecha Efectiva x UdM'!$H$25:$AK$32,4,0)) -> 0 | K137: =VLOOKUP($A137,$A$4:$O$28,6,0)*(HLOOKUP(K$113,'2.2.Brecha Efectiva x UdM'!$H$25:$AK$32,4,0)) -> 0 | ... AG137: =VLOOKUP($A137,$A$4:$O$28,6,0)*(HLOOKUP(AG$113,'2.2.Brecha Efectiva x UdM'!$H$25:$AK$32,4,0)) -> 0 | AH137: =SUM(D137:AG137) -> 0
A138: =CONCATENATE("Total"," ",B114) -> Total Nombre UdM 3 | D138: =SUM(D114:D137) -> 9.0875594e+08 | E138: =SUM(E114:E137) -> 6.1769531e+09 | F138: =SUM(F114:F137) -> 3.1397216e+08 | G138: =SUM(G114:G137) -> 1.7178102e+08 | H138: =SUM(H114:H137) -> 0 | I138: =SUM(I114:I137) -> 0 | J138: =SUM(J114:J137) -> 0 | K138: =SUM(K114:K137) -> 0 | ... AG138: =SUM(AG114:AG137) -> 0 | AH138: =SUM(D138:AG138) -> 7.5714622e+09
A139: =CONCATENATE("Total Acumulado"," ",B114) -> Total Acumulado Nombre UdM 3 | D139: =D138 -> 9.0875594e+08 | E139: =E138+D139 -> 7.0857091e+09 | F139: =F138+E139 -> 7.3996812e+09 | G139: =G138+F139 -> 7.5714622e+09 | H139: =H138+G139 -> 7.5714622e+09 | I139: =I138+H139 -> 7.5714622e+09 | J139: =J138+I139 -> 7.5714622e+09 | K139: =K138+J139 -> 7.5714622e+09 | L139: =L138+K139 -> 7.5714622e+09 | ... AG139: =AG138+AF139 -> 7.5714622e+09
A141: Chequeo | D141: =D138='2.2.Brecha Efectiva x UdM'!H28 -> TRUE | E141: =E138='2.2.Brecha Efectiva x UdM'!I28 -> TRUE | F141: =F138='2.2.Brecha Efectiva x UdM'!J28 -> TRUE | G141: =ROUND(G138,0)=ROUND('2.2.Brecha Efectiva x UdM'!K28,0) -> TRUE
G142: =AG139=SUM('2.2.Brecha Efectiva x UdM'!H28:AK28) -> TRUE
A143: Filas ocultas a continuación: Cuadros de resultado por UdM, para el caso de que la Jurisdicción hubiera calculado la brecha en más de 3 UdMs.
A144: Cuadro 2.3.3.4. Distribución provincial de la UdM 4, por brecha efectiva, en millones de pesos, ajustada en función de la tasa de crecimiento de la Poblacional Nacional.
A146: Provincia | B146: UDM | C146: UDM Provincial | D146: 2024 | E146: 2025 | F146: 2026 | G146: 2027 | H146: 2028 | I146: 2029 | J146: 2030 | K146: 2031 | L146: 2032 | M146: 2033 | N146: 2034 | O146: 2035 | P146: 2036 | Q146: 2037 | R146: 2038 | S146: 2039 | T146: 2040 | U146: 2041 | V146: 2042 | W146: 2043 | X146: 2044 | Y146: 2045 | Z146: 2046 | AA146: 2047 | AB146: 2048 | AC146: 2049 | AD146: 2050 | AE146: 2051 | AF146: 2052 | AG146: 2053 | AH146: TOTAL
A147: =A4 -> Buenos Aires | B147: =$I$3 -> 0 | C147: =CONCATENATE(A147," ",B147) -> Buenos Aires 0 | D147: =VLOOKUP($A147,$A$4:$O$28,8,0)*(HLOOKUP(D$146,'2.2.Brecha Efectiva x UdM'!$H$25:$AK$32,5,0)) -> 0 | E147: =VLOOKUP($A147,$A$4:$O$28,8,0)*(HLOOKUP(E$146,'2.2.Brecha Efectiva x UdM'!$H$25:$AK$32,5,0)) -> 0 | F147: =VLOOKUP($A147,$A$4:$O$28,8,0)*(HLOOKUP(F$146,'2.2.Brecha Efectiva x UdM'!$H$25:$AK$32,5,0)) -> 0 | G147: =VLOOKUP($A147,$A$4:$O$28,8,0)*(HLOOKUP(G$146,'2.2.Brecha Efectiva x UdM'!$H$25:$AK$32,5,0)) -> 0 | H147: =VLOOKUP($A147,$A$4:$O$28,8,0)*(HLOOKUP(H$146,'2.2.Brecha Efectiva x UdM'!$H$25:$AK$32,5,0)) -> 0 | I147: =VLOOKUP($A147,$A$4:$O$28,8,0)*(HLOOKUP(I$146,'2.2.Brecha Efectiva x UdM'!$H$25:$AK$32,5,0)) -> 0 | J147: =VLOOKUP($A147,$A$4:$O$28,8,0)*(HLOOKUP(J$146,'2.2.Brecha Efectiva x UdM'!$H$25:$AK$32,5,0)) -> 0 | K147: =VLOOKUP($A147,$A$4:$O$28,8,0)*(HLOOKUP(K$146,'2.2.Brecha Efectiva x UdM'!$H$25:$AK$32,5,0)) -> 0 | ... AG147: =VLOOKUP($A147,$A$4:$O$28,8,0)*(HLOOKUP(AG$146,'2.2.Brecha Efectiva x UdM'!$H$25:$AK$32,5,0)) -> 0 | AH147: =SUM(D147:AG147) -> 0
A148: =A5 -> CABA | B148: =$I$3 -> 0 | C148: =CONCATENATE(A148," ",B148) -> CABA 0 | D148: =VLOOKUP($A148,$A$4:$O$28,8,0)*(HLOOKUP(D$146,'2.2.Brecha Efectiva x UdM'!$H$25:$AK$32,5,0)) -> 0 | E148: =VLOOKUP($A148,$A$4:$O$28,8,0)*(HLOOKUP(E$146,'2.2.Brecha Efectiva x UdM'!$H$25:$AK$32,5,0)) -> 0 | F148: =VLOOKUP($A148,$A$4:$O$28,8,0)*(HLOOKUP(F$146,'2.2.Brecha Efectiva x UdM'!$H$25:$AK$32,5,0)) -> 0 | G148: =VLOOKUP($A148,$A$4:$O$28,8,0)*(HLOOKUP(G$146,'2.2.Brecha Efectiva x UdM'!$H$25:$AK$32,5,0)) -> 0 | H148: =VLOOKUP($A148,$A$4:$O$28,8,0)*(HLOOKUP(H$146,'2.2.Brecha Efectiva x UdM'!$H$25:$AK$32,5,0)) -> 0 | I148: =VLOOKUP($A148,$A$4:$O$28,8,0)*(HLOOKUP(I$146,'2.2.Brecha Efectiva x UdM'!$H$25:$AK$32,5,0)) -> 0 | J148: =VLOOKUP($A148,$A$4:$O$28,8,0)*(HLOOKUP(J$146,'2.2.Brecha Efectiva x UdM'!$H$25:$AK$32,5,0)) -> 0 | K148: =VLOOKUP($A148,$A$4:$O$28,8,0)*(HLOOKUP(K$146,'2.2.Brecha Efectiva x UdM'!$H$25:$AK$32,5,0)) -> 0 | ... AG148: =VLOOKUP($A148,$A$4:$O$28,8,0)*(HLOOKUP(AG$146,'2.2.Brecha Efectiva x UdM'!$H$25:$AK$32,5,0)) -> 0 | AH148: =SUM(D148:AG148) -> 0
A149: =A6 -> Catamarca | B149: =$I$3 -> 0 | C149: =CONCATENATE(A149," ",B149) -> Catamarca 0 | D149: =VLOOKUP($A149,$A$4:$O$28,8,0)*(HLOOKUP(D$146,'2.2.Brecha Efectiva x UdM'!$H$25:$AK$32,5,0)) -> 0 | E149: =VLOOKUP($A149,$A$4:$O$28,8,0)*(HLOOKUP(E$146,'2.2.Brecha Efectiva x UdM'!$H$25:$AK$32,5,0)) -> 0 | F149: =VLOOKUP($A149,$A$4:$O$28,8,0)*(HLOOKUP(F$146,'2.2.Brecha Efectiva x UdM'!$H$25:$AK$32,5,0)) -> 0 | G149: =VLOOKUP($A149,$A$4:$O$28,8,0)*(HLOOKUP(G$146,'2.2.Brecha Efectiva x UdM'!$H$25:$AK$32,5,0)) -> 0 | H149: =VLOOKUP($A149,$A$4:$O$28,8,0)*(HLOOKUP(H$146,'2.2.Brecha Efectiva x UdM'!$H$25:$AK$32,5,0)) -> 0 | I149: =VLOOKUP($A149,$A$4:$O$28,8,0)*(HLOOKUP(I$146,'2.2.Brecha Efectiva x UdM'!$H$25:$AK$32,5,0)) -> 0 | J149: =VLOOKUP($A149,$A$4:$O$28,8,0)*(HLOOKUP(J$146,'2.2.Brecha Efectiva x UdM'!$H$25:$AK$32,5,0)) -> 0 | K149: =VLOOKUP($A149,$A$4:$O$28,8,0)*(HLOOKUP(K$146,'2.2.Brecha Efectiva x UdM'!$H$25:$AK$32,5,0)) -> 0 | ... AG149: =VLOOKUP($A149,$A$4:$O$28,8,0)*(HLOOKUP(AG$146,'2.2.Brecha Efectiva x UdM'!$H$25:$AK$32,5,0)) -> 0 | AH149: =SUM(D149:AG149) -> 0
A150: =A7 -> Chaco | B150: =$I$3 -> 0 | C150: =CONCATENATE(A150," ",B150) -> Chaco 0 | D150: =VLOOKUP($A150,$A$4:$O$28,8,0)*(HLOOKUP(D$146,'2.2.Brecha Efectiva x UdM'!$H$25:$AK$32,5,0)) -> 0 | E150: =VLOOKUP($A150,$A$4:$O$28,8,0)*(HLOOKUP(E$146,'2.2.Brecha Efectiva x UdM'!$H$25:$AK$32,5,0)) -> 0 | F150: =VLOOKUP($A150,$A$4:$O$28,8,0)*(HLOOKUP(F$146,'2.2.Brecha Efectiva x UdM'!$H$25:$AK$32,5,0)) -> 0 | G150: =VLOOKUP($A150,$A$4:$O$28,8,0)*(HLOOKUP(G$146,'2.2.Brecha Efectiva x UdM'!$H$25:$AK$32,5,0)) -> 0 | H150: =VLOOKUP($A150,$A$4:$O$28,8,0)*(HLOOKUP(H$146,'2.2.Brecha Efectiva x UdM'!$H$25:$AK$32,5,0)) -> 0 | I150: =VLOOKUP($A150,$A$4:$O$28,8,0)*(HLOOKUP(I$146,'2.2.Brecha Efectiva x UdM'!$H$25:$AK$32,5,0)) -> 0 | J150: =VLOOKUP($A150,$A$4:$O$28,8,0)*(HLOOKUP(J$146,'2.2.Brecha Efectiva x UdM'!$H$25:$AK$32,5,0)) -> 0 | K150: =VLOOKUP($A150,$A$4:$O$28,8,0)*(HLOOKUP(K$146,'2.2.Brecha Efectiva x UdM'!$H$25:$AK$32,5,0)) -> 0 | ... AG150: =VLOOKUP($A150,$A$4:$O$28,8,0)*(HLOOKUP(AG$146,'2.2.Brecha Efectiva x UdM'!$H$25:$AK$32,5,0)) -> 0 | AH150: =SUM(D150:AG150) -> 0
A151: =A8 -> Chubut | B151: =$I$3 -> 0 | C151: =CONCATENATE(A151," ",B151) -> Chubut 0 | D151: =VLOOKUP($A151,$A$4:$O$28,8,0)*(HLOOKUP(D$146,'2.2.Brecha Efectiva x UdM'!$H$25:$AK$32,5,0)) -> 0 | E151: =VLOOKUP($A151,$A$4:$O$28,8,0)*(HLOOKUP(E$146,'2.2.Brecha Efectiva x UdM'!$H$25:$AK$32,5,0)) -> 0 | F151: =VLOOKUP($A151,$A$4:$O$28,8,0)*(HLOOKUP(F$146,'2.2.Brecha Efectiva x UdM'!$H$25:$AK$32,5,0)) -> 0 | G151: =VLOOKUP($A151,$A$4:$O$28,8,0)*(HLOOKUP(G$146,'2.2.Brecha Efectiva x UdM'!$H$25:$AK$32,5,0)) -> 0 | H151: =VLOOKUP($A151,$A$4:$O$28,8,0)*(HLOOKUP(H$146,'2.2.Brecha Efectiva x UdM'!$H$25:$AK$32,5,0)) -> 0 | I151: =VLOOKUP($A151,$A$4:$O$28,8,0)*(HLOOKUP(I$146,'2.2.Brecha Efectiva x UdM'!$H$25:$AK$32,5,0)) -> 0 | J151: =VLOOKUP($A151,$A$4:$O$28,8,0)*(HLOOKUP(J$146,'2.2.Brecha Efectiva x UdM'!$H$25:$AK$32,5,0)) -> 0 | K151: =VLOOKUP($A151,$A$4:$O$28,8,0)*(HLOOKUP(K$146,'2.2.Brecha Efectiva x UdM'!$H$25:$AK$32,5,0)) -> 0 | ... AG151: =VLOOKUP($A151,$A$4:$O$28,8,0)*(HLOOKUP(AG$146,'2.2.Brecha Efectiva x UdM'!$H$25:$AK$32,5,0)) -> 0 | AH151: =SUM(D151:AG151) -> 0
A152: =A9 -> Córdoba | B152: =$I$3 -> 0 | C152: =CONCATENATE(A152," ",B152) -> Córdoba 0 | D152: =VLOOKUP($A152,$A$4:$O$28,8,0)*(HLOOKUP(D$146,'2.2.Brecha Efectiva x UdM'!$H$25:$AK$32,5,0)) -> 0 | E152: =VLOOKUP($A152,$A$4:$O$28,8,0)*(HLOOKUP(E$146,'2.2.Brecha Efectiva x UdM'!$H$25:$AK$32,5,0)) -> 0 | F152: =VLOOKUP($A152,$A$4:$O$28,8,0)*(HLOOKUP(F$146,'2.2.Brecha Efectiva x UdM'!$H$25:$AK$32,5,0)) -> 0 | G152: =VLOOKUP($A152,$A$4:$O$28,8,0)*(HLOOKUP(G$146,'2.2.Brecha Efectiva x UdM'!$H$25:$AK$32,5,0)) -> 0 | H152: =VLOOKUP($A152,$A$4:$O$28,8,0)*(HLOOKUP(H$146,'2.2.Brecha Efectiva x UdM'!$H$25:$AK$32,5,0)) -> 0 | I152: =VLOOKUP($A152,$A$4:$O$28,8,0)*(HLOOKUP(I$146,'2.2.Brecha Efectiva x UdM'!$H$25:$AK$32,5,0)) -> 0 | J152: =VLOOKUP($A152,$A$4:$O$28,8,0)*(HLOOKUP(J$146,'2.2.Brecha Efectiva x UdM'!$H$25:$AK$32,5,0)) -> 0 | K152: =VLOOKUP($A152,$A$4:$O$28,8,0)*(HLOOKUP(K$146,'2.2.Brecha Efectiva x UdM'!$H$25:$AK$32,5,0)) -> 0 | ... AG152: =VLOOKUP($A152,$A$4:$O$28,8,0)*(HLOOKUP(AG$146,'2.2.Brecha Efectiva x UdM'!$H$25:$AK$32,5,0)) -> 0 | AH152: =SUM(D152:AG152) -> 0
A153: =A10 -> Corrientes | B153: =$I$3 -> 0 | C153: =CONCATENATE(A153," ",B153) -> Corrientes 0 | D153: =VLOOKUP($A153,$A$4:$O$28,8,0)*(HLOOKUP(D$146,'2.2.Brecha Efectiva x UdM'!$H$25:$AK$32,5,0)) -> 0 | E153: =VLOOKUP($A153,$A$4:$O$28,8,0)*(HLOOKUP(E$146,'2.2.Brecha Efectiva x UdM'!$H$25:$AK$32,5,0)) -> 0 | F153: =VLOOKUP($A153,$A$4:$O$28,8,0)*(HLOOKUP(F$146,'2.2.Brecha Efectiva x UdM'!$H$25:$AK$32,5,0)) -> 0 | G153: =VLOOKUP($A153,$A$4:$O$28,8,0)*(HLOOKUP(G$146,'2.2.Brecha Efectiva x UdM'!$H$25:$AK$32,5,0)) -> 0 | H153: =VLOOKUP($A153,$A$4:$O$28,8,0)*(HLOOKUP(H$146,'2.2.Brecha Efectiva x UdM'!$H$25:$AK$32,5,0)) -> 0 | I153: =VLOOKUP($A153,$A$4:$O$28,8,0)*(HLOOKUP(I$146,'2.2.Brecha Efectiva x UdM'!$H$25:$AK$32,5,0)) -> 0 | J153: =VLOOKUP($A153,$A$4:$O$28,8,0)*(HLOOKUP(J$146,'2.2.Brecha Efectiva x UdM'!$H$25:$AK$32,5,0)) -> 0 | K153: =VLOOKUP($A153,$A$4:$O$28,8,0)*(HLOOKUP(K$146,'2.2.Brecha Efectiva x UdM'!$H$25:$AK$32,5,0)) -> 0 | ... AG153: =VLOOKUP($A153,$A$4:$O$28,8,0)*(HLOOKUP(AG$146,'2.2.Brecha Efectiva x UdM'!$H$25:$AK$32,5,0)) -> 0 | AH153: =SUM(D153:AG153) -> 0
A154: =A11 -> Entre Ríos | B154: =$I$3 -> 0 | C154: =CONCATENATE(A154," ",B154) -> Entre Ríos 0 | D154: =VLOOKUP($A154,$A$4:$O$28,8,0)*(HLOOKUP(D$146,'2.2.Brecha Efectiva x UdM'!$H$25:$AK$32,5,0)) -> 0 | E154: =VLOOKUP($A154,$A$4:$O$28,8,0)*(HLOOKUP(E$146,'2.2.Brecha Efectiva x UdM'!$H$25:$AK$32,5,0)) -> 0 | F154: =VLOOKUP($A154,$A$4:$O$28,8,0)*(HLOOKUP(F$146,'2.2.Brecha Efectiva x UdM'!$H$25:$AK$32,5,0)) -> 0 | G154: =VLOOKUP($A154,$A$4:$O$28,8,0)*(HLOOKUP(G$146,'2.2.Brecha Efectiva x UdM'!$H$25:$AK$32,5,0)) -> 0 | H154: =VLOOKUP($A154,$A$4:$O$28,8,0)*(HLOOKUP(H$146,'2.2.Brecha Efectiva x UdM'!$H$25:$AK$32,5,0)) -> 0 | I154: =VLOOKUP($A154,$A$4:$O$28,8,0)*(HLOOKUP(I$146,'2.2.Brecha Efectiva x UdM'!$H$25:$AK$32,5,0)) -> 0 | J154: =VLOOKUP($A154,$A$4:$O$28,8,0)*(HLOOKUP(J$146,'2.2.Brecha Efectiva x UdM'!$H$25:$AK$32,5,0)) -> 0 | K154: =VLOOKUP($A154,$A$4:$O$28,8,0)*(HLOOKUP(K$146,'2.2.Brecha Efectiva x UdM'!$H$25:$AK$32,5,0)) -> 0 | ... AG154: =VLOOKUP($A154,$A$4:$O$28,8,0)*(HLOOKUP(AG$146,'2.2.Brecha Efectiva x UdM'!$H$25:$AK$32,5,0)) -> 0 | AH154: =SUM(D154:AG154) -> 0
A155: =A12 -> Formosa | B155: =$I$3 -> 0 | C155: =CONCATENATE(A155," ",B155) -> Formosa 0 | D155: =VLOOKUP($A155,$A$4:$O$28,8,0)*(HLOOKUP(D$146,'2.2.Brecha Efectiva x UdM'!$H$25:$AK$32,5,0)) -> 0 | E155: =VLOOKUP($A155,$A$4:$O$28,8,0)*(HLOOKUP(E$146,'2.2.Brecha Efectiva x UdM'!$H$25:$AK$32,5,0)) -> 0 | F155: =VLOOKUP($A155,$A$4:$O$28,8,0)*(HLOOKUP(F$146,'2.2.Brecha Efectiva x UdM'!$H$25:$AK$32,5,0)) -> 0 | G155: =VLOOKUP($A155,$A$4:$O$28,8,0)*(HLOOKUP(G$146,'2.2.Brecha Efectiva x UdM'!$H$25:$AK$32,5,0)) -> 0 | H155: =VLOOKUP($A155,$A$4:$O$28,8,0)*(HLOOKUP(H$146,'2.2.Brecha Efectiva x UdM'!$H$25:$AK$32,5,0)) -> 0 | I155: =VLOOKUP($A155,$A$4:$O$28,8,0)*(HLOOKUP(I$146,'2.2.Brecha Efectiva x UdM'!$H$25:$AK$32,5,0)) -> 0 | J155: =VLOOKUP($A155,$A$4:$O$28,8,0)*(HLOOKUP(J$146,'2.2.Brecha Efectiva x UdM'!$H$25:$AK$32,5,0)) -> 0 | K155: =VLOOKUP($A155,$A$4:$O$28,8,0)*(HLOOKUP(K$146,'2.2.Brecha Efectiva x UdM'!$H$25:$AK$32,5,0)) -> 0 | ... AG155: =VLOOKUP($A155,$A$4:$O$28,8,0)*(HLOOKUP(AG$146,'2.2.Brecha Efectiva x UdM'!$H$25:$AK$32,5,0)) -> 0 | AH155: =SUM(D155:AG155) -> 0
A156: =A13 -> Jujuy | B156: =$I$3 -> 0 | C156: =CONCATENATE(A156," ",B156) -> Jujuy 0 | D156: =VLOOKUP($A156,$A$4:$O$28,8,0)*(HLOOKUP(D$146,'2.2.Brecha Efectiva x UdM'!$H$25:$AK$32,5,0)) -> 0 | E156: =VLOOKUP($A156,$A$4:$O$28,8,0)*(HLOOKUP(E$146,'2.2.Brecha Efectiva x UdM'!$H$25:$AK$32,5,0)) -> 0 | F156: =VLOOKUP($A156,$A$4:$O$28,8,0)*(HLOOKUP(F$146,'2.2.Brecha Efectiva x UdM'!$H$25:$AK$32,5,0)) -> 0 | G156: =VLOOKUP($A156,$A$4:$O$28,8,0)*(HLOOKUP(G$146,'2.2.Brecha Efectiva x UdM'!$H$25:$AK$32,5,0)) -> 0 | H156: =VLOOKUP($A156,$A$4:$O$28,8,0)*(HLOOKUP(H$146,'2.2.Brecha Efectiva x UdM'!$H$25:$AK$32,5,0)) -> 0 | I156: =VLOOKUP($A156,$A$4:$O$28,8,0)*(HLOOKUP(I$146,'2.2.Brecha Efectiva x UdM'!$H$25:$AK$32,5,0)) -> 0 | J156: =VLOOKUP($A156,$A$4:$O$28,8,0)*(HLOOKUP(J$146,'2.2.Brecha Efectiva x UdM'!$H$25:$AK$32,5,0)) -> 0 | K156: =VLOOKUP($A156,$A$4:$O$28,8,0)*(HLOOKUP(K$146,'2.2.Brecha Efectiva x UdM'!$H$25:$AK$32,5,0)) -> 0 | ... AG156: =VLOOKUP($A156,$A$4:$O$28,8,0)*(HLOOKUP(AG$146,'2.2.Brecha Efectiva x UdM'!$H$25:$AK$32,5,0)) -> 0 | AH156: =SUM(D156:AG156) -> 0
A157: =A14 -> La Pampa | B157: =$I$3 -> 0 | C157: =CONCATENATE(A157," ",B157) -> La Pampa 0 | D157: =VLOOKUP($A157,$A$4:$O$28,8,0)*(HLOOKUP(D$146,'2.2.Brecha Efectiva x UdM'!$H$25:$AK$32,5,0)) -> 0 | E157: =VLOOKUP($A157,$A$4:$O$28,8,0)*(HLOOKUP(E$146,'2.2.Brecha Efectiva x UdM'!$H$25:$AK$32,5,0)) -> 0 | F157: =VLOOKUP($A157,$A$4:$O$28,8,0)*(HLOOKUP(F$146,'2.2.Brecha Efectiva x UdM'!$H$25:$AK$32,5,0)) -> 0 | G157: =VLOOKUP($A157,$A$4:$O$28,8,0)*(HLOOKUP(G$146,'2.2.Brecha Efectiva x UdM'!$H$25:$AK$32,5,0)) -> 0 | H157: =VLOOKUP($A157,$A$4:$O$28,8,0)*(HLOOKUP(H$146,'2.2.Brecha Efectiva x UdM'!$H$25:$AK$32,5,0)) -> 0 | I157: =VLOOKUP($A157,$A$4:$O$28,8,0)*(HLOOKUP(I$146,'2.2.Brecha Efectiva x UdM'!$H$25:$AK$32,5,0)) -> 0 | J157: =VLOOKUP($A157,$A$4:$O$28,8,0)*(HLOOKUP(J$146,'2.2.Brecha Efectiva x UdM'!$H$25:$AK$32,5,0)) -> 0 | K157: =VLOOKUP($A157,$A$4:$O$28,8,0)*(HLOOKUP(K$146,'2.2.Brecha Efectiva x UdM'!$H$25:$AK$32,5,0)) -> 0 | ... AG157: =VLOOKUP($A157,$A$4:$O$28,8,0)*(HLOOKUP(AG$146,'2.2.Brecha Efectiva x UdM'!$H$25:$AK$32,5,0)) -> 0 | AH157: =SUM(D157:AG157) -> 0
A158: =A15 -> La Rioja | B158: =$I$3 -> 0 | C158: =CONCATENATE(A158," ",B158) -> La Rioja 0 | D158: =VLOOKUP($A158,$A$4:$O$28,8,0)*(HLOOKUP(D$146,'2.2.Brecha Efectiva x UdM'!$H$25:$AK$32,5,0)) -> 0 | E158: =VLOOKUP($A158,$A$4:$O$28,8,0)*(HLOOKUP(E$146,'2.2.Brecha Efectiva x UdM'!$H$25:$AK$32,5,0)) -> 0 | F158: =VLOOKUP($A158,$A$4:$O$28,8,0)*(HLOOKUP(F$146,'2.2.Brecha Efectiva x UdM'!$H$25:$AK$32,5,0)) -> 0 | G158: =VLOOKUP($A158,$A$4:$O$28,8,0)*(HLOOKUP(G$146,'2.2.Brecha Efectiva x UdM'!$H$25:$AK$32,5,0)) -> 0 | H158: =VLOOKUP($A158,$A$4:$O$28,8,0)*(HLOOKUP(H$146,'2.2.Brecha Efectiva x UdM'!$H$25:$AK$32,5,0)) -> 0 | I158: =VLOOKUP($A158,$A$4:$O$28,8,0)*(HLOOKUP(I$146,'2.2.Brecha Efectiva x UdM'!$H$25:$AK$32,5,0)) -> 0 | J158: =VLOOKUP($A158,$A$4:$O$28,8,0)*(HLOOKUP(J$146,'2.2.Brecha Efectiva x UdM'!$H$25:$AK$32,5,0)) -> 0 | K158: =VLOOKUP($A158,$A$4:$O$28,8,0)*(HLOOKUP(K$146,'2.2.Brecha Efectiva x UdM'!$H$25:$AK$32,5,0)) -> 0 | ... AG158: =VLOOKUP($A158,$A$4:$O$28,8,0)*(HLOOKUP(AG$146,'2.2.Brecha Efectiva x UdM'!$H$25:$AK$32,5,0)) -> 0 | AH158: =SUM(D158:AG158) -> 0
...

Sheet 2.4.Dimension Fisica e Indicad
A1: Cuadro 2.4.6. Dimensión Física e Indicadores de Cobertura, por UdM, (ajustado por Mantenimiento e Índice de Actualización)
A2: JURISDICCIÓN | B2: SECTOR | C2: Unidad de Medida (UdM) | D2: Brecha x UdM (millones $) META 2051 | E2: Plazo (Años) META 2051 | F2: Brecha x UdM (millones $) META 2033 | G2: (%) de la Brecha cubierto en 2033 | H2: Unidades Físicas | I2: Indicadores de Cobertura
A3: ='2.2.Brecha Efectiva x UdM'!A3 -> Nombre Jurisdicción | B3: ='2.2.Brecha Efectiva x UdM'!B3 -> Nombre Sector | C3: ='2.2.Brecha Efectiva x UdM'!C3 -> Nombre UdM 1 | D3: ='2.2.Brecha Efectiva x UdM'!D65 -> 2.026868e+10 | E3: ='2.2.Brecha Efectiva x UdM'!E65 -> 10 | F3: ='2.2.Brecha Efectiva x UdM'!F65 -> 2.026868e+10 | G3: =IFERROR(F3/D3,0) -> 1 | H3: (Ej. UdM1: Red Federal de Fibra Óptica): Construir e iluminar XX kilómetros de fibra óptica, para llegar a los YY kilómetros iluminados. Actualización de equipamiento para multiplicar por ZZ la capacidad de la red troncal. | I3: Permitirá que XX millones de personas accedan a la red troncal (actualmente tienen acceso YY millones). Esto cubrirá el ZZ% de las necesidades estimadas de conexión a internet.
A4: ='2.2.Brecha Efectiva x UdM'!A4 -> Nombre Jurisdicción | B4: ='2.2.Brecha Efectiva x UdM'!B4 -> Nombre Sector | C4: ='2.2.Brecha Efectiva x UdM'!C4 -> Nombre UdM 2 | D4: ='2.2.Brecha Efectiva x UdM'!D66 -> 1.1219988e+10 | E4: ='2.2.Brecha Efectiva x UdM'!E66 -> 3 | F4: ='2.2.Brecha Efectiva x UdM'!F66 -> 1.1219988e+10 | G4: =IFERROR(F4/D4,0) -> 1 | H4: (Ej. UdM2: Plan Satelital): Reactivación de la fabricación y puesta en órbita de un satélite adicional para la flota geoestacionaria de ARSAT. Actualmente se cuentan con X cantidad de satélites. El nuevo satélite contará con prestaciones adicionales, como X, Y, Z. | I4: Brindará conectividad satelital de calidad en XX mil hogares rurales, con una capacidad de tráfico de datos a los YY Gbps, elevando dicha conectividad al ZZ% de la población rural o de difícil acceso (actualmente cubre el VV%).
A5: ='2.2.Brecha Efectiva x UdM'!A5 -> Nombre Jurisdicción | B5: ='2.2.Brecha Efectiva x UdM'!B5 -> Nombre Sector | C5: ='2.2.Brecha Efectiva x UdM'!C5 -> Nombre UdM 3 | D5: ='2.2.Brecha Efectiva x UdM'!D67 -> 8.3286085e+09 | E5: ='2.2.Brecha Efectiva x UdM'!E67 -> 4 | F5: ='2.2.Brecha Efectiva x UdM'!F67 -> 8.3286085e+09 | G5: =IFERROR(F5/D5,0) -> 1 | H5: (Ej. UdM3: Televisión Digital Abierta): Actualizar XX estaciones de transmisión y renovación de la plataforma de transmisión de Televisión Digital Abierta | I5: Posibilitará cubrir el XX% del territorio (actualmente cubre el YY%). ZZ millones de hogares accederán a un servicio de TV de calidad (VV% del total de hogares). Actualmente acceden MM millones (NN% de los hogares) a un servicio que presenta fallas.
A6: ='2.2.Brecha Efectiva x UdM'!A6 -> Nombre Jurisdicción | B6: ='2.2.Brecha Efectiva x UdM'!B6 -> Nombre Sector | C6: ='2.2.Brecha Efectiva x UdM'!C6 -> 0 | D6: ='2.2.Brecha Efectiva x UdM'!D68 -> 0 | E6: ='2.2.Brecha Efectiva x UdM'!E68 -> 0 | F6: ='2.2.Brecha Efectiva x UdM'!F68 -> 0 | G6: =IFERROR(F6/D6,0) -> 0
A7: ='2.2.Brecha Efectiva x UdM'!A7 -> Nombre Jurisdicción | B7: ='2.2.Brecha Efectiva x UdM'!B7 -> Nombre Sector | C7: ='2.2.Brecha Efectiva x UdM'!C7 -> 0 | D7: ='2.2.Brecha Efectiva x UdM'!D69 -> 0 | E7: ='2.2.Brecha Efectiva x UdM'!E69 -> 0 | F7: ='2.2.Brecha Efectiva x UdM'!F69 -> 0 | G7: =IFERROR(F7/D7,0) -> 0
A8: ='2.2.Brecha Efectiva x UdM'!A8 -> Nombre Jurisdicción | B8: ='2.2.Brecha Efectiva x UdM'!B8 -> Nombre Sector | C8: ='2.2.Brecha Efectiva x UdM'!C8 -> 0 | D8: ='2.2.Brecha Efectiva x UdM'!D70 -> 0 | E8: ='2.2.Brecha Efectiva x UdM'!E70 -> 0 | F8: ='2.2.Brecha Efectiva x UdM'!F70 -> 0 | G8: =IFERROR(F8/D8,0) -> 0
A9: TOTAL | D9: ='2.2.Brecha Efectiva x UdM'!D71 -> 3.9817277e+10 | E9: ='2.2.Brecha Efectiva x UdM'!E71 -> 0 | F9: ='2.2.Brecha Efectiva x UdM'!F71 -> 3.9817277e+10 | G9: =IFERROR(F9/D9,0) -> 1
A11: INSTRUCTIVO
A13: Por favor, completar únicamente las columnas H (Unidades Físicas) e I (Indicadores de Cobertura). (Ejemplo en Rojo)
A14: Las metas físicas establecen, para cada UdM, el uso concreto que se le dará a los fondos requeridos para cerrar la brecha (en términos generales, nos referimos a las “cantidades” utilizadas para el cálculo de las brechas -PxQ). Dependiendo del caso, puede expresarse en cantidad de equipos concretos adquiridos (patrulleros, ambulancias, helicópteros, etc); metros cuadrados construidos (o cantidad de establecimientos); KM de ruta pavimentada, vías reparadas, o de redes primarias o secundarias de agua corriente, MW de potencia instalada; o cantidad de conexiones de servicios realizadas, entre algunos ejemplos posibles. Es importante, si se cuenta con la información, indicar también desde qué base se parte actualmente (ej. cuántos son los MW de potencia instalados actualmente), de manera de poder dimensionar la importancia de la brecha en términos físicos.
A16: Los indicadores de cobertura de cada unidad física, expresan qué porcentaje de cobertura se busca alcanzar con la acción física particular, cuántas personas se van a beneficiar de ella, etc. Cada unidad física debe tener uno o más índices de cobertura, que apunten a que las autoridades puedan dimensionar, en términos cuantitativos, en qué grado o en que medida el cumplimiento de la unidad física estaría respondiendo a la solución de una problemática. Por ejemplo: Si el sector Telecomunicaciones tuviera una UDM “Red Federal de Fibra Óptica”, la meta física podría ser “Construir e iluminar 4.400 kilómetros de fibra óptica, para llegar a los 38.800 kilómetros iluminados” (Nótese que se indica tanto el punto de partida existente, como el objetivo al que se quiere llegar). El indicador de cobertura sería “22 millones de personas tendrán acceso a la red troncal (actualmente tienen acceso 20,7 millones). Esto cubrirá el 50% de las necesidades estimadas de conexión a internet”.
A18: Aclaración: Por favor, tener en cuenta que las Unidades Físicas e Indicadores de Cobertura deben ser estimados en función de los montos del Cuadro 2.2.6, es decir, luego de que se hubieran realizado todos los ajustes relacionados con el paso del tiempo hasta cerrar la brecha.
A20: Cuadro 2.4.8. Dimensión Física e Indicadores de Cobertura, por UdM, para la Reposición del Stock de Capital Existente
A21: JURISDICCIÓN | B21: SECTOR | C21: Unidad de Medida (UdM) | D21: Reposiciones del Stock de Capital Existente x UdM (millones $) META 2051 | E21: Plazo (Años) META 2051 | F21: Reposiciones del Stock de Capital Existente x UdM (millones $) META 2033 | G21: (%) de la Brecha cubierto en 2033 | H21: Inversión Física | I21: Indicadores de Cobertura
A22: ='2.2.Brecha Efectiva x UdM'!A3 -> Nombre Jurisdicción | B22: ='2.2.Brecha Efectiva x UdM'!B3 -> Nombre Sector | C22: ='2.2.Brecha Efectiva x UdM'!C3 -> Nombre UdM 1 | D22: ='2.2.Brecha Efectiva x UdM'!D87 -> 3599278080 | E22: ='2.2.Brecha Efectiva x UdM'!E84 -> 0 | F22: ='2.2.Brecha Efectiva x UdM'!F87 -> 3599278080 | G22: =IFERROR(F22/D22,0) -> 1
A23: ='2.2.Brecha Efectiva x UdM'!A4 -> Nombre Jurisdicción | B23: ='2.2.Brecha Efectiva x UdM'!B4 -> Nombre Sector | C23: ='2.2.Brecha Efectiva x UdM'!C4 -> Nombre UdM 2 | D23: ='2.2.Brecha Efectiva x UdM'!D88 -> 2.019862e+09 | E23: ='2.2.Brecha Efectiva x UdM'!E85 -> 0 | F23: ='2.2.Brecha Efectiva x UdM'!F88 -> 2.019862e+09 | G23: =IFERROR(F23/D23,0) -> 1
A24: ='2.2.Brecha Efectiva x UdM'!A5 -> Nombre Jurisdicción | B24: ='2.2.Brecha Efectiva x UdM'!B5 -> Nombre Sector | C24: ='2.2.Brecha Efectiva x UdM'!C5 -> Nombre UdM 3 | D24: ='2.2.Brecha Efectiva x UdM'!D89 -> 1.5018141e+09 | E24: ='2.2.Brecha Efectiva x UdM'!E86 -> 0 | F24: ='2.2.Brecha Efectiva x UdM'!F89 -> 1.5018141e+09 | G24: =IFERROR(F24/D24,0) -> 1
A25: ='2.2.Brecha Efectiva x UdM'!A6 -> Nombre Jurisdicción | B25: ='2.2.Brecha Efectiva x UdM'!B6 -> Nombre Sector | C25: ='2.2.Brecha Efectiva x UdM'!C6 -> 0 | D25: ='2.2.Brecha Efectiva x UdM'!D90 -> 0 | E25: ='2.2.Brecha Efectiva x UdM'!E87 -> 0 | F25: ='2.2.Brecha Efectiva x UdM'!F90 -> 0 | G25: =IFERROR(F25/D25,0) -> 0
A26: ='2.2.Brecha Efectiva x UdM'!A7 -> Nombre Jurisdicción | B26: ='2.2.Brecha Efectiva x UdM'!B7 -> Nombre Sector | C26: ='2.2.Brecha Efectiva x UdM'!C7 -> 0 | D26: ='2.2.Brecha Efectiva x UdM'!D91 -> 0 | E26: ='2.2.Brecha Efectiva x UdM'!E88 -> 0 | F26: ='2.2.Brecha Efectiva x UdM'!F91 -> 0 | G26: =IFERROR(F26/D26,0) -> 0
A27: ='2.2.Brecha Efectiva x UdM'!A8 -> Nombre Jurisdicción | B27: ='2.2.Brecha Efectiva x UdM'!B8 -> Nombre Sector | C27: ='2.2.Brecha Efectiva x UdM'!C8 -> 0 | D27: ='2.2.Brecha Efectiva x UdM'!D92 -> 0 | E27: ='2.2.Brecha Efectiva x UdM'!E89 -> 0 | F27: ='2.2.Brecha Efectiva x UdM'!F92 -> 0 | G27: =IFERROR(F27/D27,0) -> 0
A28: TOTAL | D28: =SUM(D22:D27) -> 7.1209542e+09 | E28: ='2.2.Brecha Efectiva x UdM'!E90 -> 0 | F28: =SUM(F22:F27) -> 7.1209542e+09 | G28: =IFERROR(F28/D28,0) -> 1
A30: INSTRUCTIVO
A32: Por favor, completar únicamente las columnas H (Inversión Física) e I (Indicadores de Cobertura).
A33: Las inversiones físicas establecen, para cada UdM, el uso concreto que se le dará a los fondos requeridos para reposición, de manera de mantener el stock de capital existente.
A35: Los indicadores de cobertura del stock de capital físico, expresan qué porcentaje de cobertura se busca mantener con la acción física particular.
A37: Aclaración: Por favor, tener en cuenta que las Inversiones Físicas e Indicadores de Cobertura referentes al Stock de Capital Existente, deben ser estimados en función de los montos del Cuadro 2.2.8.
