Workbook

Sheet Formulario
B1: FORMULARIO - EVALUACIÓN EX POST
B2: ACLARACIÓN METODOLÓGICA:
B3: Los datos a ingresar corresponden únicamente a aquellas celdas identificadas con color amarillo y/o que contengan texto en azul. Los valores y fechas que allí figuran son arbitrarios, al sólo efecto de que las celdas dependientes no den señal de error.
B4: Las celdas con texto en rojo se calculan automáticamente (contienen fórmulas).
B7: BAPIN Nro. | D7: 999999 - Puesta en valor del Aeropuerto XX - Operación de cargas
B9: Información registrada en el BAPIN al xx/xx/xx hh:mm
B11: 2.1. Datos Generales
B13: Jurisdicción | F13: 57 | H13: Ministerio de Transporte
B15: SAF | F15: 664 | H15: Organismo Rector del Sistema Nacional de Aeropuertos (ORSNA)
B17: Programa | F17: 16 | H17: Control del Sistema de Aeropuertos
B19: Subprograma
B21: 2.2. Denominación del Proyecto de Inversión
B23: 999999 | D23: Puesta en valor del Aeropuerto X - Operación de cargas
B25: 2.3. Contribución
B27: 2.4. Modalidad de Contratación
B29: 2.5. Finalidad Función Subfunción
B31: 2.6. Localización Geográfica
B33: 2.7. Origen del Financiamiento Externo
B35: Préstamo | D35: Denominación
B38: 2.8. Proyectos Relacionados
B40: Tipo | D40: Código BAPIN | F40: Denominación
B46: 2.9. Principios Conceptuales de Formulación
B48: 1. ¿Cuál es la necesidad a satisfacer o la problemática a solucionar con el presente proyecto de inversión?
B50: El aeropuerto de XX recibe solo vuelos ocasionales, debido a que en su condición actual no cumple con las regulaciones ni tiene las condiciones mínimas para que operen aviones de mayor porte. En consecuencia, está perdiendo la oportunidad de transformarse en un hub de salida de la producción de las economías regionales cercanas. Esa producción recorre hoy z kilómetros para exportarse por el aeropuerto internacional más cercano.
B52: 2. ¿Cuál es el objetivo del proyecto?
B54: Que el aeropuerto XX alcance los estándares de seguridad y operación necesarios como para operar con vuelos de cargan nacional e internacional.
B56: 3. ¿Cuál es el producto o servicio que brindará el proyecto una vez finalizado?
B58: Operación de aviones de carga, para vuelos nacionales e internacionales.
B60: 4. ¿Qué alternativas han sido consideradas para satisfacer la necesidad o resolver la problemática planteada?
B62: Se evaluó establecer un circuito de bi-trenes hasta el aeropuerto internacional más cercano.
B64: 4B. Ordene las respuestas anteriores en una secuencia Efecto - Problema - Causa, y ubique al proyecto
B66: Secuencia Lógica | H66: Secuencia para el Proyecto | L66: ¿Dónde se ubica el proyecto?
B67: Efecto Problemático Observado | H67: Altos costos de salida de la producción exportable regional
B68: Situación Problemática causante del Efecto | H68: Aeropuerto no apto para aviones de carga "grandes"
B69: Causa Principal de la Situación Problemática | H69: Deficiencias en la infraestructura de pista y de ilumnicación del aeropuerto | L69: Puesta en valor del aeropuerto por repavimentación de pista e instalación de ILS
B71: 5. ¿Por qué han seleccionado al proyecto como la alternativa elegida?
B73: La comparación con la mejora alternativa (sistema de bi-trenes) muestra que el proyecto presenta mejores indicadores de rentabilidad.
B76: 5B. ¿Cuál es la mejor alternativa que se dejó de lado por el proyecto?
B78: Aprovechar la autopista entre A y B para agregar un doble carril (de dos sentidos de circulación) e implementar un sistema de bi-trenes.
B80: 6. ¿Cuál será la capacidad prestacional del proyecto una vez finalizado?
B81: El proyecto podrá operar 5 vuelos por día, con una capacidad promedio de 100 toneladas de carga por vuelo.
B83: 7. ¿Cuáles son las características de la inversión física que dan cuenta de la capacidad prestacional del proyecto?
B85: Se requiere a) repavimenter la pista (2.850 metros) y b) colocar un sistema de iluminación y balizas (ILS) que permita llevar la seguridad de los vuelos a estándares internacionales y habilitar vuelos nocturnos.
B87: 8. ¿Cuál es la vida útil del principal bien de capital a incorporar en el marco del proyecto?
B89: La vida útil se estima en 20 años
B91: 9. ¿Cuál será la cobertura territorial del proyecto? ¿Quiénes y cuántos serán los beneficiarios directos e indirectos?
B93: Cobertura territorial | F93: El proyecto permitirá la salida de la producción regional en un radio de 500 km.
B95: Beneficiarios directos | F95: Se estima que alrededor de 1.000 PyMEs podrán vender al mercado nacional y exportar.
B97: Beneficiarios indirectos | F97: La cadena de valor de las PyMEs beneficiadas, y el resto de la provincia
B99: 10. ¿El proyecto presenta dificultades o riesgos significativos (sociales, institucionales, legales ambientales, etc.)
B100: pasibles de suceder durante su ejecución, puesta en funcionamiento o cierre/desmantelamiento?
B102: S/N | C102: No
B104: Enumeración de Riesgos
B106: 11. ¿Han sido dimensionados los costos de operación y mantenimiento que tendrá el proyecto | M106: Sí
B107: cuando esté en funcionamiento?
B109: Monto total de costos de operación y mantenimiento del primer año de operación del proyecto ($ millones) | M109: =-+'[1]Flujos y VAN'!$M$34 -> #REF!
B111: Costo anual equivalente de los costos de operación y mantenimiento ($ millones) | M111: =+'[1]Flujos y VAN'!$W$3 -> #REF!
B113: ¿Los costos fueron validados con la institución, autoridad o nivel de gobierno nacional,
B114: provincial, municipal) que deberá afrontarlos? | M114: Sí
B116: Nombre de la institución, autoridad o nivel de gobierno que ha realizado la autorización
B117: ORSNA
B119: 12.0 ¿El proyecto requiere intervención de una autoridad ambiental competente? | L119: No
B121: Indique cuál es la Autoridad Ambiental Competente
B124: Observaciones de la DNIP
B126: Fecha | D126: Observación
B132: 2.10. Cronograma de Gastos y Ejecución Prevista del Proyecto | CF132: Celdas auxiliares
B134: 2.10.00. Datos Generales | CF134: NO BORRAR
B136: Inversión Estimada | H136: Inversión en millones de pesos, si se realizara toda en el Año 0 | CF136: Inversión con Inflación Estimada
B138: Costo Total del Proyecto | J138: Valor de contratación | M138: Código BAPIN | CF138: =+H208+H245 -> #N/A
B140: Mes/Año PREVISTO de inicio | J140: Fecha de inicio, no del estudio | M140: Denominación del Proyecto
B142: Mes/Año PREVISTO de terminación
B144: Duración Total (en meses) | H144: =(+H142-H140)/30 -> 0 | M144: Jurisdicción/SAF
B146: 2.10.01. Índices de Ajuste PROYECTADOS EX ANTE | J146: Mes de inicio
J147: 1 | K147: 2 | L147: 3 | M147: 4 | N147: 5 | O147: 6 | P147: 7 | Q147: 8 | R147: 9 | S147: 10 | T147: 11 | U147: 12 | V147: 13 | W147: 14 | X147: 15 | Y147: 16 | Z147: 17 | AA147: 18 | AB147: 19 | AC147: 20 | AD147: 21 | AE147: 22 | AF147: 23 | AG147: 24 | AH147: 25 | AI147: 26 | AJ147: 27 | AK147: 28 | AL147: 29 | AM147: 30 | AN147: 31 | AO147: 32 | AP147: 33 | AQ147: 34 | AR147: 35 | AS147: 36 | AT147: 37 | AU147: 38 | AV147: 39 | AW147: 40 | AX147: 41 | AY147: 42 | AZ147: 43 | BA147: 44 | BB147: 45 | BC147: 46 | BD147: 47 | BE147: 48 | BF147: 49 | BG147: 50 | BH147: 51 | BI147: 52 | BJ147: 53 | BK147: 54 | BL147: 55 | BM147: 56 | BN147: 57 | BO147: 58 | BP147: 59 | BQ147: 60 | BR147: 61 | BS147: 62 | BT147: 63 | BU147: 64 | BV147: 65 | BW147: 66 | BX147: 67 | BY147: 68 | BZ147: 69 | CA147: 70 | CB147: 71 | CC147: 72
F148: Año 0 Eval. Ex Ante | J148: =HLOOKUP(J147,Calendarios!$C$4:$YM$5,2,FALSE) -> #N/A | K148: =HLOOKUP(K147,Calendarios!$C$4:$YM$5,2,FALSE) -> #N/A | L148: =HLOOKUP(L147,Calendarios!$C$4:$YM$5,2,FALSE) -> #N/A | M148: =HLOOKUP(M147,Calendarios!$C$4:$YM$5,2,FALSE) -> #N/A | N148: =HLOOKUP(N147,Calendarios!$C$4:$YM$5,2,FALSE) -> #N/A | O148: =HLOOKUP(O147,Calendarios!$C$4:$YM$5,2,FALSE) -> #N/A | P148: =HLOOKUP(P147,Calendarios!$C$4:$YM$5,2,FALSE) -> #N/A | Q148: =HLOOKUP(Q147,Calendarios!$C$4:$YM$5,2,FALSE) -> #N/A | ... CC148: =HLOOKUP(CC147,Calendarios!$C$4:$YM$5,2,FALSE) -> #N/A
B150: Índice de Precios del Proyecto | F150: =HLOOKUP(H140,'IPIM y USD'!$C$6:$NN$9,3,FALSE) -> #N/A | J150: =+$F$150 -> #N/A | K150: =+$F$150 -> #N/A | L150: =+$F$150 -> #N/A | M150: =+$F$150 -> #N/A | N150: =+$F$150 -> #N/A | O150: =+$F$150 -> #N/A | P150: =+$F$150 -> #N/A | Q150: =+$F$150 -> #N/A | ... CC150: =+$F$150 -> #N/A
B152: Tipo de cambio | F152: =HLOOKUP(H140,'IPIM y USD'!$C$15:$NN$17,3,FALSE) -> #N/A | J152: =+$F$152 -> #N/A | K152: =+$F$152 -> #N/A | L152: =+$F$152 -> #N/A | M152: =+$F$152 -> #N/A | N152: =+$F$152 -> #N/A | O152: =+$F$152 -> #N/A | P152: =+$F$152 -> #N/A | Q152: =+$F$152 -> #N/A | ... CC152: =+$F$152 -> #N/A
B154: 2.10.02. Cronograma de ejecución de la OBRA FÍSICA - PREVISTO EX ANTE | L154: El porcentaje de ejecución mensual de cada tarea se calcula: | Q154: Sobre la obra
B156: Tarea | D156: % s/Total Obra | F156: % s/Total de Cada Tarea | H156: Comprobación | J156: =+J148 -> #N/A | K156: =+K148 -> #N/A | L156: =+L148 -> #N/A | M156: =+M148 -> #N/A | N156: =+N148 -> #N/A | O156: =+O148 -> #N/A | P156: =+P148 -> #N/A | Q156: =+Q148 -> #N/A | ... CC156: =+CC148 -> #N/A
F158: =SUM(J158:CC158) -> 0 | H158: =IF($Q$154="Sobre la obra",IF(D158=F158,"Completo","Incompleto"),IF(F158<1,"Incompleto","Completo")) -> Completo | J158: 0 | K158: 0 | L158: 0 | M158: 0 | N158: 0 | O158: 0 | P158: 0 | Q158: 0 | R158: 0 | S158: 0 | T158: 0 | U158: 0 | V158: 0 | W158: 0 | X158: 0 | Y158: 0 | Z158: 0 | AA158: 0 | AB158: 0 | AC158: 0 | AD158: 0 | AE158: 0 | AF158: 0 | AG158: 0 | AH158: 0 | AI158: 0 | AJ158: 0 | AK158: 0 | AL158: 0 | AM158: 0 | AN158: 0 | AO158: 0 | AP158: 0 | AQ158: 0 | AR158: 0 | AS158: 0 | AT158: 0 | AU158: 0 | AV158: 0 | AW158: 0 | AX158: 0 | AY158: 0 | AZ158: 0 | BA158: 0 | BB158: 0 | BC158: 0 | BD158: 0 | BE158: 0 | BF158: 0 | BG158: 0 | BH158: 0 | BI158: 0 | BJ158: 0 | BK158: 0 | BL158: 0 | BM158: 0 | BN158: 0 | BO158: 0 | BP158: 0 | BQ158: 0 | BR158: 0 | BS158: 0 | BT158: 0 | BU158: 0 | BV158: 0 | BW158: 0 | BX158: 0 | BY158: 0 | BZ158: 0 | CA158: 0 | CB158: 0 | CC158: 0
F159: =SUM(J159:CC159) -> 0 | H159: =IF($Q$154="Sobre la obra",IF(D159=F159,"Completo","Incompleto"),IF(F159<1,"Incompleto","Completo")) -> Completo | J159: 0 | K159: 0 | L159: 0 | M159: 0 | N159: 0 | O159: 0 | P159: 0 | Q159: 0 | R159: 0 | S159: 0 | T159: 0 | U159: 0 | V159: 0 | W159: 0 | X159: 0 | Y159: 0 | Z159: 0 | AA159: 0 | AB159: 0 | AC159: 0 | AD159: 0 | AE159: 0 | AF159: 0 | AG159: 0 | AH159: 0 | AI159: 0 | AJ159: 0 | AK159: 0 | AL159: 0 | AM159: 0 | AN159: 0 | AO159: 0 | AP159: 0 | AQ159: 0 | AR159: 0 | AS159: 0 | AT159: 0 | AU159: 0 | AV159: 0 | AW159: 0 | AX159: 0 | AY159: 0 | AZ159: 0 | BA159: 0 | BB159: 0 | BC159: 0 | BD159: 0 | BE159: 0 | BF159: 0 | BG159: 0 | BH159: 0 | BI159: 0 | BJ159: 0 | BK159: 0 | BL159: 0 | BM159: 0 | BN159: 0 | BO159: 0 | BP159: 0 | BQ159: 0 | BR159: 0 | BS159: 0 | BT159: 0 | BU159: 0 | BV159: 0 | BW159: 0 | BX159: 0 | BY159: 0 | BZ159: 0 | CA159: 0 | CB159: 0 | CC159: 0
F160: =SUM(J160:CC160) -> 0 | H160: =IF($Q$154="Sobre la obra",IF(D160=F160,"Completo","Incompleto"),IF(F160<1,"Incompleto","Completo")) -> Completo | J160: 0 | K160: 0 | L160: 0 | M160: 0 | N160: 0 | O160: 0 | P160: 0 | Q160: 0 | R160: 0 | S160: 0 | T160: 0 | U160: 0 | V160: 0 | W160: 0 | X160: 0 | Y160: 0 | Z160: 0 | AA160: 0 | AB160: 0 | AC160: 0 | AD160: 0 | AE160: 0 | AF160: 0 | AG160: 0 | AH160: 0 | AI160: 0 | AJ160: 0 | AK160: 0 | AL160: 0 | AM160: 0 | AN160: 0 | AO160: 0 | AP160: 0 | AQ160: 0 | AR160: 0 | AS160: 0 | AT160: 0 | AU160: 0 | AV160: 0 | AW160: 0 | AX160: 0 | AY160: 0 | AZ160: 0 | BA160: 0 | BB160: 0 | BC160: 0 | BD160: 0 | BE160: 0 | BF160: 0 | BG160: 0 | BH160: 0 | BI160: 0 | BJ160: 0 | BK160: 0 | BL160: 0 | BM160: 0 | BN160: 0 | BO160: 0 | BP160: 0 | BQ160: 0 | BR160: 0 | BS160: 0 | BT160: 0 | BU160: 0 | BV160: 0 | BW160: 0 | BX160: 0 | BY160: 0 | BZ160: 0 | CA160: 0 | CB160: 0 | CC160: 0
F161: =SUM(J161:CC161) -> 0 | H161: =IF($Q$154="Sobre la obra",IF(D161=F161,"Completo","Incompleto"),IF(F161<1,"Incompleto","Completo")) -> Completo | J161: 0 | K161: 0 | L161: 0 | M161: 0 | N161: 0 | O161: 0 | P161: 0 | Q161: 0 | R161: 0 | S161: 0 | T161: 0 | U161: 0 | V161: 0 | W161: 0 | X161: 0 | Y161: 0 | Z161: 0 | AA161: 0 | AB161: 0 | AC161: 0 | AD161: 0 | AE161: 0 | AF161: 0 | AG161: 0 | AH161: 0 | AI161: 0 | AJ161: 0 | AK161: 0 | AL161: 0 | AM161: 0 | AN161: 0 | AO161: 0 | AP161: 0 | AQ161: 0 | AR161: 0 | AS161: 0 | AT161: 0 | AU161: 0 | AV161: 0 | AW161: 0 | AX161: 0 | AY161: 0 | AZ161: 0 | BA161: 0 | BB161: 0 | BC161: 0 | BD161: 0 | BE161: 0 | BF161: 0 | BG161: 0 | BH161: 0 | BI161: 0 | BJ161: 0 | BK161: 0 | BL161: 0 | BM161: 0 | BN161: 0 | BO161: 0 | BP161: 0 | BQ161: 0 | BR161: 0 | BS161: 0 | BT161: 0 | BU161: 0 | BV161: 0 | BW161: 0 | BX161: 0 | BY161: 0 | BZ161: 0 | CA161: 0 | CB161: 0 | CC161: 0
F162: =SUM(J162:CC162) -> 0 | H162: =IF($Q$154="Sobre la obra",IF(D162=F162,"Completo","Incompleto"),IF(F162<1,"Incompleto","Completo")) -> Completo | J162: 0 | K162: 0 | L162: 0 | M162: 0 | N162: 0 | O162: 0 | P162: 0 | Q162: 0 | R162: 0 | S162: 0 | T162: 0 | U162: 0 | V162: 0 | W162: 0 | X162: 0 | Y162: 0 | Z162: 0 | AA162: 0 | AB162: 0 | AC162: 0 | AD162: 0 | AE162: 0 | AF162: 0 | AG162: 0 | AH162: 0 | AI162: 0 | AJ162: 0 | AK162: 0 | AL162: 0 | AM162: 0 | AN162: 0 | AO162: 0 | AP162: 0 | AQ162: 0 | AR162: 0 | AS162: 0 | AT162: 0 | AU162: 0 | AV162: 0 | AW162: 0 | AX162: 0 | AY162: 0 | AZ162: 0 | BA162: 0 | BB162: 0 | BC162: 0 | BD162: 0 | BE162: 0 | BF162: 0 | BG162: 0 | BH162: 0 | BI162: 0 | BJ162: 0 | BK162: 0 | BL162: 0 | BM162: 0 | BN162: 0 | BO162: 0 | BP162: 0 | BQ162: 0 | BR162: 0 | BS162: 0 | BT162: 0 | BU162: 0 | BV162: 0 | BW162: 0 | BX162: 0 | BY162: 0 | BZ162: 0 | CA162: 0 | CB162: 0 | CC162: 0
F163: =SUM(J163:CC163) -> 0 | H163: =IF($Q$154="Sobre la obra",IF(D163=F163,"Completo","Incompleto"),IF(F163<1,"Incompleto","Completo")) -> Completo | J163: 0 | K163: 0 | L163: 0 | M163: 0 | N163: 0 | O163: 0 | P163: 0 | Q163: 0 | R163: 0 | S163: 0 | T163: 0 | U163: 0 | V163: 0 | W163: 0 | X163: 0 | Y163: 0 | Z163: 0 | AA163: 0 | AB163: 0 | AC163: 0 | AD163: 0 | AE163: 0 | AF163: 0 | AG163: 0 | AH163: 0 | AI163: 0 | AJ163: 0 | AK163: 0 | AL163: 0 | AM163: 0 | AN163: 0 | AO163: 0 | AP163: 0 | AQ163: 0 | AR163: 0 | AS163: 0 | AT163: 0 | AU163: 0 | AV163: 0 | AW163: 0 | AX163: 0 | AY163: 0 | AZ163: 0 | BA163: 0 | BB163: 0 | BC163: 0 | BD163: 0 | BE163: 0 | BF163: 0 | BG163: 0 | BH163: 0 | BI163: 0 | BJ163: 0 | BK163: 0 | BL163: 0 | BM163: 0 | BN163: 0 | BO163: 0 | BP163: 0 | BQ163: 0 | BR163: 0 | BS163: 0 | BT163: 0 | BU163: 0 | BV163: 0 | BW163: 0 | BX163: 0 | BY163: 0 | BZ163: 0 | CA163: 0 | CB163: 0 | CC163: 0
F164: =SUM(J164:CC164) -> 0 | H164: =IF($Q$154="Sobre la obra",IF(D164=F164,"Completo","Incompleto"),IF(F164<1,"Incompleto","Completo")) -> Completo | J164: 0 | K164: 0 | L164: 0 | M164: 0 | N164: 0 | O164: 0 | P164: 0 | Q164: 0 | R164: 0 | S164: 0 | T164: 0 | U164: 0 | V164: 0 | W164: 0 | X164: 0 | Y164: 0 | Z164: 0 | AA164: 0 | AB164: 0 | AC164: 0 | AD164: 0 | AE164: 0 | AF164: 0 | AG164: 0 | AH164: 0 | AI164: 0 | AJ164: 0 | AK164: 0 | AL164: 0 | AM164: 0 | AN164: 0 | AO164: 0 | AP164: 0 | AQ164: 0 | AR164: 0 | AS164: 0 | AT164: 0 | AU164: 0 | AV164: 0 | AW164: 0 | AX164: 0 | AY164: 0 | AZ164: 0 | BA164: 0 | BB164: 0 | BC164: 0 | BD164: 0 | BE164: 0 | BF164: 0 | BG164: 0 | BH164: 0 | BI164: 0 | BJ164: 0 | BK164: 0 | BL164: 0 | BM164: 0 | BN164: 0 | BO164: 0 | BP164: 0 | BQ164: 0 | BR164: 0 | BS164: 0 | BT164: 0 | BU164: 0 | BV164: 0 | BW164: 0 | BX164: 0 | BY164: 0 | BZ164: 0 | CA164: 0 | CB164: 0 | CC164: 0
F165: =SUM(J165:CC165) -> 0 | H165: =IF($Q$154="Sobre la obra",IF(D165=F165,"Completo","Incompleto"),IF(F165<1,"Incompleto","Completo")) -> Completo | J165: 0 | K165: 0 | L165: 0 | M165: 0 | N165: 0 | O165: 0 | P165: 0 | Q165: 0 | R165: 0 | S165: 0 | T165: 0 | U165: 0 | V165: 0 | W165: 0 | X165: 0 | Y165: 0 | Z165: 0 | AA165: 0 | AB165: 0 | AC165: 0 | AD165: 0 | AE165: 0 | AF165: 0 | AG165: 0 | AH165: 0 | AI165: 0 | AJ165: 0 | AK165: 0 | AL165: 0 | AM165: 0 | AN165: 0 | AO165: 0 | AP165: 0 | AQ165: 0 | AR165: 0 | AS165: 0 | AT165: 0 | AU165: 0 | AV165: 0 | AW165: 0 | AX165: 0 | AY165: 0 | AZ165: 0 | BA165: 0 | BB165: 0 | BC165: 0 | BD165: 0 | BE165: 0 | BF165: 0 | BG165: 0 | BH165: 0 | BI165: 0 | BJ165: 0 | BK165: 0 | BL165: 0 | BM165: 0 | BN165: 0 | BO165: 0 | BP165: 0 | BQ165: 0 | BR165: 0 | BS165: 0 | BT165: 0 | BU165: 0 | BV165: 0 | BW165: 0 | BX165: 0 | BY165: 0 | BZ165: 0 | CA165: 0 | CB165: 0 | CC165: 0
F166: =SUM(J166:CC166) -> 0 | H166: =IF($Q$154="Sobre la obra",IF(D166=F166,"Completo","Incompleto"),IF(F166<1,"Incompleto","Completo")) -> Completo | J166: 0 | K166: 0 | L166: 0 | M166: 0 | N166: 0 | O166: 0 | P166: 0 | Q166: 0 | R166: 0 | S166: 0 | T166: 0 | U166: 0 | V166: 0 | W166: 0 | X166: 0 | Y166: 0 | Z166: 0 | AA166: 0 | AB166: 0 | AC166: 0 | AD166: 0 | AE166: 0 | AF166: 0 | AG166: 0 | AH166: 0 | AI166: 0 | AJ166: 0 | AK166: 0 | AL166: 0 | AM166: 0 | AN166: 0 | AO166: 0 | AP166: 0 | AQ166: 0 | AR166: 0 | AS166: 0 | AT166: 0 | AU166: 0 | AV166: 0 | AW166: 0 | AX166: 0 | AY166: 0 | AZ166: 0 | BA166: 0 | BB166: 0 | BC166: 0 | BD166: 0 | BE166: 0 | BF166: 0 | BG166: 0 | BH166: 0 | BI166: 0 | BJ166: 0 | BK166: 0 | BL166: 0 | BM166: 0 | BN166: 0 | BO166: 0 | BP166: 0 | BQ166: 0 | BR166: 0 | BS166: 0 | BT166: 0 | BU166: 0 | BV166: 0 | BW166: 0 | BX166: 0 | BY166: 0 | BZ166: 0 | CA166: 0 | CB166: 0 | CC166: 0
F167: =SUM(J167:CC167) -> 0 | H167: =IF($Q$154="Sobre la obra",IF(D167=F167,"Completo","Incompleto"),IF(F167<1,"Incompleto","Completo")) -> Completo | J167: 0 | K167: 0 | L167: 0 | M167: 0 | N167: 0 | O167: 0 | P167: 0 | Q167: 0 | R167: 0 | S167: 0 | T167: 0 | U167: 0 | V167: 0 | W167: 0 | X167: 0 | Y167: 0 | Z167: 0 | AA167: 0 | AB167: 0 | AC167: 0 | AD167: 0 | AE167: 0 | AF167: 0 | AG167: 0 | AH167: 0 | AI167: 0 | AJ167: 0 | AK167: 0 | AL167: 0 | AM167: 0 | AN167: 0 | AO167: 0 | AP167: 0 | AQ167: 0 | AR167: 0 | AS167: 0 | AT167: 0 | AU167: 0 | AV167: 0 | AW167: 0 | AX167: 0 | AY167: 0 | AZ167: 0 | BA167: 0 | BB167: 0 | BC167: 0 | BD167: 0 | BE167: 0 | BF167: 0 | BG167: 0 | BH167: 0 | BI167: 0 | BJ167: 0 | BK167: 0 | BL167: 0 | BM167: 0 | BN167: 0 | BO167: 0 | BP167: 0 | BQ167: 0 | BR167: 0 | BS167: 0 | BT167: 0 | BU167: 0 | BV167: 0 | BW167: 0 | BX167: 0 | BY167: 0 | BZ167: 0 | CA167: 0 | CB167: 0 | CC167: 0
F168: =SUM(J168:CC168) -> 0 | H168: =IF($Q$154="Sobre la obra",IF(D168=F168,"Completo","Incompleto"),IF(F168<1,"Incompleto","Completo")) -> Completo | J168: 0 | K168: 0 | L168: 0 | M168: 0 | N168: 0 | O168: 0 | P168: 0 | Q168: 0 | R168: 0 | S168: 0 | T168: 0 | U168: 0 | V168: 0 | W168: 0 | X168: 0 | Y168: 0 | Z168: 0 | AA168: 0 | AB168: 0 | AC168: 0 | AD168: 0 | AE168: 0 | AF168: 0 | AG168: 0 | AH168: 0 | AI168: 0 | AJ168: 0 | AK168: 0 | AL168: 0 | AM168: 0 | AN168: 0 | AO168: 0 | AP168: 0 | AQ168: 0 | AR168: 0 | AS168: 0 | AT168: 0 | AU168: 0 | AV168: 0 | AW168: 0 | AX168: 0 | AY168: 0 | AZ168: 0 | BA168: 0 | BB168: 0 | BC168: 0 | BD168: 0 | BE168: 0 | BF168: 0 | BG168: 0 | BH168: 0 | BI168: 0 | BJ168: 0 | BK168: 0 | BL168: 0 | BM168: 0 | BN168: 0 | BO168: 0 | BP168: 0 | BQ168: 0 | BR168: 0 | BS168: 0 | BT168: 0 | BU168: 0 | BV168: 0 | BW168: 0 | BX168: 0 | BY168: 0 | BZ168: 0 | CA168: 0 | CB168: 0 | CC168: 0
F169: =SUM(J169:CC169) -> 0 | H169: =IF($Q$154="Sobre la obra",IF(D169=F169,"Completo","Incompleto"),IF(F169<1,"Incompleto","Completo")) -> Completo | J169: 0 | K169: 0 | L169: 0 | M169: 0 | N169: 0 | O169: 0 | P169: 0 | Q169: 0 | R169: 0 | S169: 0 | T169: 0 | U169: 0 | V169: 0 | W169: 0 | X169: 0 | Y169: 0 | Z169: 0 | AA169: 0 | AB169: 0 | AC169: 0 | AD169: 0 | AE169: 0 | AF169: 0 | AG169: 0 | AH169: 0 | AI169: 0 | AJ169: 0 | AK169: 0 | AL169: 0 | AM169: 0 | AN169: 0 | AO169: 0 | AP169: 0 | AQ169: 0 | AR169: 0 | AS169: 0 | AT169: 0 | AU169: 0 | AV169: 0 | AW169: 0 | AX169: 0 | AY169: 0 | AZ169: 0 | BA169: 0 | BB169: 0 | BC169: 0 | BD169: 0 | BE169: 0 | BF169: 0 | BG169: 0 | BH169: 0 | BI169: 0 | BJ169: 0 | BK169: 0 | BL169: 0 | BM169: 0 | BN169: 0 | BO169: 0 | BP169: 0 | BQ169: 0 | BR169: 0 | BS169: 0 | BT169: 0 | BU169: 0 | BV169: 0 | BW169: 0 | BX169: 0 | BY169: 0 | BZ169: 0 | CA169: 0 | CB169: 0 | CC169: 0
... F177: =SUM(J177:CC177) -> 0 | H177: =IF($Q$154="Sobre la obra",IF(D177=F177,"Completo","Incompleto"),IF(F177<1,"Incompleto","Completo")) -> Completo | J177: 0 | K177: 0 | L177: 0 | M177: 0 | N177: 0 | O177: 0 | P177: 0 | Q177: 0 | R177: 0 | S177: 0 | T177: 0 | U177: 0 | V177: 0 | W177: 0 | X177: 0 | Y177: 0 | Z177: 0 | AA177: 0 | AB177: 0 | AC177: 0 | AD177: 0 | AE177: 0 | AF177: 0 | AG177: 0 | AH177: 0 | AI177: 0 | AJ177: 0 | AK177: 0 | AL177: 0 | AM177: 0 | AN177: 0 | AO177: 0 | AP177: 0 | AQ177: 0 | AR177: 0 | AS177: 0 | AT177: 0 | AU177: 0 | AV177: 0 | AW177: 0 | AX177: 0 | AY177: 0 | AZ177: 0 | BA177: 0 | BB177: 0 | BC177: 0 | BD177: 0 | BE177: 0 | BF177: 0 | BG177: 0 | BH177: 0 | BI177: 0 | BJ177: 0 | BK177: 0 | BL177: 0 | BM177: 0 | BN177: 0 | BO177: 0 | BP177: 0 | BQ177: 0 | BR177: 0 | BS177: 0 | BT177: 0 | BU177: 0 | BV177: 0 | BW177: 0 | BX177: 0 | BY177: 0 | BZ177: 0 | CA177: 0 | CB177: 0 | CC177: 0
B179: Total (%) | D179: =SUM(D158:D178) -> 0 | F179: Comprobación (s/ Total Obra) | H179: =SUM(J179:CC179) -> 0 | J179: =IF($Q$154="Sobre la obra",SUM(J158:J177),IF($Q$154="Sobre cada tarea",SUMPRODUCT($D$158:$D$177,J158:J177),"")) -> 0 | K179: =IF($Q$154="Sobre la obra",SUM(K158:K177),IF($Q$154="Sobre cada tarea",SUMPRODUCT($D$158:$D$177,K158:K177),"")) -> 0 | L179: =IF($Q$154="Sobre la obra",SUM(L158:L177),IF($Q$154="Sobre cada tarea",SUMPRODUCT($D$158:$D$177,L158:L177),"")) -> 0 | M179: =IF($Q$154="Sobre la obra",SUM(M158:M177),IF($Q$154="Sobre cada tarea",SUMPRODUCT($D$158:$D$177,M158:M177),"")) -> 0 | N179: =IF($Q$154="Sobre la obra",SUM(N158:N177),IF($Q$154="Sobre cada tarea",SUMPRODUCT($D$158:$D$177,N158:N177),"")) -> 0 | O179: =IF($Q$154="Sobre la obra",SUM(O158:O177),IF($Q$154="Sobre cada tarea",SUMPRODUCT($D$158:$D$177,O158:O177),"")) -> 0 | P179: =IF($Q$154="Sobre la obra",SUM(P158:P177),IF($Q$154="Sobre cada tarea",SUMPRODUCT($D$158:$D$177,P158:P177),"")) -> 0 | Q179: =IF($Q$154="Sobre la obra",SUM(Q158:Q177),IF($Q$154="Sobre cada tarea",SUMPRODUCT($D$158:$D$177,Q158:Q177),"")) -> 0 | ... CC179: =IF($Q$154="Sobre la obra",SUM(CC158:CC177),IF($Q$154="Sobre cada tarea",SUMPRODUCT($D$158:$D$177,CC158:CC177),"")) -> 0
B181: % Acumulado | J181: =+J179 -> 0 | K181: =+J181+K179 -> 0 | L181: =+K181+L179 -> 0 | M181: =+L181+M179 -> 0 | N181: =+M181+N179 -> 0 | O181: =+N181+O179 -> 0 | P181: =+O181+P179 -> 0 | Q181: =+P181+Q179 -> 0 | R181: =+Q181+R179 -> 0 | ... CC181: =+CB181+CC179 -> 0
B183: 2.10.03A. Cronograma de la ejecución FINANCIERA EN PESOS - PREVISTO EX ANTE (Millones de pesos)
B185: Tarea | D185: %Costo Tarea s/Costo Total | F185: Costo por Tarea | H185: Costo por Tarea (Suma del Gantt) | J185: =+J156 -> #N/A | K185: =+K156 -> #N/A | L185: =+L156 -> #N/A | M185: =+M156 -> #N/A | N185: =+N156 -> #N/A | O185: =+O156 -> #N/A | P185: =+P156 -> #N/A | Q185: =+Q156 -> #N/A | ... CC185: =+CC156 -> #N/A
B187: =INDIRECT("B" & (157 + ROWS($A$1:A1))) -> 0 | D187: =IFERROR(IF($CF$138=0,0,F187/$CF$138), "Ver fechas") -> Ver fechas | F187: =H187 -> 0 | H187: =SUM(J187:CC187) -> 0 | J187: 0 | K187: 0 | L187: 0 | M187: 0 | N187: 0 | O187: 0 | P187: 0 | Q187: 0 | R187: 0 | S187: 0 | T187: 0 | U187: 0 | V187: 0 | W187: 0 | X187: 0 | Y187: 0 | Z187: 0 | AA187: 0 | AB187: 0 | AC187: 0 | AD187: 0 | AE187: 0 | AF187: 0 | AG187: 0 | AH187: 0 | AI187: 0 | AJ187: 0 | AK187: 0 | AL187: 0 | AM187: 0 | AN187: 0 | AO187: 0 | AP187: 0 | AQ187: 0 | AR187: 0 | AS187: 0 | AT187: 0 | AU187: 0 | AV187: 0 | AW187: 0 | AX187: 0 | AY187: 0 | AZ187: 0 | BA187: 0 | BB187: 0 | BC187: 0 | BD187: 0 | BE187: 0 | BF187: 0 | BG187: 0 | BH187: 0 | BI187: 0 | BJ187: 0 | BK187: 0 | BL187: 0 | BM187: 0 | BN187: 0 | BO187: 0 | BP187: 0 | BQ187: 0 | BR187: 0 | BS187: 0 | BT187: 0 | BU187: 0 | BV187: 0 | BW187: 0 | BX187: 0 | BY187: 0 | BZ187: 0 | CA187: 0 | CB187: 0 | CC187: 0
B188: =INDIRECT("B" & (157 + ROWS($A$1:A2))) -> 0 | D188: =IFERROR(IF($CF$138=0,0,F188/$CF$138), "Ver fechas") -> Ver fechas | F188: =H188 -> 0 | H188: =SUM(J188:CC188) -> 0 | J188: 0 | K188: 0 | L188: 0 | M188: 0 | N188: 0 | O188: 0 | P188: 0 | Q188: 0 | R188: 0 | S188: 0 | T188: 0 | U188: 0 | V188: 0 | W188: 0 | X188: 0 | Y188: 0 | Z188: 0 | AA188: 0 | AB188: 0 | AC188: 0 | AD188: 0 | AE188: 0 | AF188: 0 | AG188: 0 | AH188: 0 | AI188: 0 | AJ188: 0 | AK188: 0 | AL188: 0 | AM188: 0 | AN188: 0 | AO188: 0 | AP188: 0 | AQ188: 0 | AR188: 0 | AS188: 0 | AT188: 0 | AU188: 0 | AV188: 0 | AW188: 0 | AX188: 0 | AY188: 0 | AZ188: 0 | BA188: 0 | BB188: 0 | BC188: 0 | BD188: 0 | BE188: 0 | BF188: 0 | BG188: 0 | BH188: 0 | BI188: 0 | BJ188: 0 | BK188: 0 | BL188: 0 | BM188: 0 | BN188: 0 | BO188: 0 | BP188: 0 | BQ188: 0 | BR188: 0 | BS188: 0 | BT188: 0 | BU188: 0 | BV188: 0 | BW188: 0 | BX188: 0 | BY188: 0 | BZ188: 0 | CA188: 0 | CB188: 0 | CC188: 0
B189: =INDIRECT("B" & (157 + ROWS($A$1:A3))) -> 0 | D189: =IFERROR(IF($CF$138=0,0,F189/$CF$138), "Ver fechas") -> Ver fechas | F189: =H189 -> 0 | H189: =SUM(J189:CC189) -> 0 | J189: 0 | K189: 0 | L189: 0 | M189: 0 | N189: 0 | O189: 0 | P189: 0 | Q189: 0 | R189: 0 | S189: 0 | T189: 0 | U189: 0 | V189: 0 | W189: 0 | X189: 0 | Y189: 0 | Z189: 0 | AA189: 0 | AB189: 0 | AC189: 0 | AD189: 0 | AE189: 0 | AF189: 0 | AG189: 0 | AH189: 0 | AI189: 0 | AJ189: 0 | AK189: 0 | AL189: 0 | AM189: 0 | AN189: 0 | AO189: 0 | AP189: 0 | AQ189: 0 | AR189: 0 | AS189: 0 | AT189: 0 | AU189: 0 | AV189: 0 | AW189: 0 | AX189: 0 | AY189: 0 | AZ189: 0 | BA189: 0 | BB189: 0 | BC189: 0 | BD189: 0 | BE189: 0 | BF189: 0 | BG189: 0 | BH189: 0 | BI189: 0 | BJ189: 0 | BK189: 0 | BL189: 0 | BM189: 0 | BN189: 0 | BO189: 0 | BP189: 0 | BQ189: 0 | BR189: 0 | BS189: 0 | BT189: 0 | BU189: 0 | BV189: 0 | BW189: 0 | BX189: 0 | BY189: 0 | BZ189: 0 | CA189: 0 | CB189: 0 | CC189: 0
B190: =INDIRECT("B" & (157 + ROWS($A$1:A4))) -> 0 | D190: =IFERROR(IF($CF$138=0,0,F190/$CF$138), "Ver fechas") -> Ver fechas | F190: =H190 -> 0 | H190: =SUM(J190:CC190) -> 0 | J190: 0 | K190: 0 | L190: 0 | M190: 0 | N190: 0 | O190: 0 | P190: 0 | Q190: 0 | R190: 0 | S190: 0 | T190: 0 | U190: 0 | V190: 0 | W190: 0 | X190: 0 | Y190: 0 | Z190: 0 | AA190: 0 | AB190: 0 | AC190: 0 | AD190: 0 | AE190: 0 | AF190: 0 | AG190: 0 | AH190: 0 | AI190: 0 | AJ190: 0 | AK190: 0 | AL190: 0 | AM190: 0 | AN190: 0 | AO190: 0 | AP190: 0 | AQ190: 0 | AR190: 0 | AS190: 0 | AT190: 0 | AU190: 0 | AV190: 0 | AW190: 0 | AX190: 0 | AY190: 0 | AZ190: 0 | BA190: 0 | BB190: 0 | BC190: 0 | BD190: 0 | BE190: 0 | BF190: 0 | BG190: 0 | BH190: 0 | BI190: 0 | BJ190: 0 | BK190: 0 | BL190: 0 | BM190: 0 | BN190: 0 | BO190: 0 | BP190: 0 | BQ190: 0 | BR190: 0 | BS190: 0 | BT190: 0 | BU190: 0 | BV190: 0 | BW190: 0 | BX190: 0 | BY190: 0 | BZ190: 0 | CA190: 0 | CB190: 0 | CC190: 0
...

Sheet Formulario redet
A1: EVALUACIÓN DE TERMINACIÓN | N1: ACLARACIÓN:
A2: FORMULARIOS | N2: Los datos que deben cargarse son únicamente los
A3: El Paramillo, Mendoza, Colector Boedo – Ponce | N3: que están en celdas con letras azules.
B5: BAPIN Nro. | D5: 999999 - Puesta en valor del Aeropuerto XX - Operación de cargas
B7: Información registrada en el BAPIN al xx/xx/xx hh:mm
B9: 2.1. Datos Generales
B11: Jurisdicción | F11: 57 | H11: Ministerio de Transporte
B13: SAF | F13: 664 | H13: Organismo Rector del Sistema Nacional de Aeropuertos (ORSNA)
B15: Programa | F15: 16 | H15: Control del Sistema de Aeropuertos
B17: Subprograma
B19: 2.2. Denominación del Proyecto de Inversión
B21: 999999 | D21: Puesta en valor del Aeropuerto X - Operación de cargas
B23: 2.3. Contribución
B25: 2.4. Modalidad de Contratación
B27: 2.5. Finalidad Función Subfunción
B29: 2.6. Localización Geográfica
B31: 2.7. Origen del Financiamiento Externo
B33: Préstamo | D33: Denominación
B36: 2.8. Proyectos Relacionados
B38: Tipo | D38: Código BAPIN | F38: Denominación
B44: 2.9. Principios Conceptuales de Formulación
B46: 1. ¿Cuál es la necesidad a satisfacer o la problemática a solucionar con el presente proyecto de inversión?
B48: El aeropuerto de XX recibe solo vuelos ocasionales, debido a que en su condición actual no cumple con las regulaciones ni tiene las condiciones mínimas para que operen aviones de mayor porte. En consecuencia, está perdiendo la oportunidad de transformarse en un hub de salida de la producción de las economías regionales cercanas. Esa producción recorre hoy z kilómetros para exportarse por el aeropuerto internacional más cercano.
B50: 2. ¿Cuál es el objetivo del proyecto?
B52: Que el aeropuerto XX alcance los estándares de seguridad y operación necesarios como para operar con vuelos de cargan nacional e internacional.
B54: 3. ¿Cuál es el producto o servicio que brindará el proyecto una vez finalizado?
B56: Operación de aviones de carga, para vuelos nacionales e internacionales.
B58: 4. ¿Qué alternativas han sido consideradas para satisfacer la necesidad o resolver la problemática planteada?
B60: Se evaluó establecer un circuito de bi-trenes hasta el aeropuerto internacional más cercano.
B62: 4B. Ordene las respuestas anteriores en una secuencia Efecto - Problema - Causa, y ubique al proyecto
B64: Secuencia Lógica | H64: Secuencia para el Proyecto | L64: ¿Dónde se ubica el proyecto?
B65: Efecto Problemático Observado | H65: Altos costos de salida de la producción exportable regional
B66: Situación Problemática causante del Efecto | H66: Aeropuerto no apto para aviones de carga "grandes"
B67: Causa Principal de la Situación Problemática | H67: Deficiencias en la infraestructura de pista y de ilumnicación del aeropuerto | L67: Puesta en valor del aeropuerto por repavimentación de pista e instalación de ILS
B69: 5. ¿Por qué han seleccionado al proyecto como la alternativa elegida?
B71: La comparación con la mejora alternativa (sistema de bi-trenes) muestra que el proyecto presenta mejores indicadores de rentabilidad.
B74: 5B. ¿Cuál es la mejor alternativa que se dejó de lado por el proyecto?
B76: Aprovechar la autopista entre A y B para agregar un doble carril (de dos sentidos de circulación) e implementar un sistema de bi-trenes.
B78: 6. ¿Cuál será la capacidad prestacional del proyecto una vez finalizado?
B79: El proyecto podrá operar 5 vuelos por día, con una capacidad promedio de 100 toneladas de carga por vuelo.
B81: 7. ¿Cuáles son las características de la inversión física que dan cuenta de la capacidad prestacional del proyecto?
B83: Se requiere a) repavimenter la pista (2.850 metros) y b) colocar un sistema de iluminación y balizas (ILS) que permita llevar la seguridad de los vuelos a estándares internacionales y habilitar vuelos nocturnos.
B85: 8. ¿Cuál es la vida útil del principal bien de capital a incorporar en el marco del proyecto?
B87: La vida útil se estima en 20 años
B89: 9. ¿Cuál será la cobertura territorial del proyecto? ¿Quiénes y cuántos serán los beneficiarios directos e indirectos?
B91: Cobertura territorial | F91: El proyecto permitirá la salida de la producción regional en un radio de 500 km.
B93: Beneficiarios directos | F93: Se estima que alrededor de 1.000 PyMEs podrán vender al mercado nacional y exportar.
B95: Beneficiarios indirectos | F95: La cadena de valor de las PyMEs beneficiadas, y el resto de la provincia
B97: 10. ¿El proyecto presenta dificultades o riesgos significativos (sociales, institucionales, legales ambientales, etc.)
B98: pasibles de suceder durante su ejecución, puesta en funcionamiento o cierre/desmantelamiento?
B100: S/N | C100: No
B102: Enumeración de Riesgos
B104: 11. ¿Han sido dimensionados los costos de operación y mantenimiento que tendrá el proyecto | M104: Sí
B105: cuando esté en funcionamiento?
B107: Monto total de costos de operación y mantenimiento del primer año de operación del proyecto ($ millones) | M107: =-+'[1]Flujos y VAN'!$M$34 -> #REF!
B109: Costo anual equivalente de los costos de operación y mantenimiento ($ millones) | M109: =+'[1]Flujos y VAN'!$W$3 -> #REF!
B111: ¿Los costos fueron validados con la institución, autoridad o nivel de gobierno nacional,
B112: provincial, municipal) que deberá afrontarlos? | M112: Sí
B114: Nombre de la institución, autoridad o nivel de gobierno que ha realizado la autorización
B115: ORSNA
B117: 12.0 ¿El proyecto requiere intervención de una autoridad ambiental competente? | L117: No
B119: Indique cuál es la Autoridad Ambiental Competente
B122: Observaciones de la DNIP
B124: Fecha | D124: Observación
B130: 2.10. Cronograma de Gastos y Ejecución Prevista del Proyecto | CF130: Celdas auxiliares
B132: 2.10.00. Datos Generales | CF132: NO BORRAR
B134: Inversión Estimada | H134: En millones de pesos, si se hiciera toda en el Año 0 | CF134: Inversión con Inflación Estimada
B136: Costo Total del Proyecto | H136: 0 | J136: Valor de contratación, no del estudio o del pliego de licitación | CF136: =+H174+H195 -> 0
B138: Mes/Año PREVISTO de inicio | H138: 43466 | J138: Fecha prevista de inicio de la inversión luego de la licitación, no la fecha estimada en el estudio de preinversión
B140: Mes/Año PREVISTO de terminación | H140: 44196
B142: Duración Total (en meses) | H142: =(+H140-H138)/30 -> 24.333333
B144: 2.10.01. Índices de Ajuste PROYECTADOS EX ANTE | J144: Mes de inicio
J145: 1 | K145: 2 | L145: 3 | M145: 4 | N145: 5 | O145: 6 | P145: 7 | Q145: 8 | R145: 9 | S145: 10 | T145: 11 | U145: 12 | V145: 13 | W145: 14 | X145: 15 | Y145: 16 | Z145: 17 | AA145: 18 | AB145: 19 | AC145: 20 | AD145: 21 | AE145: 22 | AF145: 23 | AG145: 24 | AH145: 25 | AI145: 26 | AJ145: 27 | AK145: 28 | AL145: 29 | AM145: 30 | AN145: 31 | AO145: 32 | AP145: 33 | AQ145: 34 | AR145: 35 | AS145: 36 | AT145: 37 | AU145: 38 | AV145: 39 | AW145: 40 | AX145: 41 | AY145: 42 | AZ145: 43 | BA145: 44 | BB145: 45 | BC145: 46 | BD145: 47 | BE145: 48 | BF145: 49 | BG145: 50 | BH145: 51 | BI145: 52 | BJ145: 53 | BK145: 54 | BL145: 55 | BM145: 56 | BN145: 57 | BO145: 58 | BP145: 59 | BQ145: 60 | BR145: 61 | BS145: 62 | BT145: 63 | BU145: 64 | BV145: 65 | BW145: 66 | BX145: 67 | BY145: 68 | BZ145: 69 | CA145: 70 | CB145: 71 | CC145: 72
F146: Año 0 Eval. Ex Ante | J146: =HLOOKUP(J145,Calendarios!$C$4:$YM$5,2,FALSE) -> #N/A | K146: =HLOOKUP(K145,Calendarios!$C$4:$YM$5,2,FALSE) -> #N/A | L146: =HLOOKUP(L145,Calendarios!$C$4:$YM$5,2,FALSE) -> #N/A | M146: =HLOOKUP(M145,Calendarios!$C$4:$YM$5,2,FALSE) -> #N/A | N146: =HLOOKUP(N145,Calendarios!$C$4:$YM$5,2,FALSE) -> #N/A | O146: =HLOOKUP(O145,Calendarios!$C$4:$YM$5,2,FALSE) -> #N/A | P146: =HLOOKUP(P145,Calendarios!$C$4:$YM$5,2,FALSE) -> #N/A | Q146: =HLOOKUP(Q145,Calendarios!$C$4:$YM$5,2,FALSE) -> #N/A | ... CC146: =HLOOKUP(CC145,Calendarios!$C$4:$YM$5,2,FALSE) -> #N/A
B148: Índice de Precios del Proyecto | F148: =HLOOKUP(H138,'IPIM y USD'!$C$6:$IP$9,3,FALSE) -> 2501.7639 | J148: =+$F$148 -> 2501.7639 | K148: =+$F$148 -> 2501.7639 | L148: =+$F$148 -> 2501.7639 | M148: =+$F$148 -> 2501.7639 | N148: =+$F$148 -> 2501.7639 | O148: =+$F$148 -> 2501.7639 | P148: =+$F$148 -> 2501.7639 | Q148: =+$F$148 -> 2501.7639 | ... CC148: =+$F$148 -> 2501.7639
B150: Tipo de cambio | F150: =HLOOKUP(H138,'IPIM y USD'!$C$15:$IS$17,3,FALSE) -> 37.407727 | J150: =+$F$150 -> 37.407727 | K150: =+$F$150 -> 37.407727 | L150: =+$F$150 -> 37.407727 | M150: =+$F$150 -> 37.407727 | N150: =+$F$150 -> 37.407727 | O150: =+$F$150 -> 37.407727 | P150: =+$F$150 -> 37.407727 | Q150: =+$F$150 -> 37.407727 | ... CC150: =+$F$150 -> 37.407727
B152: 2.10.02. Cronograma de ejecución de la OBRA FÍSICA - PREVISTO EX ANTE | K152: El porcentaje de ejecución mensual de cada tarea se calcula: | Q152: Sobre cada tarea
B154: Tarea | D154: % s/Total de la Obra | F154: MM/AA Inicio | H154: MM/AA Final | J154: =+J146 -> #N/A | K154: =+K146 -> #N/A | L154: =+L146 -> #N/A | M154: =+M146 -> #N/A | N154: =+N146 -> #N/A | O154: =+O146 -> #N/A | P154: =+P146 -> #N/A | Q154: =+Q146 -> #N/A | ... CC154: =+CC146 -> #N/A
B156: Tarea 1 | D156: =SUM(J156:AG156) -> 0.7 | F156: 43556 | H156: 44196 | J156: 0.5 | K156: 0.2 | L156: 0 | M156: 0 | N156: 0 | O156: 0 | P156: 0 | Q156: 0 | R156: 0 | S156: 0 | T156: 0 | U156: 0 | V156: 0 | W156: 0 | X156: 0 | Y156: 0 | Z156: 0 | AA156: 0 | AB156: 0 | AC156: 0 | AD156: 0 | AE156: 0 | AF156: 0 | AG156: 0
B157: Tarea 2 | D157: =SUM(J157:AG157) -> 0.2 | F157: 43556 | H157: 44136 | J157: 0 | K157: 0.2 | L157: 0 | M157: 0 | N157: 0 | O157: 0 | P157: 0 | Q157: 0 | R157: 0 | S157: 0 | T157: 0 | U157: 0 | V157: 0 | W157: 0 | X157: 0 | Y157: 0 | Z157: 0 | AA157: 0 | AB157: 0 | AC157: 0 | AD157: 0 | AE157: 0 | AF157: 0 | AG157: 0
B158: Tarea 3 | D158: =SUM(J158:AG158) -> 0.2 | F158: 43556 | H158: jun.-20 | J158: 0 | K158: 0 | L158: 0.2 | M158: 0 | N158: 0 | O158: 0 | P158: 0 | Q158: 0 | R158: 0 | S158: 0 | T158: 0 | U158: 0 | V158: 0 | W158: 0 | X158: 0 | Y158: 0 | Z158: 0 | AA158: 0 | AB158: 0 | AC158: 0 | AD158: 0 | AE158: 0 | AF158: 0 | AG158: 0
B159: Tarea 4 | D159: =SUM(J159:AG159) -> 0.1 | F159: 43525 | H159: 44196 | J159: 0 | K159: 0 | L159: 0 | M159: 0.1 | N159: 0 | O159: 0 | P159: 0 | Q159: 0 | R159: 0 | S159: 0 | T159: 0 | U159: 0 | V159: 0 | W159: 0 | X159: 0 | Y159: 0 | Z159: 0 | AA159: 0 | AB159: 0 | AC159: 0 | AD159: 0 | AE159: 0 | AF159: 0 | AG159: 0
B161: Total (%) | D161: =SUM(D156:D160) -> 1.2 | F161: Comprobación | H161: =SUM(J161:CC161) -> 0.58 | J161: =IF($Q$152="Sobre la obra",SUM(J156:J160),IF($Q$152="Sobre cada tarea",SUMPRODUCT($D$156:$D$159,J156:J159),"")) -> 0.35 | K161: =IF($Q$152="Sobre la obra",SUM(K156:K160),IF($Q$152="Sobre cada tarea",SUMPRODUCT($D$156:$D$159,K156:K159),"")) -> 0.18 | L161: =IF($Q$152="Sobre la obra",SUM(L156:L160),IF($Q$152="Sobre cada tarea",SUMPRODUCT($D$156:$D$159,L156:L159),"")) -> 0.04 | M161: =IF($Q$152="Sobre la obra",SUM(M156:M160),IF($Q$152="Sobre cada tarea",SUMPRODUCT($D$156:$D$159,M156:M159),"")) -> 0.01 | N161: =IF($Q$152="Sobre la obra",SUM(N156:N160),IF($Q$152="Sobre cada tarea",SUMPRODUCT($D$156:$D$159,N156:N159),"")) -> 0 | O161: =IF($Q$152="Sobre la obra",SUM(O156:O160),IF($Q$152="Sobre cada tarea",SUMPRODUCT($D$156:$D$159,O156:O159),"")) -> 0 | P161: =IF($Q$152="Sobre la obra",SUM(P156:P160),IF($Q$152="Sobre cada tarea",SUMPRODUCT($D$156:$D$159,P156:P159),"")) -> 0 | Q161: =IF($Q$152="Sobre la obra",SUM(Q156:Q160),IF($Q$152="Sobre cada tarea",SUMPRODUCT($D$156:$D$159,Q156:Q159),"")) -> 0 | ... AG161: =IF($Q$152="Sobre la obra",SUM(AG156:AG160),IF($Q$152="Sobre cada tarea",SUMPRODUCT($D$156:$D$159,AG156:AG159),"")) -> 0
B163: % Acumulado | J163: =+J161 -> 0.35 | K163: =+J163+K161 -> 0.53 | L163: =+K163+L161 -> 0.57 | M163: =+L163+M161 -> 0.58 | N163: =+M163+N161 -> 0.58 | O163: =+N163+O161 -> 0.58 | P163: =+O163+P161 -> 0.58 | Q163: =+P163+Q161 -> 0.58 | R163: =+Q163+R161 -> 0.58 | ... AG163: =+AF163+AG161 -> 0.58
B165: 2.10.03A. Cronograma de la ejecución FINANCIERA EN PESOS - PREVISTO EX ANTE (Millones de pesos)
B167: Tarea | D167: %Costo Tarea s/Costo Total | F167: Costo por Tarea | H167: Costo por Tarea (Suma del Gantt) | J167: =+J154 -> #N/A | K167: =+K154 -> #N/A | L167: =+L154 -> #N/A | M167: =+M154 -> #N/A | N167: =+N154 -> #N/A | O167: =+O154 -> #N/A | P167: =+P154 -> #N/A | Q167: =+Q154 -> #N/A | ... CC167: =+CC154 -> #N/A
B169: =+$B$156 -> Tarea 1 | D169: =IF($H$136=0,0,F169/$H$136) -> 0 | F169: 0 | H169: =SUM(J169:CC169) -> 0 | J169: 0 | K169: 0 | L169: 0 | M169: 0 | N169: 0 | O169: 0 | P169: 0 | Q169: 0 | R169: 0 | S169: 0 | T169: 0 | U169: 0 | V169: 0 | W169: 0 | X169: 0 | Y169: 0 | Z169: 0 | AA169: 0 | AB169: 0 | AC169: 0 | AD169: 0 | AE169: 0 | AF169: 0 | AG169: 0 | AH169: 0 | AI169: 0 | AJ169: 0 | AK169: 0 | AL169: 0 | AM169: 0 | AN169: 0 | AO169: 0 | AP169: 0 | AQ169: 0 | AR169: 0 | AS169: 0 | AT169: 0 | AU169: 0 | AV169: 0 | AW169: 0 | AX169: 0 | AY169: 0 | AZ169: 0 | BA169: 0 | BB169: 0 | BC169: 0 | BD169: 0 | BE169: 0 | BF169: 0 | BG169: 0 | BH169: 0 | BI169: 0 | BJ169: 0 | BK169: 0 | BL169: 0 | BM169: 0 | BN169: 0 | BO169: 0 | BP169: 0 | BQ169: 0 | BR169: 0 | BS169: 0 | BT169: 0 | BU169: 0 | BV169: 0 | BW169: 0 | BX169: 0 | BY169: 0 | BZ169: 0 | CA169: 0 | CB169: 0 | CC169: 0
B170: =+$B$157 -> Tarea 2 | D170: =IF($H$136=0,0,F170/$H$136) -> 0 | F170: 0 | H170: =SUM(J170:CC170) -> 0 | J170: 0 | K170: 0 | L170: 0 | M170: 0 | N170: 0 | O170: 0 | P170: 0 | Q170: 0 | R170: 0 | S170: 0 | T170: 0 | U170: 0 | V170: 0 | W170: 0 | X170: 0 | Y170: 0 | Z170: 0 | AA170: 0 | AB170: 0 | AC170: 0 | AD170: 0 | AE170: 0 | AF170: 0 | AG170: 0 | AH170: 0 | AI170: 0 | AJ170: 0 | AK170: 0 | AL170: 0 | AM170: 0 | AN170: 0 | AO170: 0 | AP170: 0 | AQ170: 0 | AR170: 0 | AS170: 0 | AT170: 0 | AU170: 0 | AV170: 0 | AW170: 0 | AX170: 0 | AY170: 0 | AZ170: 0 | BA170: 0 | BB170: 0 | BC170: 0 | BD170: 0 | BE170: 0 | BF170: 0 | BG170: 0 | BH170: 0 | BI170: 0 | BJ170: 0 | BK170: 0 | BL170: 0 | BM170: 0 | BN170: 0 | BO170: 0 | BP170: 0 | BQ170: 0 | BR170: 0 | BS170: 0 | BT170: 0 | BU170: 0 | BV170: 0 | BW170: 0 | BX170: 0 | BY170: 0 | BZ170: 0 | CA170: 0 | CB170: 0 | CC170: 0
B171: =+$B$158 -> Tarea 3 | D171: =IF($H$136=0,0,F171/$H$136) -> 0 | F171: 0 | H171: =SUM(J171:CC171) -> 0 | J171: 0 | K171: 0 | L171: 0 | M171: 0 | N171: 0 | O171: 0 | P171: 0 | Q171: 0 | R171: 0 | S171: 0 | T171: 0 | U171: 0 | V171: 0 | W171: 0 | X171: 0 | Y171: 0 | Z171: 0 | AA171: 0 | AB171: 0 | AC171: 0 | AD171: 0 | AE171: 0 | AF171: 0 | AG171: 0 | AH171: 0 | AI171: 0 | AJ171: 0 | AK171: 0 | AL171: 0 | AM171: 0 | AN171: 0 | AO171: 0 | AP171: 0 | AQ171: 0 | AR171: 0 | AS171: 0 | AT171: 0 | AU171: 0 | AV171: 0 | AW171: 0 | AX171: 0 | AY171: 0 | AZ171: 0 | BA171: 0 | BB171: 0 | BC171: 0 | BD171: 0 | BE171: 0 | BF171: 0 | BG171: 0 | BH171: 0 | BI171: 0 | BJ171: 0 | BK171: 0 | BL171: 0 | BM171: 0 | BN171: 0 | BO171: 0 | BP171: 0 | BQ171: 0 | BR171: 0 | BS171: 0 | BT171: 0 | BU171: 0 | BV171: 0 | BW171: 0 | BX171: 0 | BY171: 0 | BZ171: 0 | CA171: 0 | CB171: 0 | CC171: 0
B172: =+$B$159 -> Tarea 4 | D172: =IF($H$136=0,0,F172/$H$136) -> 0 | F172: 0 | H172: =SUM(J172:CC172) -> 0 | J172: 0 | K172: 0 | L172: 0 | M172: 0 | N172: 0 | O172: 0 | P172: 0 | Q172: 0 | R172: 0 | S172: 0 | T172: 0 | U172: 0 | V172: 0 | W172: 0 | X172: 0 | Y172: 0 | Z172: 0 | AA172: 0 | AB172: 0 | AC172: 0 | AD172: 0 | AE172: 0 | AF172: 0 | AG172: 0 | AH172: 0 | AI172: 0 | AJ172: 0 | AK172: 0 | AL172: 0 | AM172: 0 | AN172: 0 | AO172: 0 | AP172: 0 | AQ172: 0 | AR172: 0 | AS172: 0 | AT172: 0 | AU172: 0 | AV172: 0 | AW172: 0 | AX172: 0 | AY172: 0 | AZ172: 0 | BA172: 0 | BB172: 0 | BC172: 0 | BD172: 0 | BE172: 0 | BF172: 0 | BG172: 0 | BH172: 0 | BI172: 0 | BJ172: 0 | BK172: 0 | BL172: 0 | BM172: 0 | BN172: 0 | BO172: 0 | BP172: 0 | BQ172: 0 | BR172: 0 | BS172: 0 | BT172: 0 | BU172: 0 | BV172: 0 | BW172: 0 | BX172: 0 | BY172: 0 | BZ172: 0 | CA172: 0 | CB172: 0 | CC172: 0
B174: Total ($ millones) | F174: =SUM(F169:F173) -> 0 | H174: =+H169+H170+H171+H172 -> 0 | J174: =SUM(J169:J173) -> 0 | K174: =SUM(K169:K173) -> 0 | L174: =SUM(L169:L173) -> 0 | M174: =SUM(M169:M173) -> 0 | N174: =SUM(N169:N173) -> 0 | O174: =SUM(O169:O173) -> 0 | P174: =SUM(P169:P173) -> 0 | Q174: =SUM(Q169:Q173) -> 0 | ... CC174: =SUM(CC169:CC173) -> 0
B176: Acumulado ($ millones) | J176: =+J174 -> 0 | K176: =+K174 -> 0 | L176: =+L174 -> 0 | M176: =+M174 -> 0 | N176: =+N174 -> 0 | O176: =+O174 -> 0 | P176: =+P174 -> 0 | Q176: =+Q174 -> 0 | ... CC176: =+CC174 -> 0
B178: Total (%) | J178: =IF($H$136=0,0,+J174/$C$136) -> 0 | K178: =IF($H$136=0,0,+K174/$C$136) -> 0 | L178: =IF($H$136=0,0,+L174/$C$136) -> 0 | M178: =IF($H$136=0,0,+M174/$C$136) -> 0 | N178: =IF($H$136=0,0,+N174/$C$136) -> 0 | O178: =IF($H$136=0,0,+O174/$C$136) -> 0 | P178: =IF($H$136=0,0,+P174/$C$136) -> 0 | Q178: =IF($H$136=0,0,+Q174/$C$136) -> 0 | ... CC178: =IF($H$136=0,0,+CC174/$C$136) -> 0
B180: % Acumulado | J180: =+J178 -> 0 | K180: =+K178 -> 0 | L180: =+L178 -> 0 | M180: =+M178 -> 0 | N180: =+N178 -> 0 | O180: =+O178 -> 0 | P180: =+P178 -> 0 | Q180: =+Q178 -> 0 | ... CC180: =+CC178 -> 0
B182: Deflactada por inflación real ex post | H182: =SUM(J182:AG182) -> 0 | J182: =IF(J148/F148<=1,+J174,+J174*$F$262/J262) -> 0 | K182: =IF(K148/J148<=1,+K174,+K174*$F$262/K262) -> 0 | L182: =IF(L148/K148<=1,+L174,+L174*$F$262/L262) -> 0 | M182: =IF(M148/L148<=1,+M174,+M174*$F$262/M262) -> 0 | N182: =IF(N148/M148<=1,+N174,+N174*$F$262/N262) -> 0 | O182: =IF(O148/N148<=1,+O174,+O174*$F$262/O262) -> 0 | P182: =IF(P148/O148<=1,+P174,+P174*$F$262/P262) -> 0 | Q182: =IF(Q148/P148<=1,+Q174,+Q174*$F$262/Q262) -> 0 | R182: =IF(R148/Q148<=1,+R174,+R174*$F$262/R262) -> 0 | ... CC182: =IF(CC148/CB148<=1,+CC174,+CC174*$F$262/CC262) -> 0
B184: 2.10.03B. Cronograma de la ejecución FINANCIERA EN DÓLARES y PESIFICADO - PREVISTO EX ANTE (Millones de dólares)
B186: Tarea | D186: % Valor s/Costo Total | F186: Costo por Tarea | J186: =+J167 -> #N/A | K186: =+K167 -> #N/A | L186: =+L167 -> #N/A | M186: =+M167 -> #N/A | N186: =+N167 -> #N/A | O186: =+O167 -> #N/A | P186: =+P167 -> #N/A | Q186: =+Q167 -> #N/A | ... CC186: =+CC167 -> #N/A
B188: =+$B$156 -> Tarea 1 | D188: =IF(F188>0,+F188*F$150/1000/H$136,0) -> 0 | F188: =SUM(J188:AG188) -> 0 | J188: 0 | K188: 0 | L188: 0 | M188: 0 | N188: 0 | O188: 0 | P188: 0 | Q188: 0 | R188: 0 | S188: 0 | T188: 0 | U188: 0 | V188: 0 | W188: 0 | X188: 0 | Y188: 0 | Z188: 0 | AA188: 0 | AB188: 0 | AC188: 0 | AD188: 0 | AE188: 0 | AF188: 0 | AG188: 0 | AH188: 0 | AI188: 0 | AJ188: 0 | AK188: 0 | AL188: 0 | AM188: 0 | AN188: 0 | AO188: 0 | AP188: 0 | AQ188: 0 | AR188: 0 | AS188: 0 | AT188: 0 | AU188: 0 | AV188: 0 | AW188: 0 | AX188: 0 | AY188: 0 | AZ188: 0 | BA188: 0 | BB188: 0 | BC188: 0 | BD188: 0 | BE188: 0 | BF188: 0 | BG188: 0 | BH188: 0 | BI188: 0 | BJ188: 0 | BK188: 0 | BL188: 0 | BM188: 0 | BN188: 0 | BO188: 0 | BP188: 0 | BQ188: 0 | BR188: 0 | BS188: 0 | BT188: 0 | BU188: 0 | BV188: 0 | BW188: 0 | BX188: 0 | BY188: 0 | BZ188: 0 | CA188: 0 | CB188: 0 | CC188: 0
B189: =+$B$157 -> Tarea 2 | D189: =IF(F189>0,+F189*F$150/1000/H$136,0) -> 0 | F189: =SUM(J189:AG189) -> 0 | J189: 0 | K189: 0 | L189: 0 | M189: 0 | N189: 0 | O189: 0 | P189: 0 | Q189: 0 | R189: 0 | S189: 0 | T189: 0 | U189: 0 | V189: 0 | W189: 0 | X189: 0 | Y189: 0 | Z189: 0 | AA189: 0 | AB189: 0 | AC189: 0 | AD189: 0 | AE189: 0 | AF189: 0 | AG189: 0 | AH189: 0 | AI189: 0 | AJ189: 0 | AK189: 0 | AL189: 0 | AM189: 0 | AN189: 0 | AO189: 0 | AP189: 0 | AQ189: 0 | AR189: 0 | AS189: 0 | AT189: 0 | AU189: 0 | AV189: 0 | AW189: 0 | AX189: 0 | AY189: 0 | AZ189: 0 | BA189: 0 | BB189: 0 | BC189: 0 | BD189: 0 | BE189: 0 | BF189: 0 | BG189: 0 | BH189: 0 | BI189: 0 | BJ189: 0 | BK189: 0 | BL189: 0 | BM189: 0 | BN189: 0 | BO189: 0 | BP189: 0 | BQ189: 0 | BR189: 0 | BS189: 0 | BT189: 0 | BU189: 0 | BV189: 0 | BW189: 0 | BX189: 0 | BY189: 0 | BZ189: 0 | CA189: 0 | CB189: 0 | CC189: 0
B190: =+$B$158 -> Tarea 3 | D190: =IF(F190>0,+F190*F$150/1000/H$136,0) -> 0 | F190: =SUM(J190:AG190) -> 0 | J190: 0 | K190: 0 | L190: 0 | M190: 0 | N190: 0 | O190: 0 | P190: 0 | Q190: 0 | R190: 0 | S190: 0 | T190: 0 | U190: 0 | V190: 0 | W190: 0 | X190: 0 | Y190: 0 | Z190: 0 | AA190: 0 | AB190: 0 | AC190: 0 | AD190: 0 | AE190: 0 | AF190: 0 | AG190: 0 | AH190: 0 | AI190: 0 | AJ190: 0 | AK190: 0 | AL190: 0 | AM190: 0 | AN190: 0 | AO190: 0 | AP190: 0 | AQ190: 0 | AR190: 0 | AS190: 0 | AT190: 0 | AU190: 0 | AV190: 0 | AW190: 0 | AX190: 0 | AY190: 0 | AZ190: 0 | BA190: 0 | BB190: 0 | BC190: 0 | BD190: 0 | BE190: 0 | BF190: 0 | BG190: 0 | BH190: 0 | BI190: 0 | BJ190: 0 | BK190: 0 | BL190: 0 | BM190: 0 | BN190: 0 | BO190: 0 | BP190: 0 | BQ190: 0 | BR190: 0 | BS190: 0 | BT190: 0 | BU190: 0 | BV190: 0 | BW190: 0 | BX190: 0 | BY190: 0 | BZ190: 0 | CA190: 0 | CB190: 0 | CC190: 0
...

Sheet Calendarios
A1: CALENDARIOs
A3: EX ANTE
C4: =IF($B$5=C5,1,0) -> 0 | D4: =IF($B$5=D5,1,IF(C4>=1,C4+1,0)) -> 0 | E4: =IF($B$5=E5,1,IF(D4>=1,D4+1,0)) -> 0 | F4: =IF($B$5=F5,1,IF(E4>=1,E4+1,0)) -> 0 | G4: =IF($B$5=G5,1,IF(F4>=1,F4+1,0)) -> 0 | H4: =IF($B$5=H5,1,IF(G4>=1,G4+1,0)) -> 0 | I4: =IF($B$5=I5,1,IF(H4>=1,H4+1,0)) -> 0 | J4: =IF($B$5=J5,1,IF(I4>=1,I4+1,0)) -> 0 | K4: =IF($B$5=K5,1,IF(J4>=1,J4+1,0)) -> 0 | ... YM4: =IF($B$5=YM5,1,IF(YL4>=1,YL4+1,0)) -> 0
A5: Fecha inicio | B5: =+Formulario!H140 -> 0 | C5: 36861 | D5: 36892 | E5: 36923 | F5: 36951 | G5: 36982 | H5: 37012 | I5: 37043 | J5: 37073 | K5: 37104 | L5: 37135 | M5: 37165 | N5: 37196 | O5: 37226 | P5: 37257 | Q5: 37288 | R5: 37316 | S5: 37347 | T5: 37377 | U5: 37408 | V5: 37438 | W5: 37469 | X5: 37500 | Y5: 37530 | Z5: 37561 | AA5: 37591 | AB5: 37622 | AC5: 37653 | AD5: 37681 | AE5: 37712 | AF5: 37742 | AG5: 37773 | AH5: 37803 | AI5: 37834 | AJ5: 37865 | AK5: 37895 | AL5: 37926 | AM5: 37956 | AN5: 37987 | AO5: 38018 | AP5: 38047 | AQ5: 38078 | AR5: 38108 | AS5: 38139 | AT5: 38169 | AU5: 38200 | AV5: 38231 | AW5: 38261 | AX5: 38292 | AY5: 38322 | AZ5: 38353 | BA5: 38384 | BB5: 38412 | BC5: 38443 | BD5: 38473 | BE5: 38504 | BF5: 38534 | BG5: 38565 | BH5: 38596 | BI5: 38626 | BJ5: 38657 | BK5: 38687 | BL5: 38718 | BM5: 38749 | BN5: 38777 | BO5: 38808 | BP5: 38838 | BQ5: 38869 | BR5: 38899 | BS5: 38930 | BT5: 38961 | BU5: 38991 | BV5: 39022 | BW5: 39052 | BX5: 39083 | BY5: 39114 | BZ5: 39142 | CA5: 39173 | CB5: 39203 | CC5: 39234 | CD5: 39264 | CE5: 39295 | CF5: 39326 | CG5: 39356 | CH5: 39387 | CI5: 39417 | CJ5: 39448 | CK5: 39479 | CL5: 39508 | CM5: 39539 | CN5: 39569 | CO5: 39600 | CP5: 39630 | CQ5: 39661 | CR5: 39692 | CS5: 39722 | CT5: 39753 | CU5: 39783 | CV5: 39814 | CW5: 39845 | CX5: 39873 | CY5: 39904 | CZ5: 39934 | DA5: 39965 | DB5: 39995 | DC5: 40026 | DD5: 40057 | DE5: 40087 | DF5: 40118 | DG5: 40148 | DH5: 40179 | DI5: 40210 | DJ5: 40238 | DK5: 40269 | DL5: 40299 | DM5: 40330 | DN5: 40360 | DO5: 40391 | DP5: 40422 | DQ5: 40452 | DR5: 40483 | DS5: 40513 | DT5: 40544 | DU5: 40575 | DV5: 40603 | DW5: 40634 | DX5: 40664 | DY5: 40695 | DZ5: 40725 | EA5: 40756 | EB5: 40787 | EC5: 40817 | ED5: 40848 | EE5: 40878 | EF5: 40909 | EG5: 40940 | EH5: 40969 | EI5: 41000 | EJ5: 41030 | EK5: 41061 | EL5: 41091 | EM5: 41122 | EN5: 41153 | EO5: 41183 | EP5: 41214 | EQ5: 41244 | ER5: 41275 | ES5: 41306 | ET5: 41334 | EU5: 41365 | EV5: 41395 | EW5: 41426 | EX5: 41456 | EY5: 41487 | EZ5: 41518 | FA5: 41548 | FB5: 41579 | FC5: 41609 | FD5: 41640 | FE5: 41671 | FF5: 41699 | FG5: 41730 | FH5: 41760 | FI5: 41791 | FJ5: 41821 | FK5: 41852 | FL5: 41883 | FM5: 41913 | FN5: 41944 | FO5: 41974 | FP5: 42005 | FQ5: 42036 | FR5: 42064 | FS5: 42095 | FT5: 42125 | FU5: 42156 | FV5: 42186 | FW5: 42217 | FX5: 42248 | FY5: 42278 | FZ5: 42309 | GA5: 42339 | GB5: 42370 | GC5: 42401 | GD5: 42430 | GE5: 42461 | GF5: 42491 | GG5: 42522 | GH5: 42552 | GI5: 42583 | GJ5: 42614 | GK5: 42644 | GL5: 42675 | GM5: 42705 | GN5: 42736 | GO5: 42767 | GP5: 42795 | GQ5: 42826 | GR5: 42856 | GS5: 42887 | GT5: 42917 | GU5: 42948 | GV5: 42979 | GW5: 43009 | GX5: 43040 | GY5: 43070 | GZ5: 43101 | HA5: 43132 | HB5: 43160 | HC5: 43191 | HD5: 43221 | HE5: 43252 | HF5: 43282 | HG5: 43313 | HH5: 43344 | HI5: 43374 | HJ5: 43405 | HK5: 43435 | HL5: 43466 | HM5: 43497 | HN5: 43525 | HO5: 43556 | HP5: 43586 | HQ5: 43617 | HR5: 43647 | HS5: 43678 | HT5: 43709 | HU5: 43739 | HV5: 43770 | HW5: 43800 | HX5: 43831 | HY5: 43862 | HZ5: 43891 | IA5: 43922 | IB5: 43952 | IC5: 43983 | ID5: 44013 | IE5: 44044 | IF5: 44075 | IG5: 44105 | IH5: 44136 | II5: 44166 | IJ5: 44197 | IK5: 44228 | IL5: 44256 | IM5: 44287 | IN5: 44317 | IO5: 44348 | IP5: 44378 | IQ5: 44409 | IR5: 44440 | IS5: 44470 | IT5: 44501 | IU5: 44531 | IV5: 44562 | IW5: 44593 | IX5: 44621 | IY5: 44652 | IZ5: 44682 | JA5: 44713 | JB5: 44743 | JC5: 44774 | JD5: 44805 | JE5: 44835 | JF5: 44866 | JG5: 44896 | JH5: 44927 | JI5: 44958 | JJ5: 44986 | JK5: 45017 | JL5: 45047 | JM5: 45078 | JN5: 45108 | JO5: 45139 | JP5: 45170 | JQ5: 45200 | JR5: 45231 | JS5: 45261 | JT5: 45292 | JU5: 45323 | JV5: 45352 | JW5: 45383 | JX5: 45413 | JY5: 45444 | JZ5: 45474 | KA5: 45505 | KB5: 45536 | KC5: 45566 | KD5: 45597 | KE5: 45627 | KF5: 45658 | KG5: 45689 | KH5: 45717 | KI5: 45748 | KJ5: 45778 | KK5: 45809 | KL5: 45839 | KM5: 45870 | KN5: 45901 | KO5: 45931 | KP5: 45962 | KQ5: 45992 | KR5: 46023 | KS5: 46054 | KT5: 46082 | KU5: 46113 | KV5: 46143 | KW5: 46174 | KX5: 46204 | KY5: 46235 | KZ5: 46266 | LA5: 46296 | LB5: 46327 | LC5: 46357 | LD5: 46388 | LE5: 46419 | LF5: 46447 | LG5: 46478 | LH5: 46508 | LI5: 46539 | LJ5: 46569 | LK5: 46600 | LL5: 46631 | LM5: 46661 | LN5: 46692 | LO5: 46722 | LP5: 46753 | LQ5: 46784 | LR5: 46813 | LS5: 46844 | LT5: 46874 | LU5: 46905 | LV5: 46935 | LW5: 46966 | LX5: 46997 | LY5: 47027 | LZ5: 47058 | MA5: 47088 | MB5: 47119 | MC5: 47150 | MD5: 47178 | ME5: 47209 | MF5: 47239 | MG5: 47270 | MH5: 47300 | MI5: 47331 | MJ5: 47362 | MK5: 47392 | ML5: 47423 | MM5: 47453 | MN5: 47484 | MO5: 47515 | MP5: 47543 | MQ5: 47574 | MR5: 47604 | MS5: 47635 | MT5: 47665 | MU5: 47696 | MV5: 47727 | MW5: 47757 | MX5: 47788 | MY5: 47818 | MZ5: 47849 | NA5: 47880 | NB5: 47908 | NC5: 47939 | ND5: 47969 | NE5: 48000 | NF5: 48030 | NG5: 48061 | NH5: 48092 | NI5: 48122 | NJ5: 48153 | NK5: 48183 | NL5: 48214 | NM5: 48245 | NN5: 48274 | NO5: 48305 | NP5: 48335 | NQ5: 48366 | NR5: 48396 | NS5: 48427 | NT5: 48458 | NU5: 48488 | NV5: 48519 | NW5: 48549 | NX5: 48580 | NY5: 48611 | NZ5: 48639 | OA5: 48670 | OB5: 48700 | OC5: 48731 | OD5: 48761 | OE5: 48792 | OF5: 48823 | OG5: 48853 | OH5: 48884 | OI5: 48914 | OJ5: 48945 | OK5: 48976 | OL5: 49004 | OM5: 49035 | ON5: 49065 | OO5: 49096 | OP5: 49126 | OQ5: 49157 | OR5: 49188 | OS5: 49218 | OT5: 49249 | OU5: 49279 | OV5: 49310 | OW5: 49341 | OX5: 49369 | OY5: 49400 | OZ5: 49430 | PA5: 49461 | PB5: 49491 | PC5: 49522 | PD5: 49553 | PE5: 49583 | PF5: 49614 | PG5: 49644 | PH5: 49675 | PI5: 49706 | PJ5: 49735 | PK5: 49766 | PL5: 49796 | PM5: 49827 | PN5: 49857 | PO5: 49888 | PP5: 49919 | PQ5: 49949 | PR5: 49980 | PS5: 50010 | PT5: 50041 | PU5: 50072 | PV5: 50100 | PW5: 50131 | PX5: 50161 | PY5: 50192 | PZ5: 50222 | QA5: 50253 | QB5: 50284 | QC5: 50314 | QD5: 50345 | QE5: 50375 | QF5: 50406 | QG5: 50437 | QH5: 50465 | QI5: 50496 | QJ5: 50526 | QK5: 50557 | QL5: 50587 | QM5: 50618 | QN5: 50649 | QO5: 50679 | QP5: 50710 | QQ5: 50740 | QR5: 50771 | QS5: 50802 | QT5: 50830 | QU5: 50861 | QV5: 50891 | QW5: 50922 | QX5: 50952 | QY5: 50983 | QZ5: 51014 | RA5: 51044 | RB5: 51075 | RC5: 51105 | RD5: 51136 | RE5: 51167 | RF5: 51196 | RG5: 51227 | RH5: 51257 | RI5: 51288 | RJ5: 51318 | RK5: 51349 | RL5: 51380 | RM5: 51410 | RN5: 51441 | RO5: 51471 | RP5: 51502 | RQ5: 51533 | RR5: 51561 | RS5: 51592 | RT5: 51622 | RU5: 51653 | RV5: 51683 | RW5: 51714 | RX5: 51745 | RY5: 51775 | RZ5: 51806 | SA5: 51836 | SB5: 51867 | SC5: 51898 | SD5: 51926 | SE5: 51957 | SF5: 51987 | SG5: 52018 | SH5: 52048 | SI5: 52079 | SJ5: 52110 | SK5: 52140 | SL5: 52171 | SM5: 52201 | SN5: 52232 | SO5: 52263 | SP5: 52291 | SQ5: 52322 | SR5: 52352 | SS5: 52383 | ST5: 52413 | SU5: 52444 | SV5: 52475 | SW5: 52505 | SX5: 52536 | SY5: 52566 | SZ5: 52597 | TA5: 52628 | TB5: 52657 | TC5: 52688 | TD5: 52718 | TE5: 52749 | TF5: 52779 | TG5: 52810 | TH5: 52841 | TI5: 52871 | TJ5: 52902 | TK5: 52932 | TL5: 52963 | TM5: 52994 | TN5: 53022 | TO5: 53053 | TP5: 53083 | TQ5: 53114 | TR5: 53144 | TS5: 53175 | TT5: 53206 | TU5: 53236 | TV5: 53267 | TW5: 53297 | TX5: 53328 | TY5: 53359 | TZ5: 53387 | UA5: 53418 | UB5: 53448 | UC5: 53479 | UD5: 53509 | UE5: 53540 | UF5: 53571 | UG5: 53601 | UH5: 53632 | UI5: 53662 | UJ5: 53693 | UK5: 53724 | UL5: 53752 | UM5: 53783 | UN5: 53813 | UO5: 53844 | UP5: 53874 | UQ5: 53905 | UR5: 53936 | US5: 53966 | UT5: 53997 | UU5: 54027 | UV5: 54058 | UW5: 54089 | UX5: 54118 | UY5: 54149 | UZ5: 54179 | VA5: 54210 | VB5: 54240 | VC5: 54271 | VD5: 54302 | VE5: 54332 | VF5: 54363 | VG5: 54393 | VH5: 54424 | VI5: 54455 | VJ5: 54483 | VK5: 54514 | VL5: 54544 | VM5: 54575 | VN5: 54605 | VO5: 54636 | VP5: 54667 | VQ5: 54697 | VR5: 54728 | VS5: 54758 | VT5: 54789 | VU5: 54820 | VV5: 54848 | VW5: 54879 | VX5: 54909 | VY5: 54940 | VZ5: 54970 | WA5: 55001 | WB5: 55032 | WC5: 55062 | WD5: 55093 | WE5: 55123 | WF5: 55154 | WG5: 55185 | WH5: 55213 | WI5: 55244 | WJ5: 55274 | WK5: 55305 | WL5: 55335 | WM5: 55366 | WN5: 55397 | WO5: 55427 | WP5: 55458 | WQ5: 55488 | WR5: 55519 | WS5: 55550 | WT5: 55579 | WU5: 55610 | WV5: 55640 | WW5: 55671 | WX5: 55701 | WY5: 55732 | WZ5: 55763 | XA5: 55793 | XB5: 55824 | XC5: 55854 | XD5: 55885 | XE5: 55916 | XF5: 55944 | XG5: 55975 | XH5: 56005 | XI5: 56036 | XJ5: 56066 | XK5: 56097 | XL5: 56128 | XM5: 56158 | XN5: 56189 | XO5: 56219 | XP5: 56250 | XQ5: 56281 | XR5: 56309 | XS5: 56340 | XT5: 56370 | XU5: 56401 | XV5: 56431 | XW5: 56462 | XX5: 56493 | XY5: 56523 | XZ5: 56554 | YA5: 56584 | YB5: 56615 | YC5: 56646 | YD5: 56674 | YE5: 56705 | YF5: 56735 | YG5: 56766 | YH5: 56796 | YI5: 56827 | YJ5: 56858 | YK5: 56888 | YL5: 56919 | YM5: 56949
C6: =IF(C7<$B$13,0,B6+1) -> 1 | D6: =IF(D7<$B$13,0,C6+1) -> 2 | E6: =IF(E7<$B$13,0,D6+1) -> 3 | F6: =IF(F7<$B$13,0,E6+1) -> 4 | G6: =IF(G7<$B$13,0,F6+1) -> 5 | H6: =IF(H7<$B$13,0,G6+1) -> 6 | I6: =IF(I7<$B$13,0,H6+1) -> 7 | J6: =IF(J7<$B$13,0,I6+1) -> 8 | ... YM6: =IF(YM7<$B$13,0,YL6+1) -> 661
A7: Fecha de cierre | B7: =+Formulario!H142 -> 0 | C7: 36891 | D7: 36922 | E7: 36950 | F7: 36981 | G7: 37011 | H7: 37042 | I7: 37072 | J7: 37103 | K7: 37134 | L7: 37164 | M7: 37195 | N7: 37225 | O7: 37256 | P7: 37287 | Q7: 37315 | R7: 37346 | S7: 37376 | T7: 37407 | U7: 37437 | V7: 37468 | W7: 37499 | X7: 37529 | Y7: 37560 | Z7: 37590 | AA7: 37621 | AB7: 37652 | AC7: 37680 | AD7: 37711 | AE7: 37741 | AF7: 37772 | AG7: 37802 | AH7: 37833 | AI7: 37864 | AJ7: 37894 | AK7: 37925 | AL7: 37955 | AM7: 37986 | AN7: 38017 | AO7: 38046 | AP7: 38077 | AQ7: 38107 | AR7: 38138 | AS7: 38168 | AT7: 38199 | AU7: 38230 | AV7: 38260 | AW7: 38291 | AX7: 38321 | AY7: 38352 | AZ7: 38383 | BA7: 38411 | BB7: 38442 | BC7: 38472 | BD7: 38503 | BE7: 38533 | BF7: 38564 | BG7: 38595 | BH7: 38625 | BI7: 38656 | BJ7: 38686 | BK7: 38717 | BL7: 38748 | BM7: 38776 | BN7: 38807 | BO7: 38837 | BP7: 38868 | BQ7: 38898 | BR7: 38929 | BS7: 38960 | BT7: 38990 | BU7: 39021 | BV7: 39051 | BW7: 39082 | BX7: 39113 | BY7: 39141 | BZ7: 39172 | CA7: 39202 | CB7: 39233 | CC7: 39263 | CD7: 39294 | CE7: 39325 | CF7: 39355 | CG7: 39386 | CH7: 39416 | CI7: 39447 | CJ7: 39478 | CK7: 39507 | CL7: 39538 | CM7: 39568 | CN7: 39599 | CO7: 39629 | CP7: 39660 | CQ7: 39691 | CR7: 39721 | CS7: 39752 | CT7: 39782 | CU7: 39813 | CV7: 39844 | CW7: 39872 | CX7: 39903 | CY7: 39933 | CZ7: 39964 | DA7: 39994 | DB7: 40025 | DC7: 40056 | DD7: 40086 | DE7: 40117 | DF7: 40147 | DG7: 40178 | DH7: 40209 | DI7: 40237 | DJ7: 40268 | DK7: 40298 | DL7: 40329 | DM7: 40359 | DN7: 40390 | DO7: 40421 | DP7: 40451 | DQ7: 40482 | DR7: 40512 | DS7: 40543 | DT7: 40574 | DU7: 40602 | DV7: 40633 | DW7: 40663 | DX7: 40694 | DY7: 40724 | DZ7: 40755 | EA7: 40786 | EB7: 40816 | EC7: 40847 | ED7: 40877 | EE7: 40908 | EF7: 40939 | EG7: 40968 | EH7: 40999 | EI7: 41029 | EJ7: 41060 | EK7: 41090 | EL7: 41121 | EM7: 41152 | EN7: 41182 | EO7: 41213 | EP7: 41243 | EQ7: 41274 | ER7: 41305 | ES7: 41333 | ET7: 41364 | EU7: 41394 | EV7: 41425 | EW7: 41455 | EX7: 41486 | EY7: 41517 | EZ7: 41547 | FA7: 41578 | FB7: 41608 | FC7: 41639 | FD7: 41670 | FE7: 41698 | FF7: 41729 | FG7: 41759 | FH7: 41790 | FI7: 41820 | FJ7: 41851 | FK7: 41882 | FL7: 41912 | FM7: 41943 | FN7: 41973 | FO7: 42004 | FP7: 42035 | FQ7: 42063 | FR7: 42094 | FS7: 42124 | FT7: 42155 | FU7: 42185 | FV7: 42216 | FW7: 42247 | FX7: 42277 | FY7: 42308 | FZ7: 42338 | GA7: 42369 | GB7: 42400 | GC7: 42429 | GD7: 42460 | GE7: 42490 | GF7: 42521 | GG7: 42551 | GH7: 42582 | GI7: 42613 | GJ7: 42643 | GK7: 42674 | GL7: 42704 | GM7: 42735 | GN7: 42766 | GO7: 42794 | GP7: 42825 | GQ7: 42855 | GR7: 42886 | GS7: 42916 | GT7: 42947 | GU7: 42978 | GV7: 43008 | GW7: 43039 | GX7: 43069 | GY7: 43100 | GZ7: 43131 | HA7: 43159 | HB7: 43190 | HC7: 43220 | HD7: 43251 | HE7: 43281 | HF7: 43312 | HG7: 43343 | HH7: 43373 | HI7: 43404 | HJ7: 43434 | HK7: 43465 | HL7: 43496 | HM7: 43524 | HN7: 43555 | HO7: 43585 | HP7: 43616 | HQ7: 43646 | HR7: 43677 | HS7: 43708 | HT7: 43738 | HU7: 43769 | HV7: 43799 | HW7: 43830 | HX7: 43861 | HY7: 43890 | HZ7: 43921 | IA7: 43951 | IB7: 43982 | IC7: 44012 | ID7: 44043 | IE7: 44074 | IF7: 44104 | IG7: 44135 | IH7: 44165 | II7: 44196 | IJ7: 44227 | IK7: 44255 | IL7: 44286 | IM7: 44316 | IN7: 44347 | IO7: 44377 | IP7: 44408 | IQ7: 44439 | IR7: 44469 | IS7: 44500 | IT7: 44530 | IU7: 44561 | IV7: 44592 | IW7: 44620 | IX7: 44651 | IY7: 44681 | IZ7: 44712 | JA7: 44742 | JB7: 44773 | JC7: 44804 | JD7: 44834 | JE7: 44865 | JF7: 44895 | JG7: 44926 | JH7: 44957 | JI7: 44985 | JJ7: 45016 | JK7: 45046 | JL7: 45077 | JM7: 45107 | JN7: 45138 | JO7: 45169 | JP7: 45199 | JQ7: 45230 | JR7: 45260 | JS7: 45291 | JT7: 45322 | JU7: 45351 | JV7: 45382 | JW7: 45412 | JX7: 45443 | JY7: 45473 | JZ7: 45504 | KA7: 45535 | KB7: 45565 | KC7: 45596 | KD7: 45626 | KE7: 45657 | KF7: 45688 | KG7: 45716 | KH7: 45747 | KI7: 45777 | KJ7: 45808 | KK7: 45838 | KL7: 45869 | KM7: 45900 | KN7: 45930 | KO7: 45961 | KP7: 45991 | KQ7: 46022 | KR7: 46053 | KS7: 46081 | KT7: 46112 | KU7: 46142 | KV7: 46173 | KW7: 46203 | KX7: 46234 | KY7: 46265 | KZ7: 46295 | LA7: 46326 | LB7: 46356 | LC7: 46387 | LD7: 46418 | LE7: 46446 | LF7: 46477 | LG7: 46507 | LH7: 46538 | LI7: 46568 | LJ7: 46599 | LK7: 46630 | LL7: 46660 | LM7: 46691 | LN7: 46721 | LO7: 46752 | LP7: 46783 | LQ7: 46812 | LR7: 46843 | LS7: 46873 | LT7: 46904 | LU7: 46934 | LV7: 46965 | LW7: 46996 | LX7: 47026 | LY7: 47057 | LZ7: 47087 | MA7: 47118 | MB7: 47149 | MC7: 47177 | MD7: 47208 | ME7: 47238 | MF7: 47269 | MG7: 47299 | MH7: 47330 | MI7: 47361 | MJ7: 47391 | MK7: 47422 | ML7: 47452 | MM7: 47483 | MN7: 47514 | MO7: 47542 | MP7: 47573 | MQ7: 47603 | MR7: 47634 | MS7: 47664 | MT7: 47695 | MU7: 47726 | MV7: 47756 | MW7: 47787 | MX7: 47817 | MY7: 47848 | MZ7: 47879 | NA7: 47907 | NB7: 47938 | NC7: 47968 | ND7: 47999 | NE7: 48029 | NF7: 48060 | NG7: 48091 | NH7: 48121 | NI7: 48152 | NJ7: 48182 | NK7: 48213 | NL7: 48244 | NM7: 48273 | NN7: 48304 | NO7: 48334 | NP7: 48365 | NQ7: 48395 | NR7: 48426 | NS7: 48457 | NT7: 48487 | NU7: 48518 | NV7: 48548 | NW7: 48579 | NX7: 48610 | NY7: 48638 | NZ7: 48669 | OA7: 48699 | OB7: 48730 | OC7: 48760 | OD7: 48791 | OE7: 48822 | OF7: 48852 | OG7: 48883 | OH7: 48913 | OI7: 48944 | OJ7: 48975 | OK7: 49003 | OL7: 49034 | OM7: 49064 | ON7: 49095 | OO7: 49125 | OP7: 49156 | OQ7: 49187 | OR7: 49217 | OS7: 49248 | OT7: 49278 | OU7: 49309 | OV7: 49340 | OW7: 49368 | OX7: 49399 | OY7: 49429 | OZ7: 49460 | PA7: 49490 | PB7: 49521 | PC7: 49552 | PD7: 49582 | PE7: 49613 | PF7: 49643 | PG7: 49674 | PH7: 49705 | PI7: 49734 | PJ7: 49765 | PK7: 49795 | PL7: 49826 | PM7: 49856 | PN7: 49887 | PO7: 49918 | PP7: 49948 | PQ7: 49979 | PR7: 50009 | PS7: 50040 | PT7: 50071 | PU7: 50099 | PV7: 50130 | PW7: 50160 | PX7: 50191 | PY7: 50221 | PZ7: 50252 | QA7: 50283 | QB7: 50313 | QC7: 50344 | QD7: 50374 | QE7: 50405 | QF7: 50436 | QG7: 50464 | QH7: 50495 | QI7: 50525 | QJ7: 50556 | QK7: 50586 | QL7: 50617 | QM7: 50648 | QN7: 50678 | QO7: 50709 | QP7: 50739 | QQ7: 50770 | QR7: 50801 | QS7: 50829 | QT7: 50860 | QU7: 50890 | QV7: 50921 | QW7: 50951 | QX7: 50982 | QY7: 51013 | QZ7: 51043 | RA7: 51074 | RB7: 51104 | RC7: 51135 | RD7: 51166 | RE7: 51195 | RF7: 51226 | RG7: 51256 | RH7: 51287 | RI7: 51317 | RJ7: 51348 | RK7: 51379 | RL7: 51409 | RM7: 51440 | RN7: 51470 | RO7: 51501 | RP7: 51532 | RQ7: 51560 | RR7: 51591 | RS7: 51621 | RT7: 51652 | RU7: 51682 | RV7: 51713 | RW7: 51744 | RX7: 51774 | RY7: 51805 | RZ7: 51835 | SA7: 51866 | SB7: 51897 | SC7: 51925 | SD7: 51956 | SE7: 51986 | SF7: 52017 | SG7: 52047 | SH7: 52078 | SI7: 52109 | SJ7: 52139 | SK7: 52170 | SL7: 52200 | SM7: 52231 | SN7: 52262 | SO7: 52290 | SP7: 52321 | SQ7: 52351 | SR7: 52382 | SS7: 52412 | ST7: 52443 | SU7: 52474 | SV7: 52504 | SW7: 52535 | SX7: 52565 | SY7: 52596 | SZ7: 52627 | TA7: 52656 | TB7: 52687 | TC7: 52717 | TD7: 52748 | TE7: 52778 | TF7: 52809 | TG7: 52840 | TH7: 52870 | TI7: 52901 | TJ7: 52931 | TK7: 52962 | TL7: 52993 | TM7: 53021 | TN7: 53052 | TO7: 53082 | TP7: 53113 | TQ7: 53143 | TR7: 53174 | TS7: 53205 | TT7: 53235 | TU7: 53266 | TV7: 53296 | TW7: 53327 | TX7: 53358 | TY7: 53386 | TZ7: 53417 | UA7: 53447 | UB7: 53478 | UC7: 53508 | UD7: 53539 | UE7: 53570 | UF7: 53600 | UG7: 53631 | UH7: 53661 | UI7: 53692 | UJ7: 53723 | UK7: 53751 | UL7: 53782 | UM7: 53812 | UN7: 53843 | UO7: 53873 | UP7: 53904 | UQ7: 53935 | UR7: 53965 | US7: 53996 | UT7: 54026 | UU7: 54057 | UV7: 54088 | UW7: 54117 | UX7: 54148 | UY7: 54178 | UZ7: 54209 | VA7: 54239 | VB7: 54270 | VC7: 54301 | VD7: 54331 | VE7: 54362 | VF7: 54392 | VG7: 54423 | VH7: 54454 | VI7: 54482 | VJ7: 54513 | VK7: 54543 | VL7: 54574 | VM7: 54604 | VN7: 54635 | VO7: 54666 | VP7: 54696 | VQ7: 54727 | VR7: 54757 | VS7: 54788 | VT7: 54819 | VU7: 54847 | VV7: 54878 | VW7: 54908 | VX7: 54939 | VY7: 54969 | VZ7: 55000 | WA7: 55031 | WB7: 55061 | WC7: 55092 | WD7: 55122 | WE7: 55153 | WF7: 55184 | WG7: 55212 | WH7: 55243 | WI7: 55273 | WJ7: 55304 | WK7: 55334 | WL7: 55365 | WM7: 55396 | WN7: 55426 | WO7: 55457 | WP7: 55487 | WQ7: 55518 | WR7: 55549 | WS7: 55578 | WT7: 55609 | WU7: 55639 | WV7: 55670 | WW7: 55700 | WX7: 55731 | WY7: 55762 | WZ7: 55792 | XA7: 55823 | XB7: 55853 | XC7: 55884 | XD7: 55915 | XE7: 55943 | XF7: 55974 | XG7: 56004 | XH7: 56035 | XI7: 56065 | XJ7: 56096 | XK7: 56127 | XL7: 56157 | XM7: 56188 | XN7: 56218 | XO7: 56249 | XP7: 56280 | XQ7: 56308 | XR7: 56339 | XS7: 56369 | XT7: 56400 | XU7: 56430 | XV7: 56461 | XW7: 56492 | XX7: 56522 | XY7: 56553 | XZ7: 56583 | YA7: 56614 | YB7: 56645 | YC7: 56673 | YD7: 56704 | YE7: 56734 | YF7: 56765 | YG7: 56795 | YH7: 56826 | YI7: 56857 | YJ7: 56887 | YK7: 56918 | YL7: 56948 | YM7: 56979
A9: EX POST
C10: =IF($B$11=C11,1,0) -> 0 | D10: =IF($B$11=D11,1,IF(C10>=1,C10+1,0)) -> 0 | E10: =IF($B$11=E11,1,IF(D10>=1,D10+1,0)) -> 0 | F10: =IF($B$11=F11,1,IF(E10>=1,E10+1,0)) -> 0 | G10: =IF($B$11=G11,1,IF(F10>=1,F10+1,0)) -> 0 | H10: =IF($B$11=H11,1,IF(G10>=1,G10+1,0)) -> 0 | I10: =IF($B$11=I11,1,IF(H10>=1,H10+1,0)) -> 0 | J10: =IF($B$11=J11,1,IF(I10>=1,I10+1,0)) -> 0 | K10: =IF($B$11=K11,1,IF(J10>=1,J10+1,0)) -> 0 | ... YM10: =IF($B$11=YM11,1,IF(YL10>=1,YL10+1,0)) -> 0
A11: Fecha inicio | B11: =+Formulario!H308 -> 0 | C11: 36861 | D11: 36892 | E11: 36923 | F11: 36951 | G11: 36982 | H11: 37012 | I11: 37043 | J11: 37073 | K11: 37104 | L11: 37135 | M11: 37165 | N11: 37196 | O11: 37226 | P11: 37257 | Q11: 37288 | R11: 37316 | S11: 37347 | T11: 37377 | U11: 37408 | V11: 37438 | W11: 37469 | X11: 37500 | Y11: 37530 | Z11: 37561 | AA11: 37591 | AB11: 37622 | AC11: 37653 | AD11: 37681 | AE11: 37712 | AF11: 37742 | AG11: 37773 | AH11: 37803 | AI11: 37834 | AJ11: 37865 | AK11: 37895 | AL11: 37926 | AM11: 37956 | AN11: 37987 | AO11: 38018 | AP11: 38047 | AQ11: 38078 | AR11: 38108 | AS11: 38139 | AT11: 38169 | AU11: 38200 | AV11: 38231 | AW11: 38261 | AX11: 38292 | AY11: 38322 | AZ11: 38353 | BA11: 38384 | BB11: 38412 | BC11: 38443 | BD11: 38473 | BE11: 38504 | BF11: 38534 | BG11: 38565 | BH11: 38596 | BI11: 38626 | BJ11: 38657 | BK11: 38687 | BL11: 38718 | BM11: 38749 | BN11: 38777 | BO11: 38808 | BP11: 38838 | BQ11: 38869 | BR11: 38899 | BS11: 38930 | BT11: 38961 | BU11: 38991 | BV11: 39022 | BW11: 39052 | BX11: 39083 | BY11: 39114 | BZ11: 39142 | CA11: 39173 | CB11: 39203 | CC11: 39234 | CD11: 39264 | CE11: 39295 | CF11: 39326 | CG11: 39356 | CH11: 39387 | CI11: 39417 | CJ11: 39448 | CK11: 39479 | CL11: 39508 | CM11: 39539 | CN11: 39569 | CO11: 39600 | CP11: 39630 | CQ11: 39661 | CR11: 39692 | CS11: 39722 | CT11: 39753 | CU11: 39783 | CV11: 39814 | CW11: 39845 | CX11: 39873 | CY11: 39904 | CZ11: 39934 | DA11: 39965 | DB11: 39995 | DC11: 40026 | DD11: 40057 | DE11: 40087 | DF11: 40118 | DG11: 40148 | DH11: 40179 | DI11: 40210 | DJ11: 40238 | DK11: 40269 | DL11: 40299 | DM11: 40330 | DN11: 40360 | DO11: 40391 | DP11: 40422 | DQ11: 40452 | DR11: 40483 | DS11: 40513 | DT11: 40544 | DU11: 40575 | DV11: 40603 | DW11: 40634 | DX11: 40664 | DY11: 40695 | DZ11: 40725 | EA11: 40756 | EB11: 40787 | EC11: 40817 | ED11: 40848 | EE11: 40878 | EF11: 40909 | EG11: 40940 | EH11: 40969 | EI11: 41000 | EJ11: 41030 | EK11: 41061 | EL11: 41091 | EM11: 41122 | EN11: 41153 | EO11: 41183 | EP11: 41214 | EQ11: 41244 | ER11: 41275 | ES11: 41306 | ET11: 41334 | EU11: 41365 | EV11: 41395 | EW11: 41426 | EX11: 41456 | EY11: 41487 | EZ11: 41518 | FA11: 41548 | FB11: 41579 | FC11: 41609 | FD11: 41640 | FE11: 41671 | FF11: 41699 | FG11: 41730 | FH11: 41760 | FI11: 41791 | FJ11: 41821 | FK11: 41852 | FL11: 41883 | FM11: 41913 | FN11: 41944 | FO11: 41974 | FP11: 42005 | FQ11: 42036 | FR11: 42064 | FS11: 42095 | FT11: 42125 | FU11: 42156 | FV11: 42186 | FW11: 42217 | FX11: 42248 | FY11: 42278 | FZ11: 42309 | GA11: 42339 | GB11: 42370 | GC11: 42401 | GD11: 42430 | GE11: 42461 | GF11: 42491 | GG11: 42522 | GH11: 42552 | GI11: 42583 | GJ11: 42614 | GK11: 42644 | GL11: 42675 | GM11: 42705 | GN11: 42736 | GO11: 42767 | GP11: 42795 | GQ11: 42826 | GR11: 42856 | GS11: 42887 | GT11: 42917 | GU11: 42948 | GV11: 42979 | GW11: 43009 | GX11: 43040 | GY11: 43070 | GZ11: 43101 | HA11: 43132 | HB11: 43160 | HC11: 43191 | HD11: 43221 | HE11: 43252 | HF11: 43282 | HG11: 43313 | HH11: 43344 | HI11: 43374 | HJ11: 43405 | HK11: 43435 | HL11: 43466 | HM11: 43497 | HN11: 43525 | HO11: 43556 | HP11: 43586 | HQ11: 43617 | HR11: 43647 | HS11: 43678 | HT11: 43709 | HU11: 43739 | HV11: 43770 | HW11: 43800 | HX11: 43831 | HY11: 43862 | HZ11: 43891 | IA11: 43922 | IB11: 43952 | IC11: 43983 | ID11: 44013 | IE11: 44044 | IF11: 44075 | IG11: 44105 | IH11: 44136 | II11: 44166 | IJ11: 44197 | IK11: 44228 | IL11: 44256 | IM11: 44287 | IN11: 44317 | IO11: 44348 | IP11: 44378 | IQ11: 44409 | IR11: 44440 | IS11: 44470 | IT11: 44501 | IU11: 44531 | IV11: 44562 | IW11: 44593 | IX11: 44621 | IY11: 44652 | IZ11: 44682 | JA11: 44713 | JB11: 44743 | JC11: 44774 | JD11: 44805 | JE11: 44835 | JF11: 44866 | JG11: 44896 | JH11: 44927 | JI11: 44958 | JJ11: 44986 | JK11: 45017 | JL11: 45047 | JM11: 45078 | JN11: 45108 | JO11: 45139 | JP11: 45170 | JQ11: 45200 | JR11: 45231 | JS11: 45261 | JT11: 45292 | JU11: 45323 | JV11: 45352 | JW11: 45383 | JX11: 45413 | JY11: 45444 | JZ11: 45474 | KA11: 45505 | KB11: 45536 | KC11: 45566 | KD11: 45597 | KE11: 45627 | KF11: 45658 | KG11: 45689 | KH11: 45717 | KI11: 45748 | KJ11: 45778 | KK11: 45809 | KL11: 45839 | KM11: 45870 | KN11: 45901 | KO11: 45931 | KP11: 45962 | KQ11: 45992 | KR11: 46023 | KS11: 46054 | KT11: 46082 | KU11: 46113 | KV11: 46143 | KW11: 46174 | KX11: 46204 | KY11: 46235 | KZ11: 46266 | LA11: 46296 | LB11: 46327 | LC11: 46357 | LD11: 46388 | LE11: 46419 | LF11: 46447 | LG11: 46478 | LH11: 46508 | LI11: 46539 | LJ11: 46569 | LK11: 46600 | LL11: 46631 | LM11: 46661 | LN11: 46692 | LO11: 46722 | LP11: 46753 | LQ11: 46784 | LR11: 46813 | LS11: 46844 | LT11: 46874 | LU11: 46905 | LV11: 46935 | LW11: 46966 | LX11: 46997 | LY11: 47027 | LZ11: 47058 | MA11: 47088 | MB11: 47119 | MC11: 47150 | MD11: 47178 | ME11: 47209 | MF11: 47239 | MG11: 47270 | MH11: 47300 | MI11: 47331 | MJ11: 47362 | MK11: 47392 | ML11: 47423 | MM11: 47453 | MN11: 47484 | MO11: 47515 | MP11: 47543 | MQ11: 47574 | MR11: 47604 | MS11: 47635 | MT11: 47665 | MU11: 47696 | MV11: 47727 | MW11: 47757 | MX11: 47788 | MY11: 47818 | MZ11: 47849 | NA11: 47880 | NB11: 47908 | NC11: 47939 | ND11: 47969 | NE11: 48000 | NF11: 48030 | NG11: 48061 | NH11: 48092 | NI11: 48122 | NJ11: 48153 | NK11: 48183 | NL11: 48214 | NM11: 48245 | NN11: 48274 | NO11: 48305 | NP11: 48335 | NQ11: 48366 | NR11: 48396 | NS11: 48427 | NT11: 48458 | NU11: 48488 | NV11: 48519 | NW11: 48549 | NX11: 48580 | NY11: 48611 | NZ11: 48639 | OA11: 48670 | OB11: 48700 | OC11: 48731 | OD11: 48761 | OE11: 48792 | OF11: 48823 | OG11: 48853 | OH11: 48884 | OI11: 48914 | OJ11: 48945 | OK11: 48976 | OL11: 49004 | OM11: 49035 | ON11: 49065 | OO11: 49096 | OP11: 49126 | OQ11: 49157 | OR11: 49188 | OS11: 49218 | OT11: 49249 | OU11: 49279 | OV11: 49310 | OW11: 49341 | OX11: 49369 | OY11: 49400 | OZ11: 49430 | PA11: 49461 | PB11: 49491 | PC11: 49522 | PD11: 49553 | PE11: 49583 | PF11: 49614 | PG11: 49644 | PH11: 49675 | PI11: 49706 | PJ11: 49735 | PK11: 49766 | PL11: 49796 | PM11: 49827 | PN11: 49857 | PO11: 49888 | PP11: 49919 | PQ11: 49949 | PR11: 49980 | PS11: 50010 | PT11: 50041 | PU11: 50072 | PV11: 50100 | PW11: 50131 | PX11: 50161 | PY11: 50192 | PZ11: 50222 | QA11: 50253 | QB11: 50284 | QC11: 50314 | QD11: 50345 | QE11: 50375 | QF11: 50406 | QG11: 50437 | QH11: 50465 | QI11: 50496 | QJ11: 50526 | QK11: 50557 | QL11: 50587 | QM11: 50618 | QN11: 50649 | QO11: 50679 | QP11: 50710 | QQ11: 50740 | QR11: 50771 | QS11: 50802 | QT11: 50830 | QU11: 50861 | QV11: 50891 | QW11: 50922 | QX11: 50952 | QY11: 50983 | QZ11: 51014 | RA11: 51044 | RB11: 51075 | RC11: 51105 | RD11: 51136 | RE11: 51167 | RF11: 51196 | RG11: 51227 | RH11: 51257 | RI11: 51288 | RJ11: 51318 | RK11: 51349 | RL11: 51380 | RM11: 51410 | RN11: 51441 | RO11: 51471 | RP11: 51502 | RQ11: 51533 | RR11: 51561 | RS11: 51592 | RT11: 51622 | RU11: 51653 | RV11: 51683 | RW11: 51714 | RX11: 51745 | RY11: 51775 | RZ11: 51806 | SA11: 51836 | SB11: 51867 | SC11: 51898 | SD11: 51926 | SE11: 51957 | SF11: 51987 | SG11: 52018 | SH11: 52048 | SI11: 52079 | SJ11: 52110 | SK11: 52140 | SL11: 52171 | SM11: 52201 | SN11: 52232 | SO11: 52263 | SP11: 52291 | SQ11: 52322 | SR11: 52352 | SS11: 52383 | ST11: 52413 | SU11: 52444 | SV11: 52475 | SW11: 52505 | SX11: 52536 | SY11: 52566 | SZ11: 52597 | TA11: 52628 | TB11: 52657 | TC11: 52688 | TD11: 52718 | TE11: 52749 | TF11: 52779 | TG11: 52810 | TH11: 52841 | TI11: 52871 | TJ11: 52902 | TK11: 52932 | TL11: 52963 | TM11: 52994 | TN11: 53022 | TO11: 53053 | TP11: 53083 | TQ11: 53114 | TR11: 53144 | TS11: 53175 | TT11: 53206 | TU11: 53236 | TV11: 53267 | TW11: 53297 | TX11: 53328 | TY11: 53359 | TZ11: 53387 | UA11: 53418 | UB11: 53448 | UC11: 53479 | UD11: 53509 | UE11: 53540 | UF11: 53571 | UG11: 53601 | UH11: 53632 | UI11: 53662 | UJ11: 53693 | UK11: 53724 | UL11: 53752 | UM11: 53783 | UN11: 53813 | UO11: 53844 | UP11: 53874 | UQ11: 53905 | UR11: 53936 | US11: 53966 | UT11: 53997 | UU11: 54027 | UV11: 54058 | UW11: 54089 | UX11: 54118 | UY11: 54149 | UZ11: 54179 | VA11: 54210 | VB11: 54240 | VC11: 54271 | VD11: 54302 | VE11: 54332 | VF11: 54363 | VG11: 54393 | VH11: 54424 | VI11: 54455 | VJ11: 54483 | VK11: 54514 | VL11: 54544 | VM11: 54575 | VN11: 54605 | VO11: 54636 | VP11: 54667 | VQ11: 54697 | VR11: 54728 | VS11: 54758 | VT11: 54789 | VU11: 54820 | VV11: 54848 | VW11: 54879 | VX11: 54909 | VY11: 54940 | VZ11: 54970 | WA11: 55001 | WB11: 55032 | WC11: 55062 | WD11: 55093 | WE11: 55123 | WF11: 55154 | WG11: 55185 | WH11: 55213 | WI11: 55244 | WJ11: 55274 | WK11: 55305 | WL11: 55335 | WM11: 55366 | WN11: 55397 | WO11: 55427 | WP11: 55458 | WQ11: 55488 | WR11: 55519 | WS11: 55550 | WT11: 55579 | WU11: 55610 | WV11: 55640 | WW11: 55671 | WX11: 55701 | WY11: 55732 | WZ11: 55763 | XA11: 55793 | XB11: 55824 | XC11: 55854 | XD11: 55885 | XE11: 55916 | XF11: 55944 | XG11: 55975 | XH11: 56005 | XI11: 56036 | XJ11: 56066 | XK11: 56097 | XL11: 56128 | XM11: 56158 | XN11: 56189 | XO11: 56219 | XP11: 56250 | XQ11: 56281 | XR11: 56309 | XS11: 56340 | XT11: 56370 | XU11: 56401 | XV11: 56431 | XW11: 56462 | XX11: 56493 | XY11: 56523 | XZ11: 56554 | YA11: 56584 | YB11: 56615 | YC11: 56646 | YD11: 56674 | YE11: 56705 | YF11: 56735 | YG11: 56766 | YH11: 56796 | YI11: 56827 | YJ11: 56858 | YK11: 56888 | YL11: 56919 | YM11: 56949
C12: =IF(C13<$B$13,0,B12+1) -> 1 | D12: =IF(D13<$B$13,0,C12+1) -> 2 | E12: =IF(E13<$B$13,0,D12+1) -> 3 | F12: =IF(F13<$B$13,0,E12+1) -> 4 | G12: =IF(G13<$B$13,0,F12+1) -> 5 | H12: =IF(H13<$B$13,0,G12+1) -> 6 | I12: =IF(I13<$B$13,0,H12+1) -> 7 | J12: =IF(J13<$B$13,0,I12+1) -> 8 | ... YM12: =IF(YM13<$B$13,0,YL12+1) -> 661
A13: Fecha de cierre | B13: =+Formulario!H310 -> 0 | C13: 36891 | D13: 36922 | E13: 36950 | F13: 36981 | G13: 37011 | H13: 37042 | I13: 37072 | J13: 37103 | K13: 37134 | L13: 37164 | M13: 37195 | N13: 37225 | O13: 37256 | P13: 37287 | Q13: 37315 | R13: 37346 | S13: 37376 | T13: 37407 | U13: 37437 | V13: 37468 | W13: 37499 | X13: 37529 | Y13: 37560 | Z13: 37590 | AA13: 37621 | AB13: 37652 | AC13: 37680 | AD13: 37711 | AE13: 37741 | AF13: 37772 | AG13: 37802 | AH13: 37833 | AI13: 37864 | AJ13: 37894 | AK13: 37925 | AL13: 37955 | AM13: 37986 | AN13: 38017 | AO13: 38046 | AP13: 38077 | AQ13: 38107 | AR13: 38138 | AS13: 38168 | AT13: 38199 | AU13: 38230 | AV13: 38260 | AW13: 38291 | AX13: 38321 | AY13: 38352 | AZ13: 38383 | BA13: 38411 | BB13: 38442 | BC13: 38472 | BD13: 38503 | BE13: 38533 | BF13: 38564 | BG13: 38595 | BH13: 38625 | BI13: 38656 | BJ13: 38686 | BK13: 38717 | BL13: 38748 | BM13: 38776 | BN13: 38807 | BO13: 38837 | BP13: 38868 | BQ13: 38898 | BR13: 38929 | BS13: 38960 | BT13: 38990 | BU13: 39021 | BV13: 39051 | BW13: 39082 | BX13: 39113 | BY13: 39141 | BZ13: 39172 | CA13: 39202 | CB13: 39233 | CC13: 39263 | CD13: 39294 | CE13: 39325 | CF13: 39355 | CG13: 39386 | CH13: 39416 | CI13: 39447 | CJ13: 39478 | CK13: 39507 | CL13: 39538 | CM13: 39568 | CN13: 39599 | CO13: 39629 | CP13: 39660 | CQ13: 39691 | CR13: 39721 | CS13: 39752 | CT13: 39782 | CU13: 39813 | CV13: 39844 | CW13: 39872 | CX13: 39903 | CY13: 39933 | CZ13: 39964 | DA13: 39994 | DB13: 40025 | DC13: 40056 | DD13: 40086 | DE13: 40117 | DF13: 40147 | DG13: 40178 | DH13: 40209 | DI13: 40237 | DJ13: 40268 | DK13: 40298 | DL13: 40329 | DM13: 40359 | DN13: 40390 | DO13: 40421 | DP13: 40451 | DQ13: 40482 | DR13: 40512 | DS13: 40543 | DT13: 40574 | DU13: 40602 | DV13: 40633 | DW13: 40663 | DX13: 40694 | DY13: 40724 | DZ13: 40755 | EA13: 40786 | EB13: 40816 | EC13: 40847 | ED13: 40877 | EE13: 40908 | EF13: 40939 | EG13: 40968 | EH13: 40999 | EI13: 41029 | EJ13: 41060 | EK13: 41090 | EL13: 41121 | EM13: 41152 | EN13: 41182 | EO13: 41213 | EP13: 41243 | EQ13: 41274 | ER13: 41305 | ES13: 41333 | ET13: 41364 | EU13: 41394 | EV13: 41425 | EW13: 41455 | EX13: 41486 | EY13: 41517 | EZ13: 41547 | FA13: 41578 | FB13: 41608 | FC13: 41639 | FD13: 41670 | FE13: 41698 | FF13: 41729 | FG13: 41759 | FH13: 41790 | FI13: 41820 | FJ13: 41851 | FK13: 41882 | FL13: 41912 | FM13: 41943 | FN13: 41973 | FO13: 42004 | FP13: 42035 | FQ13: 42063 | FR13: 42094 | FS13: 42124 | FT13: 42155 | FU13: 42185 | FV13: 42216 | FW13: 42247 | FX13: 42277 | FY13: 42308 | FZ13: 42338 | GA13: 42369 | GB13: 42400 | GC13: 42429 | GD13: 42460 | GE13: 42490 | GF13: 42521 | GG13: 42551 | GH13: 42582 | GI13: 42613 | GJ13: 42643 | GK13: 42674 | GL13: 42704 | GM13: 42735 | GN13: 42766 | GO13: 42794 | GP13: 42825 | GQ13: 42855 | GR13: 42886 | GS13: 42916 | GT13: 42947 | GU13: 42978 | GV13: 43008 | GW13: 43039 | GX13: 43069 | GY13: 43100 | GZ13: 43131 | HA13: 43159 | HB13: 43190 | HC13: 43220 | HD13: 43251 | HE13: 43281 | HF13: 43312 | HG13: 43343 | HH13: 43373 | HI13: 43404 | HJ13: 43434 | HK13: 43465 | HL13: 43496 | HM13: 43524 | HN13: 43555 | HO13: 43585 | HP13: 43616 | HQ13: 43646 | HR13: 43677 | HS13: 43708 | HT13: 43738 | HU13: 43769 | HV13: 43799 | HW13: 43830 | HX13: 43861 | HY13: 43890 | HZ13: 43921 | IA13: 43951 | IB13: 43982 | IC13: 44012 | ID13: 44043 | IE13: 44074 | IF13: 44104 | IG13: 44135 | IH13: 44165 | II13: 44196 | IJ13: 44227 | IK13: 44255 | IL13: 44286 | IM13: 44316 | IN13: 44347 | IO13: 44377 | IP13: 44408 | IQ13: 44439 | IR13: 44469 | IS13: 44500 | IT13: 44530 | IU13: 44561 | IV13: 44592 | IW13: 44620 | IX13: 44651 | IY13: 44681 | IZ13: 44712 | JA13: 44742 | JB13: 44773 | JC13: 44804 | JD13: 44834 | JE13: 44865 | JF13: 44895 | JG13: 44926 | JH13: 44957 | JI13: 44985 | JJ13: 45016 | JK13: 45046 | JL13: 45077 | JM13: 45107 | JN13: 45138 | JO13: 45169 | JP13: 45199 | JQ13: 45230 | JR13: 45260 | JS13: 45291 | JT13: 45322 | JU13: 45351 | JV13: 45382 | JW13: 45412 | JX13: 45443 | JY13: 45473 | JZ13: 45504 | KA13: 45535 | KB13: 45565 | KC13: 45596 | KD13: 45626 | KE13: 45657 | KF13: 45688 | KG13: 45716 | KH13: 45747 | KI13: 45777 | KJ13: 45808 | KK13: 45838 | KL13: 45869 | KM13: 45900 | KN13: 45930 | KO13: 45961 | KP13: 45991 | KQ13: 46022 | KR13: 46053 | KS13: 46081 | KT13: 46112 | KU13: 46142 | KV13: 46173 | KW13: 46203 | KX13: 46234 | KY13: 46265 | KZ13: 46295 | LA13: 46326 | LB13: 46356 | LC13: 46387 | LD13: 46418 | LE13: 46446 | LF13: 46477 | LG13: 46507 | LH13: 46538 | LI13: 46568 | LJ13: 46599 | LK13: 46630 | LL13: 46660 | LM13: 46691 | LN13: 46721 | LO13: 46752 | LP13: 46783 | LQ13: 46812 | LR13: 46843 | LS13: 46873 | LT13: 46904 | LU13: 46934 | LV13: 46965 | LW13: 46996 | LX13: 47026 | LY13: 47057 | LZ13: 47087 | MA13: 47118 | MB13: 47149 | MC13: 47177 | MD13: 47208 | ME13: 47238 | MF13: 47269 | MG13: 47299 | MH13: 47330 | MI13: 47361 | MJ13: 47391 | MK13: 47422 | ML13: 47452 | MM13: 47483 | MN13: 47514 | MO13: 47542 | MP13: 47573 | MQ13: 47603 | MR13: 47634 | MS13: 47664 | MT13: 47695 | MU13: 47726 | MV13: 47756 | MW13: 47787 | MX13: 47817 | MY13: 47848 | MZ13: 47879 | NA13: 47907 | NB13: 47938 | NC13: 47968 | ND13: 47999 | NE13: 48029 | NF13: 48060 | NG13: 48091 | NH13: 48121 | NI13: 48152 | NJ13: 48182 | NK13: 48213 | NL13: 48244 | NM13: 48273 | NN13: 48304 | NO13: 48334 | NP13: 48365 | NQ13: 48395 | NR13: 48426 | NS13: 48457 | NT13: 48487 | NU13: 48518 | NV13: 48548 | NW13: 48579 | NX13: 48610 | NY13: 48638 | NZ13: 48669 | OA13: 48699 | OB13: 48730 | OC13: 48760 | OD13: 48791 | OE13: 48822 | OF13: 48852 | OG13: 48883 | OH13: 48913 | OI13: 48944 | OJ13: 48975 | OK13: 49003 | OL13: 49034 | OM13: 49064 | ON13: 49095 | OO13: 49125 | OP13: 49156 | OQ13: 49187 | OR13: 49217 | OS13: 49248 | OT13: 49278 | OU13: 49309 | OV13: 49340 | OW13: 49368 | OX13: 49399 | OY13: 49429 | OZ13: 49460 | PA13: 49490 | PB13: 49521 | PC13: 49552 | PD13: 49582 | PE13: 49613 | PF13: 49643 | PG13: 49674 | PH13: 49705 | PI13: 49734 | PJ13: 49765 | PK13: 49795 | PL13: 49826 | PM13: 49856 | PN13: 49887 | PO13: 49918 | PP13: 49948 | PQ13: 49979 | PR13: 50009 | PS13: 50040 | PT13: 50071 | PU13: 50099 | PV13: 50130 | PW13: 50160 | PX13: 50191 | PY13: 50221 | PZ13: 50252 | QA13: 50283 | QB13: 50313 | QC13: 50344 | QD13: 50374 | QE13: 50405 | QF13: 50436 | QG13: 50464 | QH13: 50495 | QI13: 50525 | QJ13: 50556 | QK13: 50586 | QL13: 50617 | QM13: 50648 | QN13: 50678 | QO13: 50709 | QP13: 50739 | QQ13: 50770 | QR13: 50801 | QS13: 50829 | QT13: 50860 | QU13: 50890 | QV13: 50921 | QW13: 50951 | QX13: 50982 | QY13: 51013 | QZ13: 51043 | RA13: 51074 | RB13: 51104 | RC13: 51135 | RD13: 51166 | RE13: 51195 | RF13: 51226 | RG13: 51256 | RH13: 51287 | RI13: 51317 | RJ13: 51348 | RK13: 51379 | RL13: 51409 | RM13: 51440 | RN13: 51470 | RO13: 51501 | RP13: 51532 | RQ13: 51560 | RR13: 51591 | RS13: 51621 | RT13: 51652 | RU13: 51682 | RV13: 51713 | RW13: 51744 | RX13: 51774 | RY13: 51805 | RZ13: 51835 | SA13: 51866 | SB13: 51897 | SC13: 51925 | SD13: 51956 | SE13: 51986 | SF13: 52017 | SG13: 52047 | SH13: 52078 | SI13: 52109 | SJ13: 52139 | SK13: 52170 | SL13: 52200 | SM13: 52231 | SN13: 52262 | SO13: 52290 | SP13: 52321 | SQ13: 52351 | SR13: 52382 | SS13: 52412 | ST13: 52443 | SU13: 52474 | SV13: 52504 | SW13: 52535 | SX13: 52565 | SY13: 52596 | SZ13: 52627 | TA13: 52656 | TB13: 52687 | TC13: 52717 | TD13: 52748 | TE13: 52778 | TF13: 52809 | TG13: 52840 | TH13: 52870 | TI13: 52901 | TJ13: 52931 | TK13: 52962 | TL13: 52993 | TM13: 53021 | TN13: 53052 | TO13: 53082 | TP13: 53113 | TQ13: 53143 | TR13: 53174 | TS13: 53205 | TT13: 53235 | TU13: 53266 | TV13: 53296 | TW13: 53327 | TX13: 53358 | TY13: 53386 | TZ13: 53417 | UA13: 53447 | UB13: 53478 | UC13: 53508 | UD13: 53539 | UE13: 53570 | UF13: 53600 | UG13: 53631 | UH13: 53661 | UI13: 53692 | UJ13: 53723 | UK13: 53751 | UL13: 53782 | UM13: 53812 | UN13: 53843 | UO13: 53873 | UP13: 53904 | UQ13: 53935 | UR13: 53965 | US13: 53996 | UT13: 54026 | UU13: 54057 | UV13: 54088 | UW13: 54117 | UX13: 54148 | UY13: 54178 | UZ13: 54209 | VA13: 54239 | VB13: 54270 | VC13: 54301 | VD13: 54331 | VE13: 54362 | VF13: 54392 | VG13: 54423 | VH13: 54454 | VI13: 54482 | VJ13: 54513 | VK13: 54543 | VL13: 54574 | VM13: 54604 | VN13: 54635 | VO13: 54666 | VP13: 54696 | VQ13: 54727 | VR13: 54757 | VS13: 54788 | VT13: 54819 | VU13: 54847 | VV13: 54878 | VW13: 54908 | VX13: 54939 | VY13: 54969 | VZ13: 55000 | WA13: 55031 | WB13: 55061 | WC13: 55092 | WD13: 55122 | WE13: 55153 | WF13: 55184 | WG13: 55212 | WH13: 55243 | WI13: 55273 | WJ13: 55304 | WK13: 55334 | WL13: 55365 | WM13: 55396 | WN13: 55426 | WO13: 55457 | WP13: 55487 | WQ13: 55518 | WR13: 55549 | WS13: 55578 | WT13: 55609 | WU13: 55639 | WV13: 55670 | WW13: 55700 | WX13: 55731 | WY13: 55762 | WZ13: 55792 | XA13: 55823 | XB13: 55853 | XC13: 55884 | XD13: 55915 | XE13: 55943 | XF13: 55974 | XG13: 56004 | XH13: 56035 | XI13: 56065 | XJ13: 56096 | XK13: 56127 | XL13: 56157 | XM13: 56188 | XN13: 56218 | XO13: 56249 | XP13: 56280 | XQ13: 56308 | XR13: 56339 | XS13: 56369 | XT13: 56400 | XU13: 56430 | XV13: 56461 | XW13: 56492 | XX13: 56522 | XY13: 56553 | XZ13: 56583 | YA13: 56614 | YB13: 56645 | YC13: 56673 | YD13: 56704 | YE13: 56734 | YF13: 56765 | YG13: 56795 | YH13: 56826 | YI13: 56857 | YJ13: 56887 | YK13: 56918 | YL13: 56948 | YM13: 56979
A15: Cálculo Años
A16: Años Ex Ante | B16: 1 | C16: 13 | D16: 25 | E16: 37 | F16: 49
B17: =HLOOKUP(B16,$C$6:$YM$7,2,FALSE) -> 36891 | C17: =HLOOKUP(C16,$C$6:$YM$7,2,FALSE) -> 37256 | D17: =HLOOKUP(D16,$C$6:$YM$7,2,FALSE) -> 37621 | E17: =HLOOKUP(E16,$C$6:$YM$7,2,FALSE) -> 37986 | F17: =HLOOKUP(F16,$C$6:$YM$7,2,FALSE) -> 38352
A19: Años Ex Post | B19: 1 | C19: 13 | D19: 25 | E19: 37 | F19: 49
B20: =HLOOKUP(B19,$C$12:$YM$13,2,FALSE) -> 36891 | C20: =HLOOKUP(C19,$C$12:$YM$13,2,FALSE) -> 37256 | D20: =HLOOKUP(D19,$C$12:$YM$13,2,FALSE) -> 37621 | E20: =HLOOKUP(E19,$C$12:$YM$13,2,FALSE) -> 37986 | F20: =HLOOKUP(F19,$C$12:$YM$13,2,FALSE) -> 38352

Sheet IPIM y USD
A1: INDEC - Índice de Precios Internos al Por Mayor | D1: NO MODIFICAR NI MANIPULAR DATOS DE ESTA SOLAPA
A2: Fuente de los datos
A3: Hasta dic 2015: https://www.indec.gob.ar/indec/web/Nivel4-Tema-3-5-32. En vínculo "Serie mensual desde 1996 en adelante".
A4: Desde dic 2015: https://www.indec.gob.ar/ftp/cuadros/economia/series_sipm_dic2015.xls
A6: Calendario ex ante | C6: 36861 | D6: 36892 | E6: 36923 | F6: 36951 | G6: 36982 | H6: 37012 | I6: 37043 | J6: 37073 | K6: 37104 | L6: 37135 | M6: 37165 | N6: 37196 | O6: 37226 | P6: 37257 | Q6: 37288 | R6: 37316 | S6: 37347 | T6: 37377 | U6: 37408 | V6: 37438 | W6: 37469 | X6: 37500 | Y6: 37530 | Z6: 37561 | AA6: 37591 | AB6: 37622 | AC6: 37653 | AD6: 37681 | AE6: 37712 | AF6: 37742 | AG6: 37773 | AH6: 37803 | AI6: 37834 | AJ6: 37865 | AK6: 37895 | AL6: 37926 | AM6: 37956 | AN6: 37987 | AO6: 38018 | AP6: 38047 | AQ6: 38078 | AR6: 38108 | AS6: 38139 | AT6: 38169 | AU6: 38200 | AV6: 38231 | AW6: 38261 | AX6: 38292 | AY6: 38322 | AZ6: 38353 | BA6: 38384 | BB6: 38412 | BC6: 38443 | BD6: 38473 | BE6: 38504 | BF6: 38534 | BG6: 38565 | BH6: 38596 | BI6: 38626 | BJ6: 38657 | BK6: 38687 | BL6: 38718 | BM6: 38749 | BN6: 38777 | BO6: 38808 | BP6: 38838 | BQ6: 38869 | BR6: 38899 | BS6: 38930 | BT6: 38961 | BU6: 38991 | BV6: 39022 | BW6: 39052 | BX6: 39083 | BY6: 39114 | BZ6: 39142 | CA6: 39173 | CB6: 39203 | CC6: 39234 | CD6: 39264 | CE6: 39295 | CF6: 39326 | CG6: 39356 | CH6: 39387 | CI6: 39417 | CJ6: 39448 | CK6: 39479 | CL6: 39508 | CM6: 39539 | CN6: 39569 | CO6: 39600 | CP6: 39630 | CQ6: 39661 | CR6: 39692 | CS6: 39722 | CT6: 39753 | CU6: 39783 | CV6: 39814 | CW6: 39845 | CX6: 39873 | CY6: 39904 | CZ6: 39934 | DA6: 39965 | DB6: 39995 | DC6: 40026 | DD6: 40057 | DE6: 40087 | DF6: 40118 | DG6: 40148 | DH6: 40179 | DI6: 40210 | DJ6: 40238 | DK6: 40269 | DL6: 40299 | DM6: 40330 | DN6: 40360 | DO6: 40391 | DP6: 40422 | DQ6: 40452 | DR6: 40483 | DS6: 40513 | DT6: 40544 | DU6: 40575 | DV6: 40603 | DW6: 40634 | DX6: 40664 | DY6: 40695 | DZ6: 40725 | EA6: 40756 | EB6: 40787 | EC6: 40817 | ED6: 40848 | EE6: 40878 | EF6: 40909 | EG6: 40940 | EH6: 40969 | EI6: 41000 | EJ6: 41030 | EK6: 41061 | EL6: 41091 | EM6: 41122 | EN6: 41153 | EO6: 41183 | EP6: 41214 | EQ6: 41244 | ER6: 41275 | ES6: 41306 | ET6: 41334 | EU6: 41365 | EV6: 41395 | EW6: 41426 | EX6: 41456 | EY6: 41487 | EZ6: 41518 | FA6: 41548 | FB6: 41579 | FC6: 41609 | FD6: 41640 | FE6: 41671 | FF6: 41699 | FG6: 41730 | FH6: 41760 | FI6: 41791 | FJ6: 41821 | FK6: 41852 | FL6: 41883 | FM6: 41913 | FN6: 41944 | FO6: 41974 | FP6: 42005 | FQ6: 42036 | FR6: 42064 | FS6: 42095 | FT6: 42125 | FU6: 42156 | FV6: 42186 | FW6: 42217 | FX6: 42248 | FY6: 42278 | FZ6: 42309 | GA6: 42339 | GB6: 42370 | GC6: 42401 | GD6: 42430 | GE6: 42461 | GF6: 42491 | GG6: 42522 | GH6: 42552 | GI6: 42583 | GJ6: 42614 | GK6: 42644 | GL6: 42675 | GM6: 42705 | GN6: 42736 | GO6: 42767 | GP6: 42795 | GQ6: 42826 | GR6: 42856 | GS6: 42887 | GT6: 42917 | GU6: 42948 | GV6: 42979 | GW6: 43009 | GX6: 43040 | GY6: 43070 | GZ6: 43101 | HA6: 43132 | HB6: 43160 | HC6: 43191 | HD6: 43221 | HE6: 43252 | HF6: 43282 | HG6: 43313 | HH6: 43344 | HI6: 43374 | HJ6: 43405 | HK6: 43435 | HL6: 43466 | HM6: 43497 | HN6: 43525 | HO6: 43556 | HP6: 43586 | HQ6: 43617 | HR6: 43647 | HS6: 43678 | HT6: 43709 | HU6: 43739 | HV6: 43770 | HW6: 43800 | HX6: 43831 | HY6: 43862 | HZ6: 43891 | IA6: 43922 | IB6: 43952 | IC6: 43983 | ID6: 44013 | IE6: 44044 | IF6: 44075 | IG6: 44105 | IH6: 44136 | II6: 44166 | IJ6: 44197 | IK6: 44228 | IL6: 44256 | IM6: 44287 | IN6: 44317 | IO6: 44348 | IP6: 44378 | IQ6: 44409 | IR6: 44440 | IS6: 44470 | IT6: 44501 | IU6: 44531 | IV6: 44562 | IW6: 44593 | IX6: 44621 | IY6: 44652 | IZ6: 44682 | JA6: 44713 | JB6: 44743 | JC6: 44774 | JD6: 44805 | JE6: 44835 | JF6: 44866 | JG6: 44896 | JH6: 44927 | JI6: 44958 | JJ6: 44986 | JK6: 45017 | JL6: 45047 | JM6: 45078 | JN6: 45108 | JO6: 45139 | JP6: 45170 | JQ6: 45200 | JR6: 45231 | JS6: 45261 | JT6: 45292 | JU6: 45323 | JV6: 45352 | JW6: 45383 | JX6: 45413 | JY6: 45444 | JZ6: 45474 | KA6: 45505 | KB6: 45536 | KC6: 45566 | KD6: 45597 | KE6: 45627 | KF6: 45658 | KG6: 45689 | KH6: 45717 | KI6: 45748 | KJ6: 45778 | KK6: 45809 | KL6: 45839 | KM6: 45870 | KN6: 45901 | KO6: 45931 | KP6: 45962 | KQ6: 45992 | KR6: 46023 | KS6: 46054 | KT6: 46082 | KU6: 46113 | KV6: 46143 | KW6: 46174 | KX6: 46204 | KY6: 46235 | KZ6: 46266 | LA6: 46296 | LB6: 46327 | LC6: 46357 | LD6: 46388 | LE6: 46419 | LF6: 46447 | LG6: 46478 | LH6: 46508 | LI6: 46539 | LJ6: 46569 | LK6: 46600 | LL6: 46631 | LM6: 46661 | LN6: 46692 | LO6: 46722 | LP6: 46753 | LQ6: 46784 | LR6: 46813 | LS6: 46844 | LT6: 46874 | LU6: 46905 | LV6: 46935 | LW6: 46966 | LX6: 46997 | LY6: 47027 | LZ6: 47058 | MA6: 47088 | MB6: 47119 | MC6: 47150 | MD6: 47178 | ME6: 47209 | MF6: 47239 | MG6: 47270 | MH6: 47300 | MI6: 47331 | MJ6: 47362 | MK6: 47392 | ML6: 47423 | MM6: 47453 | MN6: 47484 | MO6: 47515 | MP6: 47543 | MQ6: 47574 | MR6: 47604 | MS6: 47635 | MT6: 47665 | MU6: 47696 | MV6: 47727 | MW6: 47757 | MX6: 47788 | MY6: 47818 | MZ6: 47849 | NA6: 47880 | NB6: 47908 | NC6: 47939 | ND6: 47969 | NE6: 48000 | NF6: 48030 | NG6: 48061 | NH6: 48092 | NI6: 48122 | NJ6: 48153 | NK6: 48183 | NL6: 48214 | NM6: 48245 | NN6: 48274 | NO6: 48305 | NP6: 48335 | NQ6: 48366 | NR6: 48396 | NS6: 48427 | NT6: 48458 | NU6: 48488 | NV6: 48519 | NW6: 48549 | NX6: 48580 | NY6: 48611 | NZ6: 48639 | OA6: 48670 | OB6: 48700 | OC6: 48731 | OD6: 48761 | OE6: 48792 | OF6: 48823 | OG6: 48853 | OH6: 48884 | OI6: 48914
A7: Calendario ex post | C7: 36891 | D7: 36922 | E7: 36950 | F7: 36981 | G7: 37011 | H7: 37042 | I7: 37072 | J7: 37103 | K7: 37134 | L7: 37164 | M7: 37195 | N7: 37225 | O7: 37256 | P7: 37287 | Q7: 37315 | R7: 37346 | S7: 37376 | T7: 37407 | U7: 37437 | V7: 37468 | W7: 37499 | X7: 37529 | Y7: 37560 | Z7: 37590 | AA7: 37621 | AB7: 37652 | AC7: 37680 | AD7: 37711 | AE7: 37741 | AF7: 37772 | AG7: 37802 | AH7: 37833 | AI7: 37864 | AJ7: 37894 | AK7: 37925 | AL7: 37955 | AM7: 37986 | AN7: 38017 | AO7: 38046 | AP7: 38077 | AQ7: 38107 | AR7: 38138 | AS7: 38168 | AT7: 38199 | AU7: 38230 | AV7: 38260 | AW7: 38291 | AX7: 38321 | AY7: 38352 | AZ7: 38383 | BA7: 38411 | BB7: 38442 | BC7: 38472 | BD7: 38503 | BE7: 38533 | BF7: 38564 | BG7: 38595 | BH7: 38625 | BI7: 38656 | BJ7: 38686 | BK7: 38717 | BL7: 38748 | BM7: 38776 | BN7: 38807 | BO7: 38837 | BP7: 38868 | BQ7: 38898 | BR7: 38929 | BS7: 38960 | BT7: 38990 | BU7: 39021 | BV7: 39051 | BW7: 39082 | BX7: 39113 | BY7: 39141 | BZ7: 39172 | CA7: 39202 | CB7: 39233 | CC7: 39263 | CD7: 39294 | CE7: 39325 | CF7: 39355 | CG7: 39386 | CH7: 39416 | CI7: 39447 | CJ7: 39478 | CK7: 39507 | CL7: 39538 | CM7: 39568 | CN7: 39599 | CO7: 39629 | CP7: 39660 | CQ7: 39691 | CR7: 39721 | CS7: 39752 | CT7: 39782 | CU7: 39813 | CV7: 39844 | CW7: 39872 | CX7: 39903 | CY7: 39933 | CZ7: 39964 | DA7: 39994 | DB7: 40025 | DC7: 40056 | DD7: 40086 | DE7: 40117 | DF7: 40147 | DG7: 40178 | DH7: 40209 | DI7: 40237 | DJ7: 40268 | DK7: 40298 | DL7: 40329 | DM7: 40359 | DN7: 40390 | DO7: 40421 | DP7: 40451 | DQ7: 40482 | DR7: 40512 | DS7: 40543 | DT7: 40574 | DU7: 40602 | DV7: 40633 | DW7: 40663 | DX7: 40694 | DY7: 40724 | DZ7: 40755 | EA7: 40786 | EB7: 40816 | EC7: 40847 | ED7: 40877 | EE7: 40908 | EF7: 40939 | EG7: 40968 | EH7: 40999 | EI7: 41029 | EJ7: 41060 | EK7: 41090 | EL7: 41121 | EM7: 41152 | EN7: 41182 | EO7: 41213 | EP7: 41243 | EQ7: 41274 | ER7: 41305 | ES7: 41333 | ET7: 41364 | EU7: 41394 | EV7: 41425 | EW7: 41455 | EX7: 41486 | EY7: 41517 | EZ7: 41547 | FA7: 41578 | FB7: 41608 | FC7: 41639 | FD7: 41670 | FE7: 41698 | FF7: 41729 | FG7: 41759 | FH7: 41790 | FI7: 41820 | FJ7: 41851 | FK7: 41882 | FL7: 41912 | FM7: 41943 | FN7: 41973 | FO7: 42004 | FP7: 42035 | FQ7: 42063 | FR7: 42094 | FS7: 42124 | FT7: 42155 | FU7: 42185 | FV7: 42216 | FW7: 42247 | FX7: 42277 | FY7: 42308 | FZ7: 42338 | GA7: 42369 | GB7: 42400 | GC7: 42429 | GD7: 42460 | GE7: 42490 | GF7: 42521 | GG7: 42551 | GH7: 42582 | GI7: 42613 | GJ7: 42643 | GK7: 42674 | GL7: 42704 | GM7: 42735 | GN7: 42766 | GO7: 42794 | GP7: 42825 | GQ7: 42855 | GR7: 42886 | GS7: 42916 | GT7: 42947 | GU7: 42978 | GV7: 43008 | GW7: 43039 | GX7: 43069 | GY7: 43100 | GZ7: 43131 | HA7: 43159 | HB7: 43190 | HC7: 43220 | HD7: 43251 | HE7: 43281 | HF7: 43312 | HG7: 43343 | HH7: 43373 | HI7: 43404 | HJ7: 43434 | HK7: 43465 | HL7: 43496 | HM7: 43524 | HN7: 43555 | HO7: 43585 | HP7: 43616 | HQ7: 43646 | HR7: 43677 | HS7: 43708 | HT7: 43738 | HU7: 43769 | HV7: 43799 | HW7: 43830 | HX7: 43861 | HY7: 43890 | HZ7: 43921 | IA7: 43951 | IB7: 43982 | IC7: 44012 | ID7: 44043 | IE7: 44074 | IF7: 44104 | IG7: 44135 | IH7: 44165 | II7: 44196 | IJ7: 44227 | IK7: 44255 | IL7: 44286 | IM7: 44316 | IN7: 44347 | IO7: 44377 | IP7: 44408 | IQ7: 44439 | IR7: 44469 | IS7: 44500 | IT7: 44530 | IU7: 44561 | IV7: 44592 | IW7: 44620 | IX7: 44651 | IY7: 44681 | IZ7: 44712 | JA7: 44742 | JB7: 44773 | JC7: 44804 | JD7: 44834 | JE7: 44865 | JF7: 44895 | JG7: 44926 | JH7: 44957 | JI7: 44985 | JJ7: 45016 | JK7: 45046 | JL7: 45077 | JM7: 45107 | JN7: 45138 | JO7: 45169 | JP7: 45199 | JQ7: 45230 | JR7: 45260 | JS7: 45291 | JT7: 45322 | JU7: 45351 | JV7: 45382 | JW7: 45412 | JX7: 45443 | JY7: 45473 | JZ7: 45504 | KA7: 45535 | KB7: 45565 | KC7: 45596 | KD7: 45626 | KE7: 45657 | KF7: 45688 | KG7: 45716 | KH7: 45747 | KI7: 45777 | KJ7: 45808 | KK7: 45838 | KL7: 45869 | KM7: 45900 | KN7: 45930 | KO7: 45961 | KP7: 45991 | KQ7: 46022 | KR7: 46053 | KS7: 46081 | KT7: 46112 | KU7: 46142 | KV7: 46173 | KW7: 46203 | KX7: 46234 | KY7: 46265 | KZ7: 46295 | LA7: 46326 | LB7: 46356 | LC7: 46387 | LD7: 46418 | LE7: 46446 | LF7: 46477 | LG7: 46507 | LH7: 46538 | LI7: 46568 | LJ7: 46599 | LK7: 46630 | LL7: 46660 | LM7: 46691 | LN7: 46721 | LO7: 46752 | LP7: 46783 | LQ7: 46812 | LR7: 46843 | LS7: 46873 | LT7: 46904 | LU7: 46934 | LV7: 46965 | LW7: 46996 | LX7: 47026 | LY7: 47057 | LZ7: 47087 | MA7: 47118 | MB7: 47149 | MC7: 47177 | MD7: 47208 | ME7: 47238 | MF7: 47269 | MG7: 47299 | MH7: 47330 | MI7: 47361 | MJ7: 47391 | MK7: 47422 | ML7: 47452 | MM7: 47483 | MN7: 47514 | MO7: 47542 | MP7: 47573 | MQ7: 47603 | MR7: 47634 | MS7: 47664 | MT7: 47695 | MU7: 47726 | MV7: 47756 | MW7: 47787 | MX7: 47817 | MY7: 47848 | MZ7: 47879 | NA7: 47907 | NB7: 47938 | NC7: 47968 | ND7: 47999 | NE7: 48029 | NF7: 48060 | NG7: 48091 | NH7: 48121 | NI7: 48152 | NJ7: 48182 | NK7: 48213 | NL7: 48244 | NM7: 48273 | NN7: 48304 | NO7: 48334 | NP7: 48365 | NQ7: 48395 | NR7: 48426 | NS7: 48457 | NT7: 48487 | NU7: 48518 | NV7: 48548 | NW7: 48579 | NX7: 48610 | NY7: 48638 | NZ7: 48669 | OA7: 48699 | OB7: 48730 | OC7: 48760 | OD7: 48791 | OE7: 48822 | OF7: 48852 | OG7: 48883 | OH7: 48913 | OI7: 48944
A8: IPIM | B8: Nivel general | D8: 100 | E8: =+D8*(1+E9) -> 100.11335 | F8: =+E8*(1+F9) -> 99.452158 | G8: =+F8*(1+G9) -> 99.263247 | H8: =+G8*(1+H9) -> 99.338812 | I8: =+H8*(1+I9) -> 98.894871 | J8: =+I8*(1+J9) -> 98.545386 | K8: =+J8*(1+K9) -> 98.063663 | L8: =+K8*(1+L9) -> 97.638613 | ... KR8: =+KQ8*(1+KR9) -> 126960.32
A9: Variación del índice base 1993 | D9: 0.00037796466 | E9: 0.0011334656 | F9: -0.0066043966 | G9: -0.0018995156 | H9: 0.00076125226 | I9: -0.004468955 | J9: -0.0035339064 | K9: -0.0048883351 | L9: -0.004334425 | M9: -0.014994679 | N9: -0.01394618 | O9: -0.0017928287 | P9: 0.063659948 | Q9: 0.12326454 | R9: 0.12577251 | S9: 0.19910979 | T9: 0.12329869 | U9: 0.0854216 | V9: 0.046478587 | W9: 0.050426687 | X9: 0.02437223 | Y9: 0.0049567412 | Z9: -0.01659044 | AA9: -0.004012402 | AB9: 0.0042116828 | AC9: 0.0038749088 | AD9: -0.006857091 | AE9: -0.018289895 | AF9: -0.0063809967 | AG9: -0.0013593962 | AH9: -0.00037551633 | AI9: 0.013664538 | AJ9: -0.0017139945 | AK9: 0.0053364269 | AL9: 0.010385414 | AM9: 0.017405208 | AN9: -0.0033676081 | AO9: 0.013921427 | AP9: 0.0043545879 | AQ9: 0.0080077866 | AR9: 0.012859902 | AS9: 0.0022533258 | AT9: 0.0091659821 | AU9: 0.024206332 | AV9: 0.0023425082 | AW9: 0.0058425841 | AX9: -0.011907725 | AY9: 0.0087339912 | AZ9: -0.0095741581 | BA9: 0.01063338 | BB9: 0.019712218 | BC9: 0.014600326 | BD9: -0.00072353083 | BE9: 0.0023732904 | BF9: 0.012520567 | BG9: 0.012484642 | BH9: 0.01890707 | BI9: 0.011256675 | BJ9: 0.00079781172 | BK9: 0.0098697946 | BL9: 0.012930872 | BM9: 0.015549041 | BN9: -0.006212088 | BO9: 0.014487425 | BP9: 0.0039869518 | BQ9: 0.0080505415 | BR9: 0.0071267414 | BS9: 0.0064362421 | BT9: -0.0026145638 | BU9: 0.0041446739 | BV9: 0.00095251535 | BW9: 0.0039474148 | BX9: 0.0035106196 | BY9: 0.0082910617 | BZ9: 0.0062452293 | CA9: 0.017309151 | CB9: 0.015523319 | CC9: 0.01945798 | CD9: 0.022687838 | CE9: 0.0076189257 | CF9: 0.010261787 | CG9: 0.0092141262 | CH9: 0.010469899 | CI9: 0.0062908598 | CJ9: 0.0079063496 | CK9: 0.0092733354 | CL9: 0.011176382 | CM9: 0.012333909 | CN9: 0.010682755 | CO9: 0.011967504 | CP9: 0.0075674742 | CQ9: 0.0083388069 | CR9: 0.0055793141 | CS9: 0.0055201938 | CT9: -0.0027729539 | CU9: -0.0026121394 | CV9: -0.00081667136 | CW9: 0.0014092049 | CX9: 0.011454786 | CY9: 0.004730369 | CZ9: 0.0047634873 | DA9: 0.011300992 | DB9: 0.01245571 | DC9: 0.010418069 | DD9: 0.010230724 | DE9: 0.0092568173 | DF9: 0.010530717 | DG9: 0.012515515 | DH9: 0.013484523 | DI9: 0.015371434 | DJ9: 0.015188366 | DK9: 0.011563096 | DL9: 0.012083424 | DM9: 0.012154063 | DN9: 0.0096725488 | DO9: 0.0099771017 | DP9: 0.0093233083 | DQ9: 0.0090538186 | DR9: 0.0094268905 | DS9: 0.0094288672 | DT9: 0.010945895 | DU9: 0.0093058128 | DV9: 0.0096132838 | DW9: 0.010041117 | DX9: 0.010284098 | DY9: 0.011409424 | DZ9: 0.010064581 | EA9: 0.010151125 | EB9: 0.010254619 | EC9: 0.0091131001 | ED9: 0.0095347525 | EE9: 0.0092050878 | EF9: 0.0095761941 | EG9: 0.0098773174 | EH9: 0.011818358 | EI9: 0.011315906 | EJ9: 0.010203114 | EK9: 0.0099123285 | EL9: 0.009703504 | EM9: 0.010346669 | EN9: 0.011133585 | EO9: 0.010344206 | EP9: 0.010042095 | EQ9: 0.0097126812 | ER9: 0.010161429 | ES9: 0.010561308 | ET9: 0.010074013 | EU9: 0.0096003799 | EV9: 0.012566782 | EW9: 0.013456114 | EX9: 0.011329219 | EY9: 0.011315623 | EZ9: 0.010932898 | FA9: 0.011400523 | FB9: 0.012164384 | FC9: 0.014926066 | FD9: 0.049529847 | FE9: 0.05121466 | FF9: 0.024339034 | FG9: 0.017193484 | FH9: 0.018679323 | FI9: 0.015057262 | FJ9: 0.013462056 | FK9: 0.016319405 | FL9: 0.01594533 | FM9: 0.012252199 | FN9: 0.0091263405 | FO9: 0.0095235811 | FP9: 0.0020079367 | FQ9: 0.0024900694 | FR9: 0.0098054291 | FS9: 0.0074495748 | FT9: 0.014823858 | FU9: 0.013152317 | FV9: 0.014372463 | FW9: 0.0142803 | FX9: 0.013507721 | FY9: 0.009271911 | FZ9: 0.01 | GA9: 0.01 | GB9: 0.087871791 | GC9: 0.049488416 | GD9: 0.024785335 | GE9: 0.015486478 | GF9: 0.036080168 | GG9: 0.029103064 | GH9: 0.027836885 | GI9: 0.0039493492 | GJ9: 0.0042682987 | GK9: 0.0059324356 | GL9: 0.012263818 | GM9: 0.0063590626 | GN9: 0.014992425 | GO9: 0.016699184 | GP9: 0.0092219706 | GQ9: 0.0046249656 | GR9: 0.0085743573 | GS9: 0.018706766 | GT9: 0.025546679 | GU9: 0.019189011 | GV9: 0.0099982664 | GW9: 0.014685135 | GX9: 0.01544315 | GY9: 0.016419563 | GZ9: 0.045689851 | HA9: 0.048475156 | HB9: 0.019355685 | HC9: 0.017931231 | HD9: 0.075087584 | HE9: 0.065323 | HF9: 0.047313598 | HG9: 0.048942157 | HH9: 0.16042481 | HI9: 0.030243185 | HJ9: 0.0010718737 | HK9: 0.012779984 | HL9: 0.0056943062 | HM9: 0.033638843 | HN9: 0.041062859 | HO9: 0.04582432 | HP9: 0.049471979 | HQ9: 0.016530764 | HR9: 0.00077137002 | HS9: 0.1121341 | HT9: 0.041673111 | HU9: 0.036115349 | HV9: 0.053890581 | HW9: 0.036857834 | HX9: 0.015057219 | HY9: 0.011169257 | HZ9: 0.0095835844 | IA9: -0.012953438 | IB9: 0.0036562559 | IC9: 0.03659384 | ID9: 0.035318225 | IE9: 0.041043633 | IF9: 0.036936622 | IG9: 0.046650583 | IH9: 0.041713982 | II9: 0.04401957 | IJ9: 0.055574037 | IK9: 0.060878744 | IL9: 0.038909324 | IM9: 0.047659752 | IN9: 0.032224824 | IO9: 0.03130378 | IP9: 0.022363752 | IQ9: 0.025153905 | IR9: 0.027914097 | IS9: 0.028472334 | IT9: 0.029457392 | IU9: 0.022581425 | IV9: 0.037251948 | IW9: 0.047378093 | IX9: 0.063293001 | IY9: 0.059018591 | IZ9: 0.051698164 | JA9: 0.048236081 | JB9: 0.070802951 | JC9: 0.081762924 | JD9: 0.054821581 | JE9: 0.047754741 | JF9: 0.062943987 | JG9: 0.061372876 | JH9: 0.06481708 | JI9: 0.070278578 | JJ9: 0.050587702 | JK9: 0.069332882 | JL9: 0.070826433 | JM9: 0.074890749 | JN9: 0.070171254 | JO9: 0.18711171 | JP9: 0.092126217 | JQ9: 0.075595103 | JR9: 0.11100615 | JS9: 0.54031677 | JT9: 0.17952745 | JU9: 0.10155919 | JV9: 0.054203782 | JW9: 0.034487838 | JX9: 0.034832876 | JY9: 0.026567816 | JZ9: 0.030826586 | KA9: 0.02070396 | KB9: 0.01975926 | KC9: 0.011832495 | KD9: 0.013876168 | KE9: 0.008483512 | KF9: 0.015067748 | KG9: 0.01640568 | KH9: 0.014826182 | KI9: 0.028340898 | KJ9: -0.0025985656 | KK9: 0.016458308 | KL9: 0.028471583 | KM9: 0.031028946 | KN9: 0.036936308 | KO9: 0.010841418 | KP9: 0.015856715 | KQ9: 0.023992555 | KR9: 0.01667107
A11: Fuente de los datos
A12: Hasta feb 2002: Serie de tipo de cambio nominal BCRA
A13: Desde mar 2002: Serie de tipo de cambio Com. A 3500 BCRA (promedio mensual)
A15: Calendario ex ante | C15: 36861 | D15: 36892 | E15: 36923 | F15: 36951 | G15: 36982 | H15: 37012 | I15: 37043 | J15: 37073 | K15: 37104 | L15: 37135 | M15: 37165 | N15: 37196 | O15: 37226 | P15: 37257 | Q15: 37288 | R15: 37316 | S15: 37347 | T15: 37377 | U15: 37408 | V15: 37438 | W15: 37469 | X15: 37500 | Y15: 37530 | Z15: 37561 | AA15: 37591 | AB15: 37622 | AC15: 37653 | AD15: 37681 | AE15: 37712 | AF15: 37742 | AG15: 37773 | AH15: 37803 | AI15: 37834 | AJ15: 37865 | AK15: 37895 | AL15: 37926 | AM15: 37956 | AN15: 37987 | AO15: 38018 | AP15: 38047 | AQ15: 38078 | AR15: 38108 | AS15: 38139 | AT15: 38169 | AU15: 38200 | AV15: 38231 | AW15: 38261 | AX15: 38292 | AY15: 38322 | AZ15: 38353 | BA15: 38384 | BB15: 38412 | BC15: 38443 | BD15: 38473 | BE15: 38504 | BF15: 38534 | BG15: 38565 | BH15: 38596 | BI15: 38626 | BJ15: 38657 | BK15: 38687 | BL15: 38718 | BM15: 38749 | BN15: 38777 | BO15: 38808 | BP15: 38838 | BQ15: 38869 | BR15: 38899 | BS15: 38930 | BT15: 38961 | BU15: 38991 | BV15: 39022 | BW15: 39052 | BX15: 39083 | BY15: 39114 | BZ15: 39142 | CA15: 39173 | CB15: 39203 | CC15: 39234 | CD15: 39264 | CE15: 39295 | CF15: 39326 | CG15: 39356 | CH15: 39387 | CI15: 39417 | CJ15: 39448 | CK15: 39479 | CL15: 39508 | CM15: 39539 | CN15: 39569 | CO15: 39600 | CP15: 39630 | CQ15: 39661 | CR15: 39692 | CS15: 39722 | CT15: 39753 | CU15: 39783 | CV15: 39814 | CW15: 39845 | CX15: 39873 | CY15: 39904 | CZ15: 39934 | DA15: 39965 | DB15: 39995 | DC15: 40026 | DD15: 40057 | DE15: 40087 | DF15: 40118 | DG15: 40148 | DH15: 40179 | DI15: 40210 | DJ15: 40238 | DK15: 40269 | DL15: 40299 | DM15: 40330 | DN15: 40360 | DO15: 40391 | DP15: 40422 | DQ15: 40452 | DR15: 40483 | DS15: 40513 | DT15: 40544 | DU15: 40575 | DV15: 40603 | DW15: 40634 | DX15: 40664 | DY15: 40695 | DZ15: 40725 | EA15: 40756 | EB15: 40787 | EC15: 40817 | ED15: 40848 | EE15: 40878 | EF15: 40909 | EG15: 40940 | EH15: 40969 | EI15: 41000 | EJ15: 41030 | EK15: 41061 | EL15: 41091 | EM15: 41122 | EN15: 41153 | EO15: 41183 | EP15: 41214 | EQ15: 41244 | ER15: 41275 | ES15: 41306 | ET15: 41334 | EU15: 41365 | EV15: 41395 | EW15: 41426 | EX15: 41456 | EY15: 41487 | EZ15: 41518 | FA15: 41548 | FB15: 41579 | FC15: 41609 | FD15: 41640 | FE15: 41671 | FF15: 41699 | FG15: 41730 | FH15: 41760 | FI15: 41791 | FJ15: 41821 | FK15: 41852 | FL15: 41883 | FM15: 41913 | FN15: 41944 | FO15: 41974 | FP15: 42005 | FQ15: 42036 | FR15: 42064 | FS15: 42095 | FT15: 42125 | FU15: 42156 | FV15: 42186 | FW15: 42217 | FX15: 42248 | FY15: 42278 | FZ15: 42309 | GA15: 42339 | GB15: 42370 | GC15: 42401 | GD15: 42430 | GE15: 42461 | GF15: 42491 | GG15: 42522 | GH15: 42552 | GI15: 42583 | GJ15: 42614 | GK15: 42644 | GL15: 42675 | GM15: 42705 | GN15: 42736 | GO15: 42767 | GP15: 42795 | GQ15: 42826 | GR15: 42856 | GS15: 42887 | GT15: 42917 | GU15: 42948 | GV15: 42979 | GW15: 43009 | GX15: 43040 | GY15: 43070 | GZ15: 43101 | HA15: 43132 | HB15: 43160 | HC15: 43191 | HD15: 43221 | HE15: 43252 | HF15: 43282 | HG15: 43313 | HH15: 43344 | HI15: 43374 | HJ15: 43405 | HK15: 43435 | HL15: 43466 | HM15: 43497 | HN15: 43525 | HO15: 43556 | HP15: 43586 | HQ15: 43617 | HR15: 43647 | HS15: 43678 | HT15: 43709 | HU15: 43739 | HV15: 43770 | HW15: 43800 | HX15: 43831 | HY15: 43862 | HZ15: 43891 | IA15: 43922 | IB15: 43952 | IC15: 43983 | ID15: 44013 | IE15: 44044 | IF15: 44075 | IG15: 44105 | IH15: 44136 | II15: 44166 | IJ15: 44197 | IK15: 44228 | IL15: 44256 | IM15: 44287 | IN15: 44317 | IO15: 44348 | IP15: 44378 | IQ15: 44409 | IR15: 44440 | IS15: 44470 | IT15: 44501 | IU15: 44531 | IV15: 44562 | IW15: 44593 | IX15: 44621 | IY15: 44652 | IZ15: 44682 | JA15: 44713 | JB15: 44743 | JC15: 44774 | JD15: 44805 | JE15: 44835 | JF15: 44866 | JG15: 44896 | JH15: 44927 | JI15: 44958 | JJ15: 44986 | JK15: 45017 | JL15: 45047 | JM15: 45078 | JN15: 45108 | JO15: 45139 | JP15: 45170 | JQ15: 45200 | JR15: 45231 | JS15: 45261 | JT15: 45292 | JU15: 45323 | JV15: 45352 | JW15: 45383 | JX15: 45413 | JY15: 45444 | JZ15: 45474 | KA15: 45505 | KB15: 45536 | KC15: 45566 | KD15: 45597 | KE15: 45627 | KF15: 45658 | KG15: 45689 | KH15: 45717 | KI15: 45748 | KJ15: 45778 | KK15: 45809 | KL15: 45839 | KM15: 45870 | KN15: 45901 | KO15: 45931 | KP15: 45962 | KQ15: 45992 | KR15: 46023 | KS15: 46054 | KT15: 46082 | KU15: 46113 | KV15: 46143 | KW15: 46174 | KX15: 46204 | KY15: 46235 | KZ15: 46266 | LA15: 46296 | LB15: 46327 | LC15: 46357 | LD15: 46388 | LE15: 46419 | LF15: 46447 | LG15: 46478 | LH15: 46508 | LI15: 46539 | LJ15: 46569 | LK15: 46600 | LL15: 46631 | LM15: 46661 | LN15: 46692 | LO15: 46722 | LP15: 46753 | LQ15: 46784 | LR15: 46813 | LS15: 46844 | LT15: 46874 | LU15: 46905 | LV15: 46935 | LW15: 46966 | LX15: 46997 | LY15: 47027 | LZ15: 47058 | MA15: 47088 | MB15: 47119 | MC15: 47150 | MD15: 47178 | ME15: 47209 | MF15: 47239 | MG15: 47270 | MH15: 47300 | MI15: 47331 | MJ15: 47362 | MK15: 47392 | ML15: 47423 | MM15: 47453 | MN15: 47484 | MO15: 47515 | MP15: 47543 | MQ15: 47574 | MR15: 47604 | MS15: 47635 | MT15: 47665 | MU15: 47696 | MV15: 47727 | MW15: 47757 | MX15: 47788 | MY15: 47818 | MZ15: 47849 | NA15: 47880 | NB15: 47908 | NC15: 47939 | ND15: 47969 | NE15: 48000 | NF15: 48030 | NG15: 48061 | NH15: 48092 | NI15: 48122 | NJ15: 48153 | NK15: 48183 | NL15: 48214 | NM15: 48245 | NN15: 48274 | NO15: 48305 | NP15: 48335 | NQ15: 48366 | NR15: 48396 | NS15: 48427 | NT15: 48458 | NU15: 48488 | NV15: 48519 | NW15: 48549 | NX15: 48580 | NY15: 48611 | NZ15: 48639 | OA15: 48670 | OB15: 48700 | OC15: 48731 | OD15: 48761 | OE15: 48792 | OF15: 48823 | OG15: 48853 | OH15: 48884 | OI15: 48914
A16: Calendario ex post | C16: 36891 | D16: 36922 | E16: 36950 | F16: 36981 | G16: 37011 | H16: 37042 | I16: 37072 | J16: 37103 | K16: 37134 | L16: 37164 | M16: 37195 | N16: 37225 | O16: 37256 | P16: 37287 | Q16: 37315 | R16: 37346 | S16: 37376 | T16: 37407 | U16: 37437 | V16: 37468 | W16: 37499 | X16: 37529 | Y16: 37560 | Z16: 37590 | AA16: 37621 | AB16: 37652 | AC16: 37680 | AD16: 37711 | AE16: 37741 | AF16: 37772 | AG16: 37802 | AH16: 37833 | AI16: 37864 | AJ16: 37894 | AK16: 37925 | AL16: 37955 | AM16: 37986 | AN16: 38017 | AO16: 38046 | AP16: 38077 | AQ16: 38107 | AR16: 38138 | AS16: 38168 | AT16: 38199 | AU16: 38230 | AV16: 38260 | AW16: 38291 | AX16: 38321 | AY16: 38352 | AZ16: 38383 | BA16: 38411 | BB16: 38442 | BC16: 38472 | BD16: 38503 | BE16: 38533 | BF16: 38564 | BG16: 38595 | BH16: 38625 | BI16: 38656 | BJ16: 38686 | BK16: 38717 | BL16: 38748 | BM16: 38776 | BN16: 38807 | BO16: 38837 | BP16: 38868 | BQ16: 38898 | BR16: 38929 | BS16: 38960 | BT16: 38990 | BU16: 39021 | BV16: 39051 | BW16: 39082 | BX16: 39113 | BY16: 39141 | BZ16: 39172 | CA16: 39202 | CB16: 39233 | CC16: 39263 | CD16: 39294 | CE16: 39325 | CF16: 39355 | CG16: 39386 | CH16: 39416 | CI16: 39447 | CJ16: 39478 | CK16: 39507 | CL16: 39538 | CM16: 39568 | CN16: 39599 | CO16: 39629 | CP16: 39660 | CQ16: 39691 | CR16: 39721 | CS16: 39752 | CT16: 39782 | CU16: 39813 | CV16: 39844 | CW16: 39872 | CX16: 39903 | CY16: 39933 | CZ16: 39964 | DA16: 39994 | DB16: 40025 | DC16: 40056 | DD16: 40086 | DE16: 40117 | DF16: 40147 | DG16: 40178 | DH16: 40209 | DI16: 40237 | DJ16: 40268 | DK16: 40298 | DL16: 40329 | DM16: 40359 | DN16: 40390 | DO16: 40421 | DP16: 40451 | DQ16: 40482 | DR16: 40512 | DS16: 40543 | DT16: 40574 | DU16: 40602 | DV16: 40633 | DW16: 40663 | DX16: 40694 | DY16: 40724 | DZ16: 40755 | EA16: 40786 | EB16: 40816 | EC16: 40847 | ED16: 40877 | EE16: 40908 | EF16: 40939 | EG16: 40968 | EH16: 40999 | EI16: 41029 | EJ16: 41060 | EK16: 41090 | EL16: 41121 | EM16: 41152 | EN16: 41182 | EO16: 41213 | EP16: 41243 | EQ16: 41274 | ER16: 41305 | ES16: 41333 | ET16: 41364 | EU16: 41394 | EV16: 41425 | EW16: 41455 | EX16: 41486 | EY16: 41517 | EZ16: 41547 | FA16: 41578 | FB16: 41608 | FC16: 41639 | FD16: 41670 | FE16: 41698 | FF16: 41729 | FG16: 41759 | FH16: 41790 | FI16: 41820 | FJ16: 41851 | FK16: 41882 | FL16: 41912 | FM16: 41943 | FN16: 41973 | FO16: 42004 | FP16: 42035 | FQ16: 42063 | FR16: 42094 | FS16: 42124 | FT16: 42155 | FU16: 42185 | FV16: 42216 | FW16: 42247 | FX16: 42277 | FY16: 42308 | FZ16: 42338 | GA16: 42369 | GB16: 42400 | GC16: 42429 | GD16: 42460 | GE16: 42490 | GF16: 42521 | GG16: 42551 | GH16: 42582 | GI16: 42613 | GJ16: 42643 | GK16: 42674 | GL16: 42704 | GM16: 42735 | GN16: 42766 | GO16: 42794 | GP16: 42825 | GQ16: 42855 | GR16: 42886 | GS16: 42916 | GT16: 42947 | GU16: 42978 | GV16: 43008 | GW16: 43039 | GX16: 43069 | GY16: 43100 | GZ16: 43131 | HA16: 43159 | HB16: 43190 | HC16: 43220 | HD16: 43251 | HE16: 43281 | HF16: 43312 | HG16: 43343 | HH16: 43373 | HI16: 43404 | HJ16: 43434 | HK16: 43465 | HL16: 43496 | HM16: 43524 | HN16: 43555 | HO16: 43585 | HP16: 43616 | HQ16: 43646 | HR16: 43677 | HS16: 43708 | HT16: 43738 | HU16: 43769 | HV16: 43799 | HW16: 43830 | HX16: 43861 | HY16: 43890 | HZ16: 43921 | IA16: 43951 | IB16: 43982 | IC16: 44012 | ID16: 44043 | IE16: 44074 | IF16: 44104 | IG16: 44135 | IH16: 44165 | II16: 44196 | IJ16: 44227 | IK16: 44255 | IL16: 44286 | IM16: 44316 | IN16: 44347 | IO16: 44377 | IP16: 44408 | IQ16: 44439 | IR16: 44469 | IS16: 44500 | IT16: 44530 | IU16: 44561 | IV16: 44592 | IW16: 44620 | IX16: 44651 | IY16: 44681 | IZ16: 44712 | JA16: 44742 | JB16: 44773 | JC16: 44804 | JD16: 44834 | JE16: 44865 | JF16: 44895 | JG16: 44926 | JH16: 44957 | JI16: 44985 | JJ16: 45016 | JK16: 45046 | JL16: 45077 | JM16: 45107 | JN16: 45138 | JO16: 45169 | JP16: 45199 | JQ16: 45230 | JR16: 45260 | JS16: 45291 | JT16: 45322 | JU16: 45351 | JV16: 45382 | JW16: 45412 | JX16: 45443 | JY16: 45473 | JZ16: 45504 | KA16: 45535 | KB16: 45565 | KC16: 45596 | KD16: 45626 | KE16: 45657 | KF16: 45688 | KG16: 45716 | KH16: 45747 | KI16: 45777 | KJ16: 45808 | KK16: 45838 | KL16: 45869 | KM16: 45900 | KN16: 45930 | KO16: 45961 | KP16: 45991 | KQ16: 46022 | KR16: 46053 | KS16: 46081 | KT16: 46112 | KU16: 46142 | KV16: 46173 | KW16: 46203 | KX16: 46234 | KY16: 46265 | KZ16: 46295 | LA16: 46326 | LB16: 46356 | LC16: 46387 | LD16: 46418 | LE16: 46446 | LF16: 46477 | LG16: 46507 | LH16: 46538 | LI16: 46568 | LJ16: 46599 | LK16: 46630 | LL16: 46660 | LM16: 46691 | LN16: 46721 | LO16: 46752 | LP16: 46783 | LQ16: 46812 | LR16: 46843 | LS16: 46873 | LT16: 46904 | LU16: 46934 | LV16: 46965 | LW16: 46996 | LX16: 47026 | LY16: 47057 | LZ16: 47087 | MA16: 47118 | MB16: 47149 | MC16: 47177 | MD16: 47208 | ME16: 47238 | MF16: 47269 | MG16: 47299 | MH16: 47330 | MI16: 47361 | MJ16: 47391 | MK16: 47422 | ML16: 47452 | MM16: 47483 | MN16: 47514 | MO16: 47542 | MP16: 47573 | MQ16: 47603 | MR16: 47634 | MS16: 47664 | MT16: 47695 | MU16: 47726 | MV16: 47756 | MW16: 47787 | MX16: 47817 | MY16: 47848 | MZ16: 47879 | NA16: 47907 | NB16: 47938 | NC16: 47968 | ND16: 47999 | NE16: 48029 | NF16: 48060 | NG16: 48091 | NH16: 48121 | NI16: 48152 | NJ16: 48182 | NK16: 48213 | NL16: 48244 | NM16: 48273 | NN16: 48304 | NO16: 48334 | NP16: 48365 | NQ16: 48395 | NR16: 48426 | NS16: 48457 | NT16: 48487 | NU16: 48518 | NV16: 48548 | NW16: 48579 | NX16: 48610 | NY16: 48638 | NZ16: 48669 | OA16: 48699 | OB16: 48730 | OC16: 48760 | OD16: 48791 | OE16: 48822 | OF16: 48852 | OG16: 48883 | OH16: 48913 | OI16: 48944
A17: Tipo de cambio $/USD promedio mensual | D17: 1 | E17: 1 | F17: 1 | G17: 1 | H17: 1 | I17: 1 | J17: 1 | K17: 1 | L17: 1 | M17: 1 | N17: 1 | O17: 1 | P17: 2.3988556 | Q17: 2.3988556 | R17: 2.3994444 | S17: 2.855 | T17: 3.3295455 | U17: 3.6221053 | V17: 3.6081818 | W17: 3.6214286 | X17: 3.6433333 | Y17: 3.6518182 | Z17: 3.5255 | AA17: 3.4909524 | AB17: 3.2568182 | AC17: 3.1625 | AD17: 3.075 | AE17: 2.895 | AF17: 2.8357143 | AG17: 2.8095 | AH17: 2.8022727 | AI17: 2.9285 | AJ17: 2.9213636 | AK17: 2.8586364 | AL17: 2.8847368 | AM17: 2.9604762 | AN17: 2.8933333 | AO17: 2.9315 | AP17: 2.8978261 | AQ17: 2.8357895 | AR17: 2.9185 | AS17: 2.9595238 | AT17: 2.9552381 | AU17: 3.0138095 | AV17: 2.9945455 | AW17: 2.9695 | AX17: 2.9545455 | AY17: 2.9709091 | AZ17: 2.9471429 | BA17: 2.9165 | BB17: 2.9266667 | BC17: 2.8995238 | BD17: 2.8928571 | BE17: 2.8833333 | BF17: 2.8685714 | BG17: 2.8881818 | BH17: 2.9113636 | BI17: 2.967 | BJ17: 2.9668182 | BK17: 3.015 | BL17: 3.0459091 | BM17: 3.0695 | BN17: 3.0763636 | BO17: 3.0661111 | BP17: 3.0542857 | BQ17: 3.0814286 | BR17: 3.0819048 | BS17: 3.0795455 | BT17: 3.1 | BU17: 3.0990476 | BV17: 3.0761905 | BW17: 3.0615789 | BX17: 3.0854545 | BY17: 3.1005 | BZ17: 3.1009091 | CA17: 3.0894444 | CB17: 3.0795238 | CC17: 3.0785 | CD17: 3.1109524 | CE17: 3.1522727 | CF17: 3.1475 | CG17: 3.1604545 | CH17: 3.1352381 | CI17: 3.1388889 | CJ17: 3.145 | CK17: 3.157619 | CL17: 3.1555556 | CM17: 3.1657143 | CN17: 3.1509524 | CO17: 3.042 | CP17: 3.0227273 | CQ17: 3.034 | CR17: 3.0822727 | CS17: 3.2390909 | CT17: 3.33 | CU17: 3.4228571 | CV17: 3.4638095 | CW17: 3.5125 | CX17: 3.6538095 | CY17: 3.6936842 | CZ17: 3.7247368 | DA17: 3.7690476 | DB17: 3.8104762 | DC17: 3.839 | DD17: 3.8427273 | DE17: 3.8252381 | DF17: 3.8115 | DG17: 3.807619 | DH17: 3.805 | DI17: 3.851 | DJ17: 3.8622727 | DK17: 3.876 | DL17: 3.9036842 | DM17: 3.9271429 | DN17: 3.9342857 | DO17: 3.9361905 | DP17: 3.9527273 | DQ17: 3.9584211 | DR17: 3.9671429 | DS17: 3.978 | DT17: 3.9809524 | DU17: 4.0215 | DV17: 4.0368421 | DW17: 4.0647368 | DX17: 4.0847619 | DY17: 4.0947619 | DZ17: 4.127619 | EA17: 4.1690909 | EB17: 4.2027273 | EC17: 4.222 | ED17: 4.26 | EE17: 4.2878947 | EF17: 4.3209524 | EG17: 4.3472222 | EH17: 4.3568182 | EI17: 4.3970588 | EJ17: 4.45 | EK17: 4.499 | EL17: 4.5528571 | EM17: 4.61 | EN17: 4.6684211 | EO17: 4.7295455 | EP17: 4.797 | EQ17: 4.8789474 | ER17: 4.9490476 | ES17: 5.0105882 | ET17: 5.0847368 | EU17: 5.156 | EV17: 5.24 | EW17: 5.3311111 | EX17: 5.4404545 | EY17: 5.5814286 | EZ17: 5.7361905 | FA17: 5.8472727 | FB17: 6.0142105 | FC17: 6.3194737 | FD17: 7.0977273 | FE17: 7.856 | FF17: 7.9316667 | FG17: 8 | FH17: 8.0425 | FI17: 8.1245 | FJ17: 8.16 | FK17: 8.3155 | FL17: 8.4181818 | FM17: 8.4804545 | FN17: 8.5138889 | FO17: 8.5478947 | FP17: 8.602381 | FQ17: 8.6855556 | FR17: 8.779 | FS17: 8.8655 | FT17: 8.9484211 | FU17: 9.0422727 | FV17: 9.1422727 | FW17: 9.2435 | FX17: 9.365 | FY17: 9.49 | FZ17: 9.6268421 | GA17: 11.4295 | GB17: 13.6555 | GC17: 14.814211 | GD17: 14.962381 | GE17: 14.409524 | GF17: 14.136667 | GG17: 14.141 | GH17: 14.91 | GI17: 14.849545 | GJ17: 15.101818 | GK17: 15.181 | GL17: 15.34 | GM17: 15.829 | GN17: 15.906364 | GO17: 15.599444 | GP17: 15.525 | GQ17: 15.359444 | GR17: 15.698571 | GS17: 16.117143 | GT17: 17.168571 | GU17: 17.415909 | GV17: 17.247619 | GW17: 17.452857 | GX17: 17.492 | GY17: 17.700526 | GZ17: 19.029545 | HA17: 19.841667 | HB17: 20.237 | HC17: 20.235263 | HD17: 23.67 | HE17: 26.534 | HF17: 27.625238 | HG17: 30.125 | HH17: 38.5905 | HI17: 37.120455 | HJ17: 36.460526 | HK17: 37.885556 | HL17: 37.407727 | HM17: 38.41 | HN17: 41.363158 | HO17: 43.232632 | HP17: 44.934091 | HQ17: 43.79 | HR17: 42.545238 | HS17: 52.727619 | HT17: 56.501905 | HU17: 58.530455 | HV17: 59.738421 | HW17: 59.883158 | HX17: 60.011364 | HY17: 61.347778 | HZ17: 63.123684 | IA17: 65.7645 | IB17: 67.730526 | IC17: 69.545714 | ID17: 71.479524 | IE17: 73.298 | IF17: 75.203636 | IG17: 77.570476 | IH17: 79.933684 | II17: 82.640556 | IJ17: 85.9725 | IK17: 88.677778 | IL17: 91.068636 | IM17: 92.8675 | IN17: 94.109474 | IO17: 95.257143 | IP17: 96.241429 | IQ17: 97.215238 | IR17: 98.285909 | IS17: 99.251053 | IT17: 100.31095 | IU17: 101.89 | IV17: 103.98476 | IW17: 106.30947 | IX17: 109.45952 | IY17: 113.33526 | IZ17: 117.7755 | JA17: 122.7385 | JB17: 128.44524 | JC17: 135.29091 | JD17: 143.62714 | JE17: 152.59421 | JF17: 162.12 | JG17: 172.9 | JH17: 182.24455 | JI17: 191.89222 | JJ17: 203.10636 | JK17: 216.55778 | JL17: 231.1915 | JM17: 248.762 | JN17: 266.46524 | JO17: 322.13591 | JP17: 349.99952 | JQ17: 350.0245 | JR17: 353.844 | JS17: 641.99789 | JT17: 818.3455 | JU17: 834.914 | JV17: 850.3377 | JW17: 868.9583 | JX17: 886.8636 | JY17: 903.7794 | JZ17: 923.7652 | KA17: 942.9204 | KB17: 961.8254 | KC17: 981.5682 | KD17: 1001.8377 | KE17: 1020.7061 | KF17: 1043.5644 | KG17: 1058.4625 | KH17: 1069.0347 | KI17: 1121.568 | KJ17: 1147.5292 | KK17: 1181.3553 | KL17: 1267.0227 | KM17: 1329.5375 | KN17: 1399.8977 | KO17: 1432.0227 | KP17: 1427.6176 | KQ17: 1447.8377
